Workbook
Name \0: #REF!
Name \0: #REF!
Name \0: #REF!
Name \0: #REF!
Name \G: #REF!
Name \G: #REF!
Name \G: #REF!
Name \G: #REF!
Name \G: #REF!
Name \G: #REF!
Name \M: #REF!
Name \M: #REF!
Name \M: #REF!
Name \M: #REF!
Name \Q: #REF!
Name \Q: #REF!
Name \Q: #REF!
Name \Q: #REF!
Name \Z: #REF!
Name \Z: #REF!
Name \Z: #REF!
Name ________ADJ81: #REF!
Name ________CEP1: #REF!
Name ________CEP2: #REF!
Name ________DAT1: #REF!
Name ________DAT10: #REF!
Name ________DAT11: #REF!
Name ________DAT12: #REF!
Name ________DAT13: #REF!
Name ________DAT14: #REF!
Name ________DAT15: #REF!
Name ________DAT16: #REF!
Name ________DAT17: #REF!
Name ________DAT18: #REF!
Name ________DAT19: #REF!
Name ________DAT2: #REF!
Name ________DAT20: #REF!
Name ________DAT21: #REF!
Name ________DAT22: #REF!
Name ________DAT23: #REF!
Name ________DAT24: #REF!
Name ________DAT25: #REF!
Name ________DAT26: #REF!
Name ________DAT27: #REF!
Name ________DAT28: #REF!
Name ________DAT29: #REF!
Name ________DAT3: #REF!
Name ________DAT30: #REF!
Name ________DAT31: #REF!
Name ________DAT32: #REF!
Name ________DAT33: #REF!
Name ________DAT34: #REF!
Name ________DAT35: #REF!
Name ________DAT36: #REF!
Name ________DAT37: #REF!
Name ________DAT38: #REF!
Name ________DAT39: #REF!
Name ________DAT4: #REF!
Name ________DAT40: #REF!
Name ________DAT41: #REF!

Sheet HC
B1: 43374 | C1: 43405 | D1: 43435 | E1: 43466 | F1: 43497 | G1: 43525 | H1: 43556 | I1: 43586 | J1: 43617 | K1: 43647 | L1: 43678 | M1: 43709 | N1: 43739 | O1: 43770 | P1: 43800 | Q1: 43831 | R1: 43862 | S1: 43891 | T1: 43922 | U1: 43952 | V1: 43983 | W1: 44043 | X1: 44074 | Y1: 44104 | Z1: 44135 | AA1: 44165 | AB1: 44196 | AC1: 44227 | AD1: 44255 | AE1: 44286 | AF1: 44316 | AG1: 44347 | AH1: Jun-2021 | AI1: Jul-2021 | AJ1: Aug-2021 | AK1: Sep-2021 | AL1: Oct-2021 | AM1: 44501 | AN1: 44531 | AO1: 44562 | AP1: 44593 | AQ1: 44621 | AR1: 44652 | AS1: 44682 | AT1: 44713 | AU1: 44743 | AV1: 44774 | AW1: 44805 | AX1: 44835 | AY1: 44866 | AZ1: 44896 | BA1: 44927 | BB1: 44958 | BC1: 44986 | BD1: 45017 | BE1: 45047 | BF1: 45078 | BG1: 45108 | BH1: 45139 | BI1: 45170 | BJ1: 45200 | BK1: 45231 | BL1: 45261 | BM1: 45292 | BN1: 45323 | BO1: 45352 | BP1: 45383 | BQ1: 45413 | BR1: 45444 | BS1: 45474 | BT1: 45505 | BU1: 45536 | BV1: 45566 | BW1: 45597 | BX1: 45627 | BY1: 45658 | BZ1: 45689 | CA1: 45717 | CB1: 45748 | CC1: 45778 | CD1: 45809 | CE1: 45839 | CF1: 45870 | CG1: 45901 | CH1: 45931 | CI1: 45962 | CJ1: 45992 | CK1: 46023 | CL1: 46054 | CM1: 46082 | CN1: 46113 | CO1: 46143 | CP1: 46174
A2: Current 3P Op | B2: 316 | C2: 271 | D2: 263 | E2: 224 | F2: 223 | G2: 221 | H2: 246 | I2: 262 | J2: 263 | K2: 265 | L2: 296 | M2: 268 | N2: 248 | O2: =N10 -> 242 | P2: =O10 -> 235 | Q2: =P10 -> 195 | R2: =Q10 -> 169 | S2: =R10 -> 148 | T2: =S10 -> 194 | U2: =T10 -> 195 | V2: =U10 -> 166 | ... CP2: =CO10 -> 349
A3: New hire | B3: 2 | D3: 0 | E3: 0 | F3: 8 | G3: 46 | H3: 31 | I3: 23 | J3: 15 | K3: 63 | L3: 0 | M3: 1 | N3: 1 | O3: 0 | P3: 0 | Q3: 0 | R3: 0 | S3: =62+17 -> 79 | T3: =11+6 -> 17 | U3: 0 | V3: 0 | W3: 0 | X3: 0 | Y3: 1 | Z3: =25 -> 25 | AA3: 76 | AB3: =13+34 -> 47 | AC3: =5+13 -> 18 | AD3: 16 | AE3: =73+32 -> 105 | AF3: =27+5 -> 32 | AG3: =49+19 -> 68 | AH3: 6 | AI3: 18 | AK3: 21 | AL3: 20 | AM3: 69 | AN3: 23 | AO3: 0 | AP3: 1 | AQ3: 58 | AR3: 1 | AS3: 18 | AT3: 19 | AU3: 0 | AV3: 29 | AW3: 0 | AX3: 0 | AY3: 0 | AZ3: 0 | BA3: 0 | BB3: 20 | BC3: 0 | BD3: 0 | BE3: 0 | BF3: 0 | BG3: 0 | BH3: 0 | BI3: 2 | BJ3: 0 | BK3: 0 | BL3: 1 | BM3: 31 | BN3: =49+5 -> 54 | BO3: 40 | BP3: 31 | BQ3: 115 | BR3: 1 | BS3: 20 | BT3: 1 | BU3: 0 | BV3: 0 | BW3: 0 | BX3: 1 | BY3: 0 | BZ3: 20 | CA3: 58 | CB3: 17 | CC3: 28 | CD3: 36 | CE3: 1 | CF3: 0 | CG3: 2 | CH3: 71 | CI3: 105 | CJ3: 30 | CK3: 28 | CL3: 0 | CM3: 147 | CN3: 96 | CO3: 97 | CP3: 106
A4: 3P Op | B4: 318 | C4: 269 | D4: 263 | E4: 224 | F4: 231 | G4: 267 | H4: 277 | I4: 285 | J4: 278 | K4: 328 | L4: 296 | M4: =M2+M3 -> 269 | N4: =N2+N3 -> 249 | O4: =O2+O3 -> 242 | P4: =P2+P3 -> 235 | Q4: =Q2+Q3 -> 195 | R4: =R2+R3 -> 169 | S4: =S2+S3 -> 227 | T4: =T2+T3 -> 211 | ... CP4: =CP2+CP3 -> 455
A5: TO | B5: 39 | C5: 45 | D5: 36 | E5: 45 | F5: 44 | G5: 45 | H5: 40 | I5: 45 | J5: 46 | K5: 49 | L5: 46 | M5: 32 | N5: 44 | O5: 34 | P5: 38 | Q5: 21 | R5: 0 | S5: 0 | T5: 0 | U5: 0 | V5: 0 | W5: 0 | X5: 0 | Y5: 0 | Z5: 0 | AA5: 0 | AB5: 0 | AC5: 0 | AD5: 0 | AE5: 0 | AF5: 0 | AG5: 0 | AH5: 0 | AI5: 0 | AJ5: 0 | AK5: 0 | AL5: 0 | AM5: 0 | AN5: 0 | AO5: 0 | AP5: 0 | AQ5: 0 | AR5: 0 | AS5: 0 | AT5: 0 | AU5: 0 | AV5: 0 | AW5: 0 | AX5: 0 | AY5: 0 | AZ5: 0 | BA5: 0 | BB5: 0 | BC5: 0 | BD5: 0 | BE5: 0 | BF5: 0 | BG5: 0 | BH5: 0 | BI5: 0 | BJ5: 0 | BK5: 0 | BL5: 0 | BM5: 0 | BN5: 0 | BO5: 0 | BP5: 0 | BQ5: 0 | BR5: 0 | BS5: 0 | BT5: 0 | BU5: 0 | BV5: 0 | BW5: 0 | BX5: 0 | BY5: 0 | BZ5: 0 | CA5: 0 | CB5: 0 | CC5: 0 | CD5: 0 | CE5: 0 | CF5: 0 | CG5: 0 | CH5: 0 | CI5: 0 | CJ5: 0 | CK5: 0 | CL5: 0 | CM5: 0 | CN5: 0 | CO5: 0 | CP5: 0
A6: SC | B6: 16 | C6: 0 | D6: 0 | E6: 0 | F6: 0 | H6: 0 | I6: 0 | K6: 0
A7: Out of payroll | B7: 0 | C7: 7 | D7: 0 | E7: 32 | F7: 0 | G7: 1 | H7: 1 | K7: 0 | AC7: 1 | AF7: 1 | AH7: 2 | AI7: 1 | AK7: 2 | AL7: 0 | AM7: 0 | AN7: 12 | AO7: 0 | AP7: 0 | AQ7: 0 | AR7: 0 | AS7: 0 | AT7: 0 | AU7: 1 | AV7: 1 | AW7: 0 | AX7: 0 | AY7: 0 | AZ7: 0 | BA7: 0 | BB7: 0 | BC7: 0 | BD7: 0 | BE7: 0 | BF7: 0 | BG7: 0 | BH7: 0 | BI7: 0 | BJ7: 0 | BK7: 0 | BL7: 0 | BM7: 0 | BN7: 1 | BO7: 0 | BP7: 0 | BQ7: 0 | BR7: 0 | BS7: 0 | BT7: 0 | BU7: 0 | BV7: 0 | BW7: 0 | BX7: 0 | BY7: 0 | BZ7: 0 | CA7: 0 | CB7: 0 | CC7: 0 | CD7: 0 | CE7: 0 | CF7: 0 | CG7: 0 | CH7: 0 | CI7: 0 | CJ7: 0 | CK7: 0 | CL7: 0 | CM7: 0 | CN7: 0 | CO7: 0 | CP7: 0
A8: Total payroll | B8: 373 | C8: 321 | D8: 299 | E8: 301 | F8: 275 | G8: 313 | H8: 318 | I8: 330 | J8: 324 | K8: 377 | L8: 342 | M8: =M4+M5 -> 301 | N8: =N4+N5 -> 293 | O8: =O4+O5 -> 276 | P8: =P4+P5 -> 273 | Q8: =Q4+Q5 -> 216 | R8: =R4+R5 -> 169 | S8: =S4+S5 -> 227 | T8: =T4+T5 -> 211 | ... AB8: =AB4+AB5 -> 239 | AC8: =AC4+AC5+AC7 -> 235 | AD8: =AD4+AD5+AD7 -> 224 | AE8: =AE4+AE5+AE7 -> 305 | AF8: =AF4+AF5+AF7 -> 287 | AG8: =AG4+AG5+AG7 -> 323 | AH8: =AH4+AH5+AH7 -> 289 | AI8: =AI4+AI5+AI7 -> 289 | AJ8: =AJ4+AJ5+AJ7 -> 273 | ... CP8: =CP4+CP5+CP7 -> 455
A9: Termination | B9: 47 | C9: 6 | D9: 39 | E9: 1 | F9: 10 | G9: 21 | H9: 15 | I9: 22 | J9: 13 | K9: 32 | L9: 28 | M9: 21 | N9: 7 | O9: 7 | P9: 40 | Q9: 26 | R9: 21 | S9: =17+16 -> 33 | T9: 16 | U9: =17+11+1 -> 29 | V9: 27 | W9: =8+1 -> 9 | X9: 6 | Y9: 7 | Z9: =2+3 -> 5 | AA9: 22 | AB9: =23 -> 23 | AC9: 26 | AD9: 24 | AE9: 51 | AF9: 31 | AG9: =30+11+1 -> 42 | AH9: 17 | AI9: 15 | AJ9: 57 | AK9: 4 | AL9: 17 | AM9: 15 | AN9: 19 | AO9: 12 | AP9: 29 | AQ9: 16 | AR9: =14+18 -> 32 | AS9: 12 | AT9: 15 | AU9: 11 | AV9: 9 | AW9: 6 | AX9: 11 | AY9: 7 | AZ9: 2 | BA9: 7 | BB9: 10 | BC9: 9 | BD9: 32 | BE9: 2 | BF9: 39 | BG9: 5 | BH9: 2 | BI9: 6 | BJ9: 62 | BK9: 49 | BL9: 1 | BM9: 2 | BN9: 10 | BO9: 8 | BP9: 9 | BQ9: 34 | BR9: 12 | BS9: 12 | BT9: 20 | BU9: 11 | BV9: 10 | BW9: 4 | BX9: 4 | BY9: 3 | BZ9: 13 | CA9: 23 | CB9: 13 | CC9: 25 | CD9: 23 | CE9: 10 | CF9: 12 | CG9: 17 | CH9: 18 | CI9: 67 | CJ9: 36 | CK9: 22 | CL9: 25 | CM9: 192 | CN9: 51 | CO9: 52 | CP9: 90
A10: T3 OP- presence | B10: 271 | C10: 263 | D10: 224 | E10: 223 | F10: 221 | G10: 246 | H10: 262 | I10: 263 | J10: 265 | K10: 296 | L10: 268 | M10: =M4-M9 -> 248 | N10: =N4-N9 -> 242 | O10: =O4-O9 -> 235 | P10: =P4-P9 -> 195 | Q10: =Q4-Q9 -> 169 | R10: =R4-R9 -> 148 | S10: =S4-S9 -> 194 | T10: =T4-T9 -> 195 | ... CP10: =CP4-CP9 -> 365
A12: Termination
A13: Voluntary | P13: 8 | Q13: 7 | R13: 21 | S13: 21 | T13: 14 | U13: =17+1 -> 18 | V13: 17 | W13: 9 | X13: 5 | Y13: 7 | Z13: 2 | AA13: 11 | AB13: 16
A14: Redundancy/not following the rule/not get performance | P14: 32 | Q14: 19 | R14: 0 | S14: 5 | T14: 0 | U14: 0 | V14: 10 | W14: 0 | X14: 0 | Y14: 0 | Z14: 0 | AA14: 0 | AB14: 4
A15: Not taking a job | P15: 0 | Q15: 0 | R15: 0 | S15: 6 | T15: 2 | U15: 0 | V15: 0 | W15: 0 | X15: 0 | Y15: 0 | Z15: 3 | AA15: 5 | AB15: 2
A16: to be regular | P16: 0 | Q16: 0 | R16: 0 | S16: 1 | T16: 0 | U16: 11 | V16: 0 | W16: 0 | X16: 1 | Y16: 0 | Z16: 0 | AA16: 6 | AB16: 1

Sheet Compare
B1: 44166 | C1: 44197 | D1: 44228 | E1: 44256 | F1: 44287 | G1: 44317 | H1: 44377 | I1: 44407 | J1: 44439 | K1: 44469 | L1: 44490 | M1: 44501 | N1: 44531 | O1: 44562 | P1: 44593 | Q1: 44621 | R1: 44652 | S1: 44682 | T1: 44713 | U1: 44743 | V1: 44774 | W1: 44805 | X1: 44835 | Y1: 44866 | Z1: 44896 | AA1: 44927 | AB1: 44958 | AC1: 44986 | AD1: 45017 | AE1: 45047 | AF1: 45078 | AG1: 45108 | AH1: 45139 | AI1: 45170 | AJ1: 45200 | AK1: 45231 | AL1: 45261 | AM1: 45292 | AN1: 45323 | AO1: 45352 | AP1: 45383 | AQ1: 45413 | AR1: 45444 | AS1: 45474 | AT1: 45505 | AU1: 45536 | AV1: 45566 | AW1: 45597 | AX1: 45627 | AY1: 45658 | AZ1: 45689 | BA1: 45717 | BB1: 45748 | BC1: 45778 | BD1: 45809 | BE1: 45839 | BF1: 45870 | BG1: 45901 | BH1: 45931 | BI1: 45962 | BJ1: 45992 | BK1: 46023 | BL1: 46054 | BM1: 46082 | BN1: 46113 | BO1: 46143 | BP1: 46174 | BQ1: May26 vs Apr26 | BR1: Unit
A2: (1) | B2: (2) | C2: (3) | D2: (4) | E2: (5) | F2: (6) | G2: (7) | H2: (8) | I2: (9) | J2: (10) | K2: (11) | L2: -12 | M2: -13 | N2: -14 | O2: -15 | P2: -16 | Q2: -17 | R2: -18 | S2: -19 | T2: -20 | U2: -21 | V2: -22 | W2: -23 | X2: -24 | Y2: -24 | Z2: -25 | AA2: -26 | AB2: -27 | AC2: -28 | AD2: -29 | AE2: -30 | AF2: -31 | AG2: -32 | AH2: (33) | AI2: (34) | AJ2: (35) | AK2: (36) | AL2: (37) | AM2: -38 | AN2: -39 | AO2: -40 | AP2: -41 | AQ2: -42 | AR2: -43 | AS2: -44 | AT2: -45 | AU2: -46 | AV2: -47 | AW2: -48 | AX2: -49 | AY2: -50 | AZ2: -51 | BA2: -52 | BB2: -53 | BC2: -54 | BD2: -55 | BE2: -56 | BF2: -57 | BG2: -58 | BH2: -59 | BI2: -60 | BJ2: -61 | BK2: -62 | BL2: -63 | BM2: -64 | BN2: -65 | BO2: -66 | BP2: -67 | BQ2: -68
A3: Số giờ làm việc được trả lương | B3: 42711.633 | C3: 43496.098 | D3: 38581.067 | E3: 48746.415 | F3: 51792.765 | G3: 55357.452 | H3: 54107.166 | I3: 49944.281 | J3: 42943.95 | K3: 44657.65 | L3: 48290.785 | M3: 54986.217 | N3: 58522.584 | O3: 55167.552 | P3: 52138.433 | Q3: 55812.551 | R3: 56310.999 | S3: 50359.032 | T3: 53953.583 | U3: 52461.45 | V3: 53346.583 | W3: 55725.817 | X3: 53955.313 | Y3: 52606.134 | Z3: 51076.8 | AA3: 47675.287 | AB3: 51045.25 | AC3: 51014.083 | AD3: 48540.166 | AE3: 44318.75 | AF3: 42273.233 | AG3: 35510.733 | AH3: 35194 | AI3: 34710.483 | AJ3: 28310.967 | AK3: 14964 | AL3: 11587.5 | AM3: 11348.297 | AN3: 18422.384 | AO3: 29485.667 | AP3: 36755.483 | AQ3: 47498.766 | AR3: 52713.234 | AS3: 49896.383 | AT3: 51872.383 | AU3: 47560.083 | AV3: 45231.25 | AW3: 44670.5 | AX3: 43931.666 | AY3: 40126.683 | AZ3: 41032.75 | BA3: 48352.734 | BB3: 51299.517 | BC3: 54490.8 | BD3: 54305.383 | BE3: 53526.017 | BF3: 52004.35 | BG3: 49211.133 | BH3: 53378.151 | BI3: 60089.1 | BJ3: 66625.15 | BK3: 63092.484 | BL3: 58167.35 | BM3: 67432.967 | BN3: 55987.95 | BO3: 64159.116 | BP3: 70177.715 | BQ3: =BP3-BO3 -> 6018.599 | BR3: hours | BW3: =BQ3/BO3 -> 0.093807387
A4: Overtime 150% (hour) | B4: 15 | C4: 11.5 | D4: 9 | E4: 27.5 | F4: 26 | G4: 16 | H4: 33 | I4: 1.5 | J4: 0 | K4: 0 | L4: 11.5 | M4: 7 | N4: 24 | O4: 16.5 | P4: 28 | Q4: 123.5 | R4: 222.5 | S4: 148 | T4: 165.5 | U4: 87.5 | V4: 297 | W4: 262 | X4: 116.5 | Y4: 166.5 | Z4: 131 | AA4: 513 | AB4: 102 | AC4: 59 | AD4: 68.5 | AE4: 312 | AF4: 50 | AG4: 0 | AH4: 37.5 | AI4: 48 | AJ4: 0 | AK4: 0 | AL4: 2.5 | AM4: 0 | AN4: 196 | AO4: 5.5 | AP4: 356 | AQ4: 654 | AR4: 37 | AS4: 25 | AT4: 21.5 | AU4: 809.5 | AV4: 12 | AW4: 18.5 | AX4: 23.5 | AY4: 8.5 | AZ4: 3.5 | BA4: 11 | BB4: 597 | BC4: 345.5 | BD4: 15.5 | BE4: 18.5 | BF4: 11 | BG4: 743.5 | BH4: 40.5 | BI4: 28 | BJ4: 214.5 | BK4: 1021.5 | BL4: 5988.75 | BM4: 13775.75 | BN4: 8870.25 | BO4: 9165.5 | BP4: 11557.75 | BQ4: =BP4-BO4 -> 2392.25 | BR4: hours
A5: Overtime 175% (hour) | B5: 10400.5 | C5: 5897.75 | D5: 3601 | E5: 14526.25 | F5: 11776.75 | G5: 14473.25 | H5: 14623 | I5: 3654 | J5: 28 | K5: 27.5 | L5: 3836.75 | M5: 15 | N5: 0 | O5: 0 | P5: 0 | Q5: 0 | R5: 0 | S5: 0 | T5: 0 | U5: 0 | V5: 0 | W5: 0 | X5: 0 | Y5: 0 | Z5: 0 | AA5: 0 | AB5: 0 | AC5: 0 | AD5: 0 | AE5: 0 | AF5: 0 | AG5: 0 | AH5: 0 | AI5: 0 | AJ5: 0 | AK5: 0 | AL5: 0 | AM5: 0 | AN5: 0 | AO5: 0 | AP5: 0 | AQ5: 0 | AR5: 0 | AS5: 0 | AT5: 0 | AU5: 0 | AV5: 0 | AW5: 0 | AX5: 0 | AY5: 0 | AZ5: 0 | BA5: 0 | BB5: 0 | BC5: 0 | BD5: 0 | BE5: 0 | BF5: 0 | BG5: 0 | BH5: 0 | BI5: 0 | BJ5: 0 | BK5: 0 | BL5: 0 | BM5: 0 | BN5: 0 | BO5: 0 | BP5: 0 | BQ5: =BP5-BO5 -> 0 | BR5: hours
A6: Overtime 200% (hour) | B6: 1339.5 | C6: 762 | D6: 1579 | E6: 1700.25 | F6: 1568 | G6: 2089.75 | H6: 2837.25 | I6: 8578 | J6: 13462.25 | K6: 18705.5 | L6: 7636.75 | M6: 11501.75 | N6: 141 | O6: 4877.25 | P6: 9473.75 | Q6: 14569.5 | R6: 9851 | S6: 10905.25 | T6: 12720 | U6: 6181.5 | V6: 10645 | W6: 13430.25 | X6: 11935.5 | Y6: 8090 | Z6: 5842.25 | AA6: 303 | AB6: 11544.25 | AC6: 7326.75 | AD6: 825.5 | AE6: 3042 | AF6: 2624.5 | AG6: 63 | AH6: 707.75 | AI6: 344 | AJ6: 36 | AK6: 40 | AL6: 60 | AM6: 2156.25 | AN6: 5015.5 | AO6: 9212.25 | AP6: 7493 | AQ6: 14013 | AR6: 20007.5 | AS6: 11363.25 | AT6: 8982.75 | AU6: 12837.25 | AV6: 2195.25 | AW6: 2894.25 | AX6: 3808.75 | AY6: 267.75 | AZ6: 6066.75 | BA6: 10411.25 | BB6: 6066.25 | BC6: 7968.75 | BD6: 9878.25 | BE6: 2268.75 | BF6: 3479.5 | BG6: 2793 | BH6: 6301.5 | BI6: 7364 | BJ6: 5114 | BK6: 4127 | BL6: 1299.75 | BM6: 5122 | BN6: 1684.25 | BO6: 1704.5 | BP6: 3387.75 | BQ6: =BP6-BO6 -> 1683.25 | BR6: hours
A7: Overtime 210% (hour) | I7: 1806 | J7: 2195.5 | K7: 4153.5 | L7: 0 | M7: 0 | N7: 10090 | O7: 0 | P7: 0 | Q7: 0 | R7: 0 | S7: 0 | T7: 0 | U7: 0 | V7: 0 | W7: 0 | X7: 0 | Y7: 0 | Z7: 0 | AA7: 0 | AB7: 0 | AC7: 0 | AD7: 0 | AE7: 0 | AF7: 0 | AG7: 0 | AH7: 0 | AI7: 0 | AJ7: 0 | AK7: 0 | AL7: 0 | AM7: 0 | AN7: 0 | AO7: 0 | AP7: 0 | AQ7: 0 | AR7: 0 | AS7: 0 | AT7: 0 | AU7: 0 | AV7: 0 | AW7: 0 | AX7: 0 | AY7: 0 | AZ7: 0 | BA7: 0 | BB7: 0 | BC7: 0 | BD7: 0 | BE7: 0 | BF7: 0 | BG7: 0 | BH7: 0 | BI7: 0 | BJ7: 0 | BK7: 0 | BL7: 0 | BM7: 0 | BN7: 0 | BO7: 0 | BP7: 0 | BQ7: =BP7-BO7 -> 0 | BR7: hours
A8: Overtime 220% (hour) | B8: 0 | C8: 0 | D8: 0 | E8: 2 | F8: 0 | G8: 0 | H8: 1.5 | I8: 0 | J8: 0 | K8: 1 | L8: 0 | M8: 0 | N8: 0 | O8: 0 | P8: 0 | Q8: 0 | R8: 0 | S8: 0 | T8: 0 | U8: 0 | V8: 0 | W8: 1 | X8: 0 | Y8: 0 | Z8: 0 | AA8: 0 | AB8: 0 | AC8: 0 | AD8: 0 | AE8: 0 | AF8: 0 | AG8: 0 | AH8: 0 | AI8: 0 | AJ8: 0 | AK8: 0 | AL8: 0 | AM8: 0 | AN8: 0 | AO8: 0 | AP8: 0 | AQ8: 0 | AR8: 0 | AS8: 0 | AT8: 0 | AU8: 0 | AV8: 0 | AW8: 0 | AX8: 0 | AY8: 0 | AZ8: 0 | BA8: 0 | BB8: 0 | BC8: 0 | BD8: 0 | BE8: 0 | BF8: 0 | BG8: 0 | BH8: 0 | BI8: 0 | BJ8: 0 | BK8: 0 | BL8: 0 | BM8: 0 | BN8: 0 | BO8: 0 | BP8: 0 | BQ8: =BP8-BO8 -> 0 | BR8: hours
A9: Overtime 290% (hour) | B9: 0 | C9: 0 | D9: 0 | E9: 0 | F9: 0 | G9: 80 | H9: 0 | I9: 0 | J9: 0 | K9: 840 | L9: 2823 | M9: 5121 | N9: 0 | O9: 1983.5 | P9: 2479.75 | Q9: 3871.25 | R9: 1464 | S9: 3722 | T9: 2776 | U9: 1512 | V9: 2160 | W9: 2888 | X9: 2728 | Y9: 1744 | Z9: 1496 | AA9: 40 | AB9: 3546.25 | AC9: 1440 | AD9: 80 | AE9: 698 | AF9: 320 | AG9: 0 | AH9: 120 | AI9: 32 | AJ9: 0 | AK9: 8 | AL9: 0 | AM9: 360 | AN9: 536 | AO9: 1656 | AP9: 1232 | AQ9: 3135.75 | AR9: 4536 | AS9: 2736 | AT9: 2176 | AU9: 2736 | AV9: 552 | AW9: 576 | AX9: 800 | AY9: 128 | AZ9: 1184 | BA9: 2704 | BB9: 1672 | BC9: 2128 | BD9: 2696 | BE9: 776 | BF9: 1029.75 | BG9: 728 | BH9: 1929.5 | BI9: 1952 | BJ9: 1544 | BK9: 1431.75 | BL9: 256 | BM9: 1624 | BN9: 400 | BO9: 360 | BP9: 616 | BQ9: =BP9-BO9 -> 256 | BR9: hours
A10: Overtime 300% (hour) | E10: 0 | F10: 0 | G10: 0 | H10: 0 | I10: 0 | J10: 0 | K10: 3163 | L10: 0 | M10: 0 | N10: 4312 | O10: 0 | P10: 0 | Q10: 0 | R10: 0 | S10: 0 | T10: 0 | U10: 0 | V10: 0 | W10: 165 | X10: 0 | Y10: 0 | Z10: 0 | AA10: 0 | AB10: 0 | AC10: 0 | AD10: 0 | AE10: 0 | AF10: 0 | AG10: 0 | AH10: 0 | AI10: 0 | AJ10: 0 | AK10: 0 | AL10: 0 | AM10: 0 | AN10: 0 | AO10: 0 | AP10: 8 | AQ10: 12 | AR10: 0 | AS10: 0 | AT10: 0 | AU10: 0 | AV10: 0 | AW10: 0 | AX10: 0 | AY10: 0 | AZ10: 0 | BA10: 0 | BB10: 0 | BC10: 0 | BD10: 0 | BE10: 0 | BF10: 0 | BG10: 0 | BH10: 0 | BI10: 0 | BJ10: 0 | BK10: 0 | BL10: 219.75 | BM10: 0 | BN10: 0 | BO10: 0 | BP10: 0 | BQ10: =BP10-BO10 -> 0 | BR10: hours
A11: Overtime 410% (hour) | C11: 0 | D11: 0 | E11: 0 | F11: 0 | G11: 0 | H11: 0 | I11: 0 | J11: 0 | K11: 20 | L11: 0 | M11: 0 | N11: 0 | O11: 0 | P11: 0 | Q11: 0 | R11: 0 | S11: 0 | T11: 0 | U11: 0 | V11: 0 | W11: 88 | X11: 0 | Y11: 0 | Z11: 0 | AA11: 0 | AB11: 0 | AC11: 0 | AD11: 0 | AE11: 0 | AF11: 0 | AG11: 0 | AH11: 0 | AI11: 0 | AJ11: 0 | AK11: 0 | AL11: 0 | AM11: 0 | AN11: 0 | AO11: 0 | AP11: 0 | AQ11: 0 | AR11: 0 | AS11: 0 | AT11: 0 | AU11: 0 | AV11: 0 | AW11: 0 | AX11: 0 | AY11: 0 | AZ11: 0 | BA11: 0 | BB11: 0 | BC11: 0 | BD11: 0 | BE11: 0 | BF11: 0 | BG11: 0 | BH11: 0 | BI11: 0 | BJ11: 0 | BK11: 0 | BL11: 120 | BM11: 0 | BN11: 0 | BO11: 0 | BP11: 0 | BQ11: =BP11-BO11 -> 0 | BR11: hours
A12: Overtime 100% (hour) | B12: 0 | C12: 0 | D12: 0 | E12: 36 | F12: 0 | G12: 0 | H12: 0 | I12: 0 | J12: 0 | K12: 0 | L12: 0 | M12: 0 | N12: 0 | O12: 0 | P12: 0 | Q12: 36 | R12: 55.75 | S12: 0 | T12: 0 | U12: 0 | V12: 0 | W12: 0 | X12: 0 | Y12: 0 | Z12: 0 | AA12: 0 | AB12: 0 | AC12: 0 | AD12: 0 | AE12: 0 | AF12: 0 | AG12: 0 | AH12: 0 | AI12: 0 | AJ12: 0 | AK12: 0 | AL12: 0 | AM12: 0 | AN12: 0 | AO12: 0 | AP12: 0 | AQ12: 0 | AR12: 0 | AS12: 28 | AT12: 4 | AU12: 0 | AV12: 0 | AW12: 0 | AX12: 0 | AY12: 0 | AZ12: 0 | BA12: 3.5 | BB12: 0 | BC12: 0 | BD12: 0 | BE12: 0 | BF12: 0 | BG12: 0 | BH12: 0 | BI12: 0 | BJ12: 0 | BK12: 0 | BL12: 0 | BM12: 0 | BN12: 0 | BO12: 0 | BP12: 0 | BQ12: =BP12-BO12 -> 0 | BR12: hours
A13: Night shift (day) | B13: 0 | C13: 0 | D13: 0 | E13: 0 | F13: 0 | G13: 0 | H13: 0 | I13: 0 | J13: 0 | K13: 0 | L13: 1119.0884 | M13: 1710.505 | N13: 1913.9076 | O13: 1516.7451 | P13: 779.9541 | Q13: 1583.9235 | R13: 1107.1927 | S13: 1424.0046 | T13: 1655.4006 | U13: 1382.6038 | V13: 1441.1435 | W13: 1481.6849 | X13: 1525.059 | Y13: 1683.6702 | Z13: 1628.5328 | AA13: 592.25 | AB13: 1357.0827 | AC13: 1652.9312 | AD13: 849.1665 | AE13: 871.0832 | AF13: 1114.4166 | AG13: 724.8733 | AH13: 905.6455 | AI13: 620.5415 | AJ13: 535.354 | AK13: 304.8748 | AL13: 161.3124 | AM13: 180.0249 | AN13: 177 | AO13: 652.9889 | AP13: 679.3762 | AQ13: 1275.2784 | AR13: 1337.5396 | AS13: 1376.8538 | AT13: 1509.0413 | AU13: 1061.8181 | AV13: 1189.9991 | AW13: 1003.7081 | AX13: 1157.7504 | AY13: 605.5371 | AZ13: 769.4581 | BA13: 1258.6248 | BB13: 1127.958 | BC13: 1329.3197 | BD13: 1342.062 | BE13: 1428.7357 | BF13: 1313.3953 | BG13: 941.458 | BH13: 1520.8714 | BI13: 1381.9161 | BJ13: 1951.618 | BK13: 1644.0825 | BL13: 972.2433 | BM13: 2023.9369 | BN13: 1330.2665 | BO13: 2197.2666 | BP13: 2190.3683 | BQ13: =BP13-BO13 -> -6.8983 | BR13: hours
A14: Day Off | B14: 171 | C14: 97 | D14: 379 | E14: 212 | F14: 197 | G14: 271 | H14: 335 | I14: 319 | J14: 275 | K14: 918 | L14: 1251 | M14: 1845 | N14: 1441 | O14: 689 | P14: 1172 | Q14: 1670 | R14: 968 | S14: 1233 | T14: 1369 | U14: 684 | V14: 1136 | W14: 1427 | X14: 1293 | Y14: 867 | Z14: 649 | AA14: 27 | AB14: 1339 | AC14: 782 | AD14: 85 | AE14: 324 | AF14: 262 | AG14: 5 | AH14: 71 | AI14: 34 | AJ14: 3 | AK14: 4 | AL14: 5 | AM14: 214 | AN14: 466 | AO14: 922 | AP14: 734 | AQ14: 1443 | AR14: 2056 | AS14: 1203 | AT14: 949 | AU14: 1310 | AV14: 229 | AW14: 290 | AX14: 386 | AY14: 33 | AZ14: 607 | BA14: 1099 | BB14: 645 | BC14: 860 | BD14: 1053 | BE14: 251 | BF14: 374 | BG14: 301 | BH14: 687 | BI14: 776 | BJ14: 555 | BK14: 462 | BL14: 160 | BM14: 568 | BN14: 175 | BO14: 189 | BP14: 363 | BQ14: =BP14-BO14 -> 174 | BR14: Days
A15: Số giờ làm thêm T.O | B15: 0 | C15: 0 | D15: 0 | E15: 0 | F15: 0 | G15: 0 | H15: 0 | I15: 0 | J15: 0 | K15: 0 | L15: 0 | M15: 0 | N15: 0 | O15: 0 | P15: 0 | Q15: 0 | R15: 0 | S15: 0 | T15: 0 | U15: 0 | V15: 0 | W15: 0 | X15: 0 | Y15: 0 | Z15: 0 | AA15: 0 | AB15: 0 | AC15: 0 | AD15: 0 | AE15: 0 | AF15: 0 | AG15: 0 | AH15: 0 | AI15: 0 | AJ15: 0 | AK15: 0 | AL15: 0 | AM15: 0 | AN15: 0 | AO15: 0 | AP15: 0 | AQ15: 0 | AR15: 0 | AS15: 0 | AT15: 0 | AU15: 0 | AV15: 0 | AW15: 0 | AX15: 0 | AY15: 0 | AZ15: 0 | BA15: 0 | BB15: 0 | BC15: 0 | BD15: 0 | BE15: 0 | BF15: 0 | BG15: 0 | BH15: 0 | BI15: 0 | BJ15: 0 | BK15: 0 | BL15: 0 | BM15: 0 | BN15: 0 | BO15: 0 | BP15: 0 | BQ15: =BP15-BO15 -> 0 | BR15: hours
A16: Lương tháng | B16: 9.9241345e+08 | C16: 1.0466725e+09 | D16: 9.2825516e+08 | E16: 1.1780599e+09 | F16: 1.2619119e+09 | G16: 1.339181e+09 | H16: 1.3166717e+09 | I16: 1.21645e+09 | J16: 1.046748e+09 | K16: 1.0844416e+09 | L16: 1.172016e+09 | M16: 1.3222308e+09 | N16: 1.4167305e+09 | O16: 1.3942185e+09 | P16: 1.3192975e+09 | Q16: 1.4042639e+09 | R16: 1.4304482e+09 | S16: 1.2759876e+09 | T16: 1.367639e+09 | U16: 1.332546e+09 | V16: 1.3480911e+09 | W16: 1.4160722e+09 | X16: 1.3652182e+09 | Y16: 1.3315176e+09 | Z16: 1.2874126e+09 | AA16: 1.2018124e+09 | AB16: 1.280137e+09 | AC16: 1.2851234e+09 | AD16: 1.2231984e+09 | AE16: 1.115305e+09 | AF16: 1.0639364e+09 | AG16: 8.9446909e+08 | AH16: 8.8539902e+08 | AI16: 8.7517543e+08 | AJ16: 7.1600524e+08 | AK16: 3.813173e+08 | AL16: 2.9723345e+08 | AM16: 2.8222722e+08 | AN16: 4.5214836e+08 | AO16: 7.3291089e+08 | AP16: 9.2500821e+08 | AQ16: 1.1698756e+09 | AR16: 1.3284214e+09 | AS16: 1.3387591e+09 | AT16: 1.3985359e+09 | AU16: 1.2820744e+09 | AV16: 1.21997e+09 | AW16: 1.2049734e+09 | AX16: 1.184798e+09 | AY16: 1.0813562e+09 | AZ16: 1.0989296e+09 | BA16: 1.2898574e+09 | BB16: 1.3812474e+09 | BC16: 1.4738159e+09 | BD16: 1.4717382e+09 | BE16: 1.4646547e+09 | BF16: 1.4178603e+09 | BG16: 1.3468218e+09 | BH16: 1.4841928e+09 | BI16: 1.6733407e+09 | BJ16: 1.8469181e+09 | BK16: 1.8791971e+09 | BL16: 1.7420459e+09 | BM16: 2.0065965e+09 | BN16: 1.6751594e+09 | BO16: 1.9071987e+09 | BP16: 2.0543648e+09 | BQ16: =BP16-BO16 -> 1.471661e+08 | BR16: vnd | BW16: =BQ16/BO16 -> 0.077163485
A17: Overtime 150% (vnd) | B17: 794836.96 | C17: 667410.71 | D17: 548437.5 | E17: 1523437.5 | F17: 1440340.9 | G17: 886363.64 | H17: 1828125 | I17: 83096.591 | J17: 0 | K17: 0 | L17: 637073.86 | M17: 387784.09 | N17: 1213505.2 | O17: 869859.05 | P17: 1542187.5 | Q17: 5650384.6 | R17: 9070078.1 | S17: 6538184.8 | T17: 8361064.3 | U17: 4639343 | V17: 12287665 | W17: 11352697 | X17: 5365220.7 | Y17: 7632053.1 | Z17: 5725092.9 | AA17: 19709135 | AB17: 4845596.6 | AC17: 2578895.3 | AD17: 2830545.2 | AE17: 12015997 | AF17: 2409375 | AG17: 0 | AH17: 1539302.9 | AI17: 1805769.2 | AJ17: 0 | AK17: 0 | AL17: 138494.32 | AM17: 0 | AN17: 7631774.5 | AO17: 260369.32 | AP17: 13608403 | AQ17: 24736757 | AR17: 1963210.2 | AS17: 1203835.2 | AT17: 1035298.3 | AU17: 32635866 | AV17: 618110.8 | AW17: 988636.36 | AX17: 1245006.6 | AY17: 409303.98 | AZ17: 168536.93 | BA17: 529687.5 | BB17: 24075918 | BC17: 13961129 | BD17: 746377.84 | BE17: 890838.07 | BF17: 564204.55 | BG17: 30239030 | BH17: 2070809.7 | BI17: 1733735.8 | BJ17: 9122333.9 | BK17: 43722058 | BL17: 2.5568323e+08 | BM17: 5.8750009e+08 | BN17: 3.7886347e+08 | BO17: 3.9053798e+08 | BP17: 4.9316481e+08 | BQ17: =BP17-BO17 -> 1.0262683e+08 | BR17: vnd
A18: Overtime 175% (vnd) | B18: 4.2329471e+08 | C18: 2.4899934e+08 | D18: 1.5217249e+08 | E18: 6.2159358e+08 | F18: 5.0288858e+08 | G18: 6.1707997e+08 | H18: 6.20316e+08 | I18: 1.5531237e+08 | J18: 1809659.1 | K18: 1777343.8 | L18: 1.6274989e+08 | M18: 640264.42 | N18: 0 | O18: 0 | P18: 0 | Q18: 0 | R18: 0 | S18: 0 | T18: 0 | U18: 0 | V18: 0 | W18: 0 | X18: 0 | Y18: 0 | Z18: 0 | AA18: 0 | AB18: 0 | AC18: 0 | AD18: 0 | AE18: 0 | AF18: 0 | AG18: 0 | AH18: 0 | AI18: 0 | AJ18: 0 | AK18: 0 | AL18: 0 | AM18: 0 | AN18: 0 | AO18: 0 | AP18: 0 | AQ18: 0 | AR18: 0 | AS18: 0 | AT18: 0 | AU18: 0 | AV18: 0 | AW18: 0 | AX18: 0 | AY18: 0 | AZ18: 0 | BA18: 0 | BB18: 0 | BC18: 0 | BD18: 0 | BE18: 0 | BF18: 0 | BG18: 0 | BH18: 0 | BI18: 0 | BJ18: 0 | BK18: 0 | BL18: 0 | BM18: 0 | BN18: 0 | BO18: 0 | BP18: 0 | BQ18: =BP18-BO18 -> 0 | BR18: vnd
A19: Overtime 200% (vnd) | B19: 63267600 | C19: 37973855 | D19: 76865505 | E19: 83646077 | F19: 77049530 | G19: 1.0295061e+08 | H19: 1.3843548e+08 | I19: 4.1689241e+08 | J19: 6.5327478e+08 | K19: 9.0702104e+08 | L19: 3.7107775e+08 | M19: 5.5726902e+08 | N19: 7785861 | O19: 2.4580608e+08 | P19: 4.7690632e+08 | Q19: 7.3378108e+08 | R19: 4.9653285e+08 | S19: 5.4869401e+08 | T19: 6.404009e+08 | U19: 3.1241941e+08 | V19: 5.3578593e+08 | W19: 6.7581634e+08 | X19: 6.005588e+08 | Y19: 4.0764541e+08 | Z19: 2.9479655e+08 | AA19: 15831469 | AB19: 5.7967955e+08 | AC19: 3.6869913e+08 | AD19: 42144362 | AE19: 1.5312751e+08 | AF19: 1.3274788e+08 | AG19: 3346875 | AH19: 35668269 | AI19: 17453846 | AJ19: 1834615.4 | AK19: 2040384.6 | AL19: 3017307.7 | AM19: 1.0830865e+08 | AN19: 2.5176779e+08 | AO19: 4.6258917e+08 | AP19: 3.7584869e+08 | AQ19: 7.0254823e+08 | AR19: 1.0029912e+09 | AS19: 6.1036769e+08 | AT19: 4.8277e+08 | AU19: 6.8852676e+08 | AV19: 1.1858283e+08 | AW19: 1.5639678e+08 | AX19: 2.0484481e+08 | AY19: 14753617 | AZ19: 3.2569914e+08 | BA19: 5.5888972e+08 | BB19: 3.2542807e+08 | BC19: 4.2747597e+08 | BD19: 5.2929245e+08 | BE19: 1.2572239e+08 | BF19: 1.8948883e+08 | BG19: 1.4998676e+08 | BH19: 3.3782048e+08 | BI19: 3.9471888e+08 | BJ19: 2.7553372e+08 | BK19: 2.3626803e+08 | BL19: 74858501 | BM19: 2.9428942e+08 | BN19: 98673274 | BO19: 98424038 | BP19: 1.9483149e+08 | BQ19: =BP19-BO19 -> 96407452 | BR19: vnd
A20: Overtime 210% (vnd) | I20: 92016346 | J20: 1.1176316e+08 | K20: 2.1137409e+08 | L20: 0 | M20: 0 | N20: 5.1241742e+08 | O20: 0 | P20: 0 | Q20: 0 | R20: 0 | S20: 0 | T20: 0 | U20: 0 | V20: 0 | W20: 0 | X20: 0 | Y20: 0 | Z20: 0 | AA20: 0 | AB20: 0 | AC20: 0 | AD20: 0 | AE20: 0 | AF20: 0 | AG20: 0 | AH20: 0 | AI20: 0 | AJ20: 0 | AK20: 0 | AL20: 0 | AM20: 0 | AN20: 0 | AO20: 0 | AP20: 0 | AQ20: 0 | AR20: 0 | AS20: 0 | AT20: 0 | AU20: 0 | AV20: 0 | AW20: 0 | AX20: 0 | AY20: 0 | AZ20: 0 | BA20: 0 | BB20: 0 | BC20: 0 | BD20: 0 | BE20: 0 | BF20: 0 | BG20: 0 | BH20: 0 | BI20: 0 | BJ20: 0 | BK20: 0 | BL20: 0 | BM20: 0 | BN20: 0 | BO20: 0 | BP20: 0 | BQ20: =BP20-BO20 -> 0
A21: Overtime 220% (vnd) | B21: 0 | C21: 0 | D21: 0 | E21: 162500 | F21: 0 | G21: 0 | H21: 121875 | I21: 0 | J21: 0 | K21: 81250 | L21: 0 | M21: 0 | N21: 0 | O21: 0 | P21: 0 | Q21: 0 | R21: 0 | S21: 0 | T21: 0 | U21: 0 | V21: 0 | W21: 81250 | X21: 0 | Y21: 0 | Z21: 0 | AA21: 0 | AB21: 0 | AC21: 0 | AD21: 0 | AE21: 0 | AF21: 0 | AG21: 0 | AH21: 0 | AI21: 0 | AJ21: 0 | AK21: 0 | AL21: 0 | AM21: 0 | AN21: 0 | AO21: 0 | AP21: 0 | AQ21: 0 | AR21: 0 | AS21: 0 | AT21: 0 | AU21: 0 | AV21: 0 | AW21: 0 | AX21: 0 | AY21: 0 | AZ21: 0 | BA21: 0 | BB21: 0 | BC21: 0 | BD21: 0 | BE21: 0 | BF21: 0 | BG21: 0 | BH21: 0 | BI21: 0 | BJ21: 0 | BK21: 0 | BL21: 0 | BM21: 0 | BN21: 0 | BO21: 0 | BP21: 0 | BQ21: =BP21-BO21 -> 0 | BR21: vnd
A22: Overtime 290% (vnd) | B22: 0 | C22: 0 | D22: 0 | E22: 0 | F22: 0 | G22: 5576923.1 | H22: 0 | I22: 0 | J22: 0 | K22: 58948077 | L22: 1.9793825e+08 | M22: 3.5917894e+08 | N22: 0 | O22: 1.446626e+08 | P22: 1.8073553e+08 | Q22: 2.8227234e+08 | R22: 1.0675737e+08 | S22: 2.7071165e+08 | T22: 2.0208762e+08 | U22: 1.100589e+08 | V22: 1.5713538e+08 | W22: 2.102539e+08 | X22: 1.9845481e+08 | Y22: 1.2709808e+08 | Z22: 1.0895077e+08 | AA22: 2900000 | AB22: 2.5775214e+08 | AC22: 1.0469558e+08 | AD22: 5827884.6 | AE22: 50733269 | AF22: 23250192 | AG22: 0 | AH22: 8778076.9 | AI22: 2320000 | AJ22: 0 | AK22: 596730.77 | AL22: 0 | AM22: 26267308 | AN22: 38993846 | AO22: 1.2031096e+08 | AP22: 89504038 | AQ22: 2.2753707e+08 | AR22: 3.2936192e+08 | AS22: 2.1273173e+08 | AT22: 1.6904769e+08 | AU22: 2.126425e+08 | AV22: 42986923 | AW22: 44860769 | AX22: 62238462 | AY22: 9971538.5 | AZ22: 91946731 | BA22: 2.0972577e+08 | BB22: 1.2976385e+08 | BC22: 1.6504904e+08 | BD22: 2.0888365e+08 | BE22: 60197308 | BF22: 79838011 | BG22: 56388269 | BH22: 1.4957203e+08 | BI22: 1.5119596e+08 | BJ22: 1.1957481e+08 | BK22: 1.1783097e+08 | BL22: 21058462 | BM22: 1.3365654e+08 | BN22: 32903846 | BO22: 29613462 | BP22: 50671923 | BQ22: =BP22-BO22 -> 21058462 | BR22: vnd
A23: Overtime 300% (vnd) | E23: 0 | F23: 0 | G23: 0 | H23: 0 | I23: 0 | J23: 0 | K23: 2.3024502e+08 | L23: 0 | M23: 0 | N23: 3.1250192e+08 | O23: 0 | P23: 0 | Q23: 0 | R23: 0 | S23: 0 | T23: 0 | U23: 0 | V23: 0 | W23: 12409615 | X23: 0 | Y23: 0 | Z23: 0 | AA23: 0 | AB23: 0 | AC23: 0 | AD23: 0 | AE23: 0 | AF23: 0 | AG23: 0 | AH23: 0 | AI23: 0 | AJ23: 0 | AK23: 0 | AL23: 0 | AM23: 0 | AN23: 0 | AO23: 0 | AP23: 600000 | AQ23: 900000 | AR23: 0 | AS23: 0 | AT23: 0 | AU23: 0 | AV23: 0 | AW23: 0 | AX23: 0 | AY23: 0 | AZ23: 0 | BA23: 0 | BB23: 0 | BC23: 0 | BD23: 0 | BE23: 0 | BF23: 0 | BG23: 0 | BH23: 0 | BI23: 0 | BJ23: 0 | BK23: 0 | BL23: 21156785 | BM23: 0 | BN23: 0 | BO23: 0 | BP23: 0 | BQ23: =BP23-BO23 -> 0 | BR23: vnd
A24: Overtime 410% (vnd) | C24: 0 | D24: 0 | E24: 0 | F24: 0 | G24: 0 | H24: 0 | I24: 0 | J24: 0 | K24: 1982980.8 | L24: 0 | M24: 0 | N24: 0 | O24: 0 | P24: 0 | Q24: 0 | R24: 0 | S24: 0 | T24: 0 | U24: 0 | V24: 0 | W24: 9114615.4 | X24: 0 | Y24: 0 | Z24: 0 | AA24: 0 | AB24: 0 | AC24: 0 | AD24: 0 | AE24: 0 | AF24: 0 | AG24: 0 | AH24: 0 | AI24: 0 | AJ24: 0 | AK24: 0 | AL24: 0 | AM24: 0 | AN24: 0 | AO24: 0 | AP24: 0 | AQ24: 0 | AR24: 0 | AS24: 0 | AT24: 0 | AU24: 0 | AV24: 0 | AW24: 0 | AX24: 0 | AY24: 0 | AZ24: 0 | BA24: 0 | BB24: 0 | BC24: 0 | BD24: 0 | BE24: 0 | BF24: 0 | BG24: 0 | BH24: 0 | BI24: 0 | BJ24: 0 | BK24: 0 | BL24: 13955769 | BM24: 0 | BN24: 0 | BO24: 0 | BP24: 0 | BQ24: =BP24-BO24 -> 0 | BR24: vnd
A25: Overtime 100% (vnd) | B25: 0 | C25: 0 | D25: 0 | E25: 769230.77 | F25: 0 | G25: 0 | H25: 0 | I25: 0 | J25: 0 | K25: 0 | L25: 0 | M25: 0 | N25: 0 | O25: 0 | P25: 0 | Q25: 905769.23 | R25: 1393750 | S25: 0 | T25: 0 | U25: 0 | V25: 0 | W25: 0 | X25: 0 | Y25: 0 | Z25: 0 | AA25: 0 | AB25: 0 | AC25: 0 | AD25: 0 | AE25: 0 | AF25: 0 | AG25: 0 | AH25: 0 | AI25: 0 | AJ25: 0 | AK25: 0 | AL25: 0 | AM25: 0 | AN25: 0 | AO25: 0 | AP25: 0 | AQ25: 0 | AR25: 0 | AS25: 749038.46 | AT25: 106730.77 | AU25: 0 | AV25: 0 | AW25: 0 | AX25: 0 | AY25: 0 | AZ25: 0 | BA25: 93389.423 | BB25: 0 | BC25: 0 | BD25: 0 | BE25: 0 | BF25: 0 | BG25: 0 | BH25: 0 | BI25: 0 | BJ25: 0 | BK25: 0 | BL25: 0 | BM25: 0 | BN25: 0 | BO25: 0 | BP25: 0 | BQ25: =BP25-BO25 -> 0 | BR25: vnd
A26: Night allowance (vnd) | B26: 0 | C26: 0 | D26: 0 | E26: 0 | F26: 0 | G26: 0 | H26: 0 | I26: 0 | J26: 0 | K26: 0 | L26: 65007600 | M26: 99297644 | N26: 1.1100332e+08 | O26: 91444129 | P26: 47036015 | Q26: 95550857 | R26: 66771915 | S26: 85718073 | T26: 99660168 | U26: 83215382 | V26: 86760656 | W26: 89202696 | X26: 91765557 | Y26: 1.0136175e+08 | Z26: 98026429 | AA26: 35672769 | AB26: 81617077 | AC26: 99414646 | AD26: 51072298 | AE26: 52419607 | AF26: 67042111 | AG26: 43584970 | AH26: 54437961 | AI26: 37344194 | AJ26: 32201280 | AK26: 18351334 | AL26: 9746820.9 | AM26: 10855148 | AN26: 10649423 | AO26: 39246834 | AP26: 40808149 | AQ26: 76589973 | AR26: 80359684 | AS26: 88547849 | AT26: 96925121 | AU26: 68224770 | AV26: 76472514 | AW26: 64498230 | AX26: 74361780 | AY26: 38922881 | AZ26: 49405298 | BA26: 80788569 | BB26: 72419522 | BC26: 85282204 | BD26: 86068778 | BE26: 91641728 | BF26: 84210507 | BG26: 60363945 | BH26: 97559781 | BI26: 88578762 | BJ26: 1.2508467e+08 | BK26: 1.1190271e+08 | BL26: 66216178 | BM26: 1.3783878e+08 | BN26: 90560450 | BO26: 1.1751892e+08 | BP26: 1.4911353e+08 | BQ26: =BP26-BO26 -> 31594616 | BR26: vnd
A27: Phụ cấp đi lại | B27: 62869537 | C27: 64218677 | D27: 58442449 | E27: 71201689 | F27: 76989898 | G27: 81294375 | H27: 77428888 | I27: 54923506 | J27: 58305288 | K27: 62330245 | L27: 69566617 | M27: 74055614 | N27: 76772468 | O27: 82434519 | P27: 76880953 | Q27: 76921126 | R27: 84855704 | S27: 78496136 | T27: 81224981 | U27: 79029031 | V27: 80080253 | W27: 84006316 | X27: 81198774 | Y27: 78563812 | Z27: 76865338 | AA27: 74308001 | AB27: 76404135 | AC27: 76276755 | AD27: 72693576 | AE27: 65319286 | AF27: 62125427 | AG27: 52201243 | AH27: 51678720 | AI27: 50928690 | AJ27: 41091840 | AK27: 21919195 | AL27: 17100000 | AM27: 20183441 | AN27: 27783372 | AO27: 43465236 | AP27: 55106453 | AQ27: 68469018 | AR27: 77856668 | AS27: 74595403 | AT27: 77070419 | AU27: 70338333 | AV27: 67082321 | AW27: 66032083 | AX27: 64946667 | AY27: 63322032 | AZ27: 63813803 | BA27: 70889766 | BB27: 76516639 | BC27: 80108830 | BD27: 80440150 | BE27: 79607898 | BF27: 76945812 | BG27: 72884927 | BH27: 77884335 | BI27: 88736445 | BJ27: 99435774 | BK27: 94934220 | BL27: 93099962 | BM27: 1.0433955e+08 | BN27: 87687572 | BO27: 99398251 | BP27: 1.1063146e+08 | BQ27: =BP27-BO27 -> 11233213 | BR27: vnd
A28: Phụ cấp nhà ở | B28: 30855023 | C28: 32206190 | D28: 29850000 | E28: 33627303 | F28: 37652079 | G28: 40251083 | H28: 39750000 | I28: 38219444 | J28: 30750000 | K28: 30686538 | L28: 35272795 | M28: 38866276 | N28: 43226024 | O28: 42450000 | P28: 39367500 | Q28: 40379232 | R28: 42550000 | S28: 39000000 | T28: 41099660 | U28: 40500000 | V28: 39286957 | W28: 42300000 | X28: 41250000 | Y28: 39600000 | Z28: 38850000 | AA28: 38400000 | AB28: 38520402 | AC28: 38100000 | AD28: 36600000 | AE28: 32700000 | AF28: 32550000 | AG28: 26250000 | AH28: 26100000 | AI28: 25500000 | AJ28: 24150000 | AK28: 8700000 | AL28: 8550000 | AM28: 8550000 | AN28: 12900000 | AO28: 20628947 | AP28: 27768572 | AQ28: 31427369 | AR28: 39750000 | AS28: 37500000 | AT28: 39282955 | AU28: 35700000 | AV28: 33750000 | AW28: 33150000 | AX28: 32650000 | AY28: 32250000 | AZ28: 32359548 | BA28: 34786988 | BB28: 38072515 | BC28: 40299466 | BD28: 40296069 | BE28: 40193478 | BF28: 38700000 | BG28: 36965199 | BH28: 38388545 | BI28: 42260857 | BJ28: 50316841 | BK28: 47890327 | BL28: 47250000 | BM28: 50678169 | BN28: 42623586 | BO28: 49761341 | BP28: 55243028 | BQ28: =BP28-BO28 -> 5481686.7 | BR28: vnd
A29: Thưởng hiệu suất | B29: 85459500 | C29: 84086000 | D29: 61354000 | E29: 83313500 | F29: 104674500 | G29: 97416500 | H29: 116703500 | I29: 81547000 | J29: 88929500 | K29: 118120500 | L29: 99000500 | M29: 119414500 | N29: 129295500 | O29: 111161000 | P29: 74724000 | Q29: 118200000 | R29: 115637811 | S29: 116137500 | T29: 124479000 | U29: 110275500 | V29: 119061500 | W29: 119817500 | X29: 121427000 | Y29: 124400000 | Z29: 110189000 | AA29: 85441500 | AB29: 83086667 | AC29: 109876095 | AD29: 104444310 | AE29: 88395238 | AF29: 99472429 | AG29: 65455048 | AH29: 74612738 | AI29: 70043119 | AJ29: 53381167 | AK29: 36256738 | AL29: 24904119 | AM29: 16295405 | AN29: 34702595 | AO29: 65326238 | AP29: 86850548 | AQ29: 102447357 | AR29: 169809929 | AS29: 118951429 | AT29: 122311048 | AU29: 117283000 | AV29: 92327000 | AW29: 97617000 | AX29: 96161000 | AY29: 76799500 | AZ29: 65235000 | BA29: 100312000 | BB29: 107023000 | BC29: 116914000 | BD29: 136441000 | BE29: 109335000 | BF29: 112595000 | BG29: 104520000 | BH29: 113927000 | BI29: 132676000 | BJ29: 136791800 | BK29: 131197500 | BL29: 111758250 | BM29: 137519176 | BN29: 109895973 | BO29: 133659034 | BP29: 169846362 | BQ29: =BP29-BO29 -> 36187328 | BR29: vnd
A30: NVXS&TB tháng | B30: 1530000 | C30: 2280000 | D30: 1770000 | E30: 1890000 | F30: 2280000 | G30: 1650000 | H30: 1920000 | I30: 3360000 | J30: 2160000 | K30: 1470000 | L30: 1710000 | M30: 2220000 | N30: 1770000 | O30: 1560000 | P30: 1980000 | Q30: 2400000 | R30: 2400000 | S30: 3090000 | T30: 2430000 | U30: 2820000 | V30: 2700000 | W30: 1770000 | X30: 2970000 | Y30: 2970000 | Z30: 2610000 | AA30: 2760000 | AB30: 1590000 | AC30: 1410000 | AD30: 2280000 | AE30: 2370000 | AF30: 1500000 | AG30: 1470000 | AH30: 2040000 | AI30: 1830000 | AJ30: 1320000 | AK30: 570000 | AL30: 660000 | AM30: 600000 | AN30: 240000 | AO30: 600000 | AP30: 1050000 | AQ30: 1050000 | AR30: 1650000 | AS30: 1830000 | AT30: 2340000 | AU30: 930000 | AV30: 1590000 | AW30: 1950000 | AX30: 1680000 | AY30: 2310000 | AZ30: 1770000 | BA30: 2010000 | BB30: 2220000 | BC30: 2550000 | BD30: 1980000 | BE30: 2010000 | BF30: 1500000 | BG30: 3120000 | BH30: 2610000 | BI30: 3180000 | BJ30: 2820000 | BK30: 2040000 | BL30: 1590000 | BM30: 1560000 | BN30: 1380000 | BO30: 2520000 | BP30: 1110000 | BQ30: =BP30-BO30 -> -1410000 | BR30: vnd
A31: Thưởng TRP | B31: 35350000 | C31: 46150000 | D31: 30450000 | E31: 38200000 | F31: 40150000 | G31: 54650000 | H31: 42600000 | I31: 28550000 | J31: 43850000 | K31: 40000000 | L31: 51900000 | M31: 43550000 | N31: 43150000 | O31: 55200000 | P31: 42400000 | Q31: 38700000 | R31: 41850000 | S31: 43300000 | T31: 44950000 | U31: 55300000 | V31: 43800000 | W31: 46150000 | X31: 56000000 | Y31: 44800000 | Z31: 42650000 | AA31: 41700000 | AB31: 42150000 | AC31: 43800000 | AD31: 52300000 | AE31: 39350000 | AF31: 39700000 | AG31: 32050000 | AH31: 32450000 | AI31: 31150000 | AJ31: 32150000 | AK31: 14250000 | AL31: 12300000 | AM31: 10500000 | AN31: 13450000 | AO31: 29750000 | AP31: 30700000 | AQ31: 36600000 | AR31: 56000000 | AS31: 43150000 | AT31: 44800000 | AU31: 52400000 | AV31: 40100000 | AW31: 39700000 | AX31: 48550000 | AY31: 33850000 | AZ31: 33500000 | BA31: 51600000 | BB31: 43800000 | BC31: 45950000 | BD31: 57850000 | BE31: 46300000 | BF31: 57000000 | BG31: 42400000 | BH31: 43550000 | BI31: 1.6416849e+08 | BJ31: 1.4406326e+08 | BK31: 1.4205081e+08 | BL31: 2.3493953e+08 | BM31: 2.9246342e+08 | BN31: 1.8913689e+08 | BO31: 2.8133024e+08 | BP31: 2.6111093e+08 | BQ31: =BP31-BO31 -> -20219318 | BR31: vnd | BW31: =BQ31/BO31 -> -0.071870403
A32: Thưởng quý | B32: 53781000 | C32: 0 | D32: 0 | E32: 67781000 | F32: 0 | G32: 0 | H32: 75767143 | I32: 0 | J32: 0 | K32: 55141096 | L32: 0 | M32: 0 | N32: 94266667 | O32: 0 | P32: 0 | Q32: 95700000 | R32: 0 | S32: 0 | T32: 96009235 | U32: 0 | V32: 0 | W32: 104024460 | X32: 0 | Y32: 0 | Z32: 105657000 | AA32: 0 | AB32: 0 | AC32: 94703241 | AD32: 0 | AE32: 0 | AF32: 100694000 | AG32: 0 | AH32: 0 | AI32: 81215056 | AJ32: 0 | AK32: 0 | AL32: 26361112 | AM32: 0 | AN32: 0 | AO32: 31499000 | AP32: 0 | AQ32: 0 | AR32: 77682407 | AS32: 0 | AT32: 0 | AU32: 96018536 | AV32: 0 | AW32: 0 | AX32: 100631491 | AY32: 0 | AZ32: 0 | BA32: 88714839 | BB32: 0 | BC32: 0 | BD32: 98424043 | BE32: 0 | BF32: 0 | BG32: 106713547 | BH32: 0 | BI32: 0 | BJ32: 113453489 | BK32: 0 | BL32: 0 | BM32: 105268176 | BN32: 0 | BO32: 0 | BP32: 83317235 | BQ32: =BP32-BO32 -> 83317235 | BR32: vnd
A33: Lương tháng 13 | B33: 0 | C33: 0 | D33: 0 | E33: 0 | F33: 0 | G33: 0 | H33: 0 | I33: 0 | J33: 0 | K33: 0 | L33: 0 | M33: 0 | N33: 0 | O33: 0 | P33: 0 | Q33: 0 | R33: 0 | S33: 0 | T33: 0 | U33: 0 | V33: 0 | W33: 0 | X33: 0 | Y33: 0 | Z33: 0 | AA33: 0 | AB33: 0 | AC33: 0 | AD33: 0 | AE33: 0 | AF33: 0 | AG33: 0 | AH33: 0 | AI33: 0 | AJ33: 0 | AK33: 0 | AL33: 0 | AM33: 0 | AN33: 0 | AO33: 0 | AP33: 0 | AQ33: 0 | AR33: 0 | AS33: 0 | AT33: 0 | AU33: 0 | AV33: 0 | AW33: 0 | AX33: 0 | AY33: 0 | AZ33: 0 | BA33: 0 | BB33: 0 | BC33: 0 | BD33: 0 | BE33: 0 | BF33: 0 | BG33: 0 | BH33: 0 | BI33: 0 | BJ33: 0 | BK33: 0 | BL33: 0 | BM33: 0 | BN33: 0 | BO33: 0 | BP33: 0 | BQ33: =BP33-BO33 -> 0 | BR33: vnd
A34: Thưởng ca ngày (12h) | B34: 0 | C34: 0 | D34: 0 | E34: 0 | F34: 0 | G34: 0 | H34: 0 | I34: 0 | J34: 0 | K34: 0 | L34: 44069952 | M34: 55082933 | N34: 59175000 | O34: 58825962 | P34: 46525481 | Q34: 74406298 | R34: 65310144 | S34: 60255337 | T34: 68671707 | U34: 66533870 | V34: 73185168 | W34: 63384736 | X34: 64591010 | Y34: 65502115 | Z34: 61589159 | AA34: 29730937 | AB34: 61625721 | AC34: 68102644 | AD34: 48263702 | AE34: 51259375 | AF34: 57311298 | AG34: 42212740 | AH34: 42556250 | AI34: 44369216 | AJ34: 35120428 | AK34: 23275481 | AL34: 15439663 | AM34: 16325721 | AN34: 21444231 | AO34: 40386779 | AP34: 45032933 | AQ34: 64345913 | AR34: 64898077 | AS34: 75766346 | AT34: 73892788 | AU34: 56794231 | AV34: 70102644 | AW34: 65389904 | AX34: 57916346 | AY34: 45166346 | AZ34: 54077404 | BA34: 68530048 | BB34: 64217308 | BC34: 76263462 | BD34: 75382452 | BE34: 81184856 | BF34: 74279808 | BG34: 67132933 | BH34: 73850481 | BI34: 79720433 | BJ34: 92450481 | BK34: 82387740 | BL34: 0 | BM34: 0 | BN34: 0 | BO34: 0 | BP34: 0 | BQ34: =BP34-BO34 -> 0 | BR34: vnd
A35: Thưởng ca đêm (12h) | B35: 0 | C35: 0 | D35: 0 | E35: 0 | F35: 0 | G35: 0 | H35: 0 | I35: 0 | J35: 0 | K35: 0 | L35: 97511400 | M35: 1.4894647e+08 | N35: 1.6650498e+08 | O35: 1.3716619e+08 | P35: 70554023 | Q35: 1.4332628e+08 | R35: 1.0015787e+08 | S35: 1.2857711e+08 | T35: 1.4949025e+08 | U35: 1.2482307e+08 | V35: 1.3014098e+08 | W35: 1.3380404e+08 | X35: 1.3764833e+08 | Y35: 1.5204263e+08 | Z35: 1.4703964e+08 | AA35: 53509154 | AB35: 1.2242562e+08 | AC35: 1.4912197e+08 | AD35: 76608447 | AE35: 78629411 | AF35: 1.0056317e+08 | AG35: 65377455 | AH35: 81656941 | AI35: 56016291 | AJ35: 48301921 | AK35: 27527001 | AL35: 14620231 | AM35: 16282722 | AN35: 15974135 | AO35: 58870251 | AP35: 61212223 | AQ35: 1.1488496e+08 | AR35: 1.2053953e+08 | AS35: 1.3282177e+08 | AT35: 1.4538768e+08 | AU35: 1.0233715e+08 | AV35: 1.1470877e+08 | AW35: 96530037 | AX35: 1.1154267e+08 | AY35: 58384321 | AZ35: 74107946 | BA35: 1.2118285e+08 | BB35: 1.0862928e+08 | BC35: 1.2792331e+08 | BD35: 1.2910317e+08 | BE35: 1.3746259e+08 | BF35: 1.2631576e+08 | BG35: 90545918 | BH35: 1.4633967e+08 | BI35: 1.3286814e+08 | BJ35: 1.8762701e+08 | BK35: 1.6785406e+08 | BL35: 71734193 | BM35: 1.4932535e+08 | BN35: 98107154 | BO35: 1.2731216e+08 | BP35: 1.6153966e+08 | BQ35: =BP35-BO35 -> 34227500 | BR35: vnd
A36: Ca 2 | B36: 800.7809 | C36: 1257.3311 | D36: 544.3124 | E36: 810.3977 | F36: 814.8665 | G36: 772.2622 | H36: 681.875 | I36: 272.1163 | J36: 7 | K36: 0 | L36: 0 | M36: 0 | N36: 0 | O36: 0 | P36: 0 | Q36: 0 | R36: 0 | S36: 0 | T36: 0 | U36: 0 | V36: 0 | W36: 10 | X36: 0 | Y36: 0 | Z36: 0 | AA36: 162.0248 | AB36: 0 | AC36: 0 | AD36: 320.9687 | AE36: 191.5 | AF36: 0 | AG36: 0 | AH36: 153 | AI36: 0 | AJ36: 0 | AK36: 0 | AL36: 0 | AM36: 0 | AN36: 0 | AO36: 0 | AP36: 0 | AQ36: 0 | AR36: 0 | AS36: 0 | AT36: 0 | AU36: 0 | AV36: 0 | AW36: 0 | AX36: 35 | AY36: 26 | AZ36: 0 | BA36: 0 | BB36: 23.9978 | BC36: 0 | BD36: 0 | BE36: 0 | BF36: 0 | BG36: 0 | BH36: 0 | BI36: 0 | BJ36: 0 | BK36: 1 | BL36: 2 | BM36: 0 | BN36: 7.8896 | BO36: 0 | BP36: 0 | BQ36: =BP36-BO36 -> 0 | BR36: Days
A37: P/c ca 2 | B37: 14827494 | C37: 24029310 | D37: 10383003 | E37: 15764589 | F37: 15826183 | G37: 14987134 | H37: 13210481 | I37: 5274159.6 | J37: 135000 | K37: 0 | L37: 0 | M37: 0 | N37: 0 | O37: 0 | P37: 0 | Q37: 0 | R37: 0 | S37: 0 | T37: 0 | U37: 0 | V37: 0 | W37: 200384.62 | X37: 0 | Y37: 0 | Z37: 0 | AA37: 3254745.2 | AB37: 0 | AC37: 0 | AD37: 6437643.2 | AE37: 3840000 | AF37: 0 | AG37: 0 | AH37: 3068076.9 | AI37: 0 | AJ37: 0 | AK37: 0 | AL37: 0 | AM37: 0 | AN37: 0 | AO37: 0 | AP37: 0 | AQ37: 0 | AR37: 0 | AS37: 0 | AT37: 0 | AU37: 0 | AV37: 0 | AW37: 0 | AX37: 748653.85 | AY37: 558269.23 | AZ37: 0 | BA37: 0 | BB37: 514376.11 | BC37: 0 | BD37: 0 | BE37: 0 | BF37: 0 | BG37: 0 | BH37: 0 | BI37: 0 | BJ37: 0 | BK37: 22692.308 | BL37: 45384.615 | BM37: 0 | BN37: 179033.23 | BO37: 0 | BP37: 0 | BQ37: =BP37-BO37 -> 0 | BR37: vnd
A38: Ca 3 | B38: 1306.5374 | C38: 832 | D38: 493.804 | E38: 1812.9269 | F38: 1483.9936 | G38: 1964.1789 | H38: 2253.4916 | I38: 1009.0937 | J38: 1758.9687 | K38: 1435 | L38: 460.8352 | M38: 0 | N38: 0 | O38: 0 | P38: 7 | Q38: 0 | R38: 81 | S38: 0 | T38: 0 | U38: 0 | V38: 5 | W38: 36 | X38: 0 | Y38: 0 | Z38: 0 | AA38: 57 | AB38: 0 | AC38: 0 | AD38: 53 | AE38: 111.9375 | AF38: 0 | AG38: 0 | AH38: 77 | AI38: 0 | AJ38: 0 | AK38: 0 | AL38: 0 | AM38: 0 | AN38: 0 | AO38: 0 | AP38: 0 | AQ38: 49 | AR38: 0 | AS38: 0 | AT38: 0 | AU38: 60 | AV38: 0 | AW38: 0 | AX38: 0 | AY38: 31 | AZ38: 0 | BA38: 0 | BB38: 63 | BC38: 32 | BD38: 0 | BE38: 0 | BF38: 0 | BG38: 67 | BH38: 0 | BI38: 0 | BJ38: 5 | BK38: 199.1728 | BL38: 220 | BM38: 458 | BN38: 532.9374 | BO38: 471 | BP38: 492.7478 | BQ38: =BP38-BO38 -> 21.7478 | BR38: Days
A39: P/c ca 3 | B39: 1.2114768e+08 | C39: 79476923 | D39: 47304439 | E39: 1.7641797e+08 | F39: 1.4429256e+08 | G39: 1.9056161e+08 | H39: 2.1838567e+08 | I39: 97584971 | J39: 1.7068834e+08 | K39: 1.3895865e+08 | L39: 44650500 | M39: 0 | N39: 0 | O39: 0 | P39: 702884.62 | Q39: 0 | R39: 8131730.8 | S39: 0 | T39: 0 | U39: 0 | V39: 505769.23 | W39: 3605769.2 | X39: 0 | Y39: 0 | Z39: 0 | AA39: 5719230.8 | AB39: 0 | AC39: 0 | AD39: 5311538.5 | AE39: 11201442 | AF39: 0 | AG39: 0 | AH39: 7719230.8 | AI39: 0 | AJ39: 0 | AK39: 0 | AL39: 0 | AM39: 0 | AN39: 0 | AO39: 0 | AP39: 0 | AQ39: 4915384.6 | AR39: 0 | AS39: 0 | AT39: 0 | AU39: 6422115.4 | AV39: 0 | AW39: 0 | AX39: 0 | AY39: 3325961.5 | AZ39: 0 | BA39: 0 | BB39: 6732692.3 | BC39: 3417307.7 | BD39: 0 | BE39: 0 | BF39: 0 | BG39: 7167307.7 | BH39: 0 | BI39: 0 | BJ39: 533653.85 | BK39: 22566000 | BL39: 24971154 | BM39: 51988462 | BN39: 60467897 | BO39: 53440385 | BP39: 55907923 | BQ39: =BP39-BO39 -> 2467538.8 | BR39: vnd
A40: Ca Lỡ | I40: 0 | J40: 29.25 | K40: 0 | L40: 0 | M40: 0 | N40: 0 | O40: 0 | P40: 0 | Q40: 0 | R40: 0 | S40: 0 | T40: 0 | U40: 0 | V40: 0 | W40: 0 | X40: 0 | Y40: 0 | Z40: 0 | AA40: 0 | AB40: 0 | AC40: 0 | AD40: 0 | AE40: 0 | AF40: 0 | AG40: 0 | AH40: 0 | AI40: 0 | AJ40: 0 | AK40: 0 | AL40: 0 | AM40: 0 | AN40: 0 | AO40: 0 | AP40: 0 | AQ40: 0 | AR40: 0 | AS40: 0 | AT40: 0 | AU40: 0 | AV40: 0 | AW40: 0 | AX40: 0 | AY40: 0 | AZ40: 0 | BA40: 0 | BB40: 0 | BC40: 0 | BD40: 0 | BE40: 0 | BF40: 0 | BG40: 0 | BH40: 0 | BI40: 0 | BJ40: 0 | BK40: 0 | BL40: 0 | BM40: 0 | BN40: 0 | BO40: 0 | BP40: 0 | BQ40: =BP40-BO40 -> 0
A41: P/c ca Lỡ | I41: 0 | J41: 2831250 | K41: 0 | L41: 0 | M41: 0 | N41: 0 | O41: 0 | P41: 0 | Q41: 0 | R41: 0 | S41: 0 | T41: 0 | U41: 0 | V41: 0 | W41: 0 | X41: 0 | Y41: 0 | Z41: 0 | AA41: 0 | AB41: 0 | AC41: 0 | AD41: 0 | AE41: 0 | AF41: 0 | AG41: 0 | AH41: 0 | AI41: 0 | AJ41: 0 | AK41: 0 | AL41: 0 | AM41: 0 | AN41: 0 | AO41: 0 | AP41: 0 | AQ41: 0 | AR41: 0 | AS41: 0 | AT41: 0 | AU41: 0 | AV41: 0 | AW41: 0 | AX41: 0 | AY41: 0 | AZ41: 0 | BA41: 0 | BB41: 0 | BC41: 0 | BD41: 0 | BE41: 0 | BF41: 0 | BG41: 0 | BH41: 0 | BI41: 0 | BJ41: 0 | BK41: 0 | BL41: 0 | BM41: 0 | BN41: 0 | BO41: 0 | BP41: 0 | BQ41: =BP41-BO41 -> 0
A42: Giờ thưởng OT | I42: 902 | J42: 1094 | K42: 2560 | L42: 0 | M42: 0 | N42: 0 | O42: 0 | P42: 0 | Q42: 0 | R42: 0 | S42: 0 | T42: 0 | U42: 0 | V42: 0 | W42: 0 | X42: 0 | Y42: 0 | Z42: 0 | AA42: 0 | AB42: 0 | AC42: 0 | AD42: 0 | AE42: 0 | AF42: 0 | AG42: 0 | AH42: 0 | AI42: 0 | AJ42: 0 | AK42: 0 | AL42: 0 | AM42: 0 | AN42: 0 | AO42: 0 | AP42: 0 | AQ42: 0 | AR42: 0 | AS42: 0 | AT42: 0 | AU42: 0 | AV42: 0 | AW42: 0 | AX42: 0 | AY42: 0 | AZ42: 0 | BA42: 0 | BB42: 0 | BC42: 0 | BD42: 0 | BE42: 0 | BF42: 0 | BG42: 0 | BH42: 0 | BI42: 0 | BJ42: 0 | BK42: 0 | BL42: 2976 | BM42: 6839 | BN42: 4414 | BO42: 4566 | BP42: 5743 | BQ42: =BP42-BO42 -> 1177
A43: Tiền thưởng OT | I43: 21884615 | J43: 26519231 | K43: 62020192 | L43: 0 | M43: 0 | N43: 0 | O43: 0 | P43: 0 | Q43: 0 | R43: 0 | S43: 0 | T43: 0 | U43: 0 | V43: 0 | W43: 0 | X43: 0 | Y43: 0 | Z43: 0 | AA43: 0 | AB43: 0 | AC43: 0 | AD43: 0 | AE43: 0 | AF43: 0 | AG43: 0 | AH43: 0 | AI43: 0 | AJ43: 0 | AK43: 0 | AL43: 0 | AM43: 0 | AN43: 0 | AO43: 0 | AP43: 0 | AQ43: 0 | AR43: 0 | AS43: 0 | AT43: 0 | AU43: 0 | AV43: 0 | AW43: 0 | AX43: 0 | AY43: 0 | AZ43: 0 | BA43: 0 | BB43: 0 | BC43: 0 | BD43: 0 | BE43: 0 | BF43: 0 | BG43: 0 | BH43: 0 | BI43: 0 | BJ43: 0 | BK43: 0 | BL43: 84458173 | BM43: 1.9406202e+08 | BN43: 1.2520962e+08 | BO43: 1.2951635e+08 | BP43: 1.629024e+08 | BQ43: =BP43-BO43 -> 33386058
A44: Sat/Sun transportation | B44: 29610000 | C44: 33120000 | D44: 22590000 | E44: 39210000 | F44: 33900000 | G44: 39930000 | H44: 43290000 | I44: 36120000 | J44: 31650000 | K44: 40920000 | L44: 53640000 | M44: 61440000 | N44: 43350000 | O44: 20850000 | P44: 35580000 | Q44: 50400000 | R44: 29340000 | S44: 48120000 | T44: 41370000 | U44: 20760000 | V44: 34260000 | W44: 42960000 | X44: 39240000 | Y44: 26220000 | Z44: 19830000 | AA44: 1020000 | AB44: 40260000 | AC44: 23850000 | AD44: 2700000 | AE44: 10260000 | AF44: 7890000 | AG44: 390000 | AH44: 2160000 | AI44: 1110000 | AJ44: 240000 | AK44: 180000 | AL44: 150000 | AM44: 6450000 | AN44: 13980000 | AO44: 27690000 | AP44: 22050000 | AQ44: 43320000 | AR44: 61770000 | AS44: 36270000 | AT44: 28590000 | AU44: 39480000 | AV44: 6870000 | AW44: 8700000 | AX44: 11580000 | AY44: 1260000 | AZ44: 18240000 | BA44: 33000000 | BB44: 19500000 | BC44: 25830000 | BD44: 31590000 | BE44: 7590000 | BF44: 11310000 | BG44: 9180000 | BH44: 20670000 | BI44: 23430000 | BJ44: 16680000 | BK44: 14010000 | BL44: 4980000 | BM44: 17160000 | BN44: 5340000 | BO44: 5670000 | BP44: 10980000 | BQ44: =BP44-BO44 -> 5310000 | BR44: vnd
A45: Phụ cấp phụ nữ (1.5 giờ/ tháng) | C45: 3376442.3 | D45: 3307932.7 | E45: 4710266 | F45: 4827455 | G45: 5359315 | H45: 4960515 | I45: 5032631 | J45: 3970365 | K45: 4293806 | L45: 4510154 | M45: 5447662 | N45: 5231314 | O45: 5220993 | P45: 5168152 | Q45: 5803488 | R45: 5584224 | S45: 5456709 | T45: 5487391 | U45: 5374891 | V45: 5645914 | W45: 5495914 | X45: 5400459 | Y45: 5287959 | Z45: 5165232 | AA45: 5127732 | AB45: 5390232 | AC45: 5390232 | AD45: 5201650 | AE45: 4825208 | AF45: 4787708 | AG45: 4111626 | AH45: 3895149 | AI45: 3954808 | AJ45: 3842308 | AK45: 2678005 | AL45: 1521602 | AM45: 2158381 | AN45: 2833381 | AO45: 3808381 | AP45: 4333381 | AQ45: 5570881 | AR45: 5345881 | AS45: 5785643 | AT45: 5576673 | AU45: 5131001 | AV45: 4970905 | AW45: 4850112 | AX45: 4890857 | AY45: 4850833 | AZ45: 5050953 | BA45: 6090856 | BB45: 6279110 | BC45: 6639326 | BD45: 6795817 | BE45: 6497850 | BF45: 6337754 | BG45: 6256952 | BH45: 7584038 | BI45: 8505050 | BJ45: 8624401 | BK45: 8977957 | BL45: 8693823 | BM45: 10480839 | BN45: 9345483 | BO45: 10604025 | BP45: 12002864 | BQ45: =BP45-BO45 -> 1398839 | BR45: vnd
A46: Phụ cấp bằng cấp - cấp 3 | E46: 26100000 | F46: 25200000 | G46: 28100000 | H46: 25300000 | I46: 25300000 | J46: 19600000 | K46: 20900000 | L46: 24800000 | M46: 28900000 | N46: 30400000 | O46: 29350000 | P46: 27950000 | Q46: 30450000 | R46: 29350000 | S46: 28450000 | T46: 28900000 | U46: 28100000 | V46: 29850000 | W46: 29550000 | X46: 29050000 | Y46: 27750000 | Z46: 27250000 | AA46: 26950000 | AB46: 28300000 | AC46: 27500000 | AD46: 26100000 | AE46: 23250000 | AF46: 23050000 | AG46: 18800000 | AH46: 18300000 | AI46: 18150000 | AJ46: 17850000 | AK46: 11750000 | AL46: 6750000 | AM46: 9650000 | AN46: 11400000 | AO46: 17400000 | AP46: 20900000 | AQ46: 29850000 | AR46: 29600000 | AS46: 30950000 | AT46: 30150000 | AU46: 27600000 | AV46: 26400000 | AW46: 25500000 | AX46: 25200000 | AY46: 24800000 | AZ46: 26150000 | BA46: 29750000 | BB46: 30200000 | BC46: 31750000 | BD46: 32050000 | BE46: 29950000 | BF46: 29050000 | BG46: 28150000 | BH46: 32800000 | BI46: 36450000 | BJ46: 36900000 | BK46: 35900000 | BL46: 34300000 | BM46: 40450000 | BN46: 33300000 | BO46: 38500000 | BP46: 41450000 | BQ46: =BP46-BO46 -> 2950000 | BR46: vnd
A47: P/c bữa ăn ca chính | B47: 49187000 | C47: 59949000 | D47: 31967000 | E47: 45572000 | F47: 48363000 | G47: 51604000 | H47: 52102000 | I47: 28866000 | J47: 29422000 | K47: 7023000 | L47: 70705000 | M47: 90853000 | N47: 100034000 | O47: 85927000 | P47: 59425000 | Q47: 101141000 | R47: 78983000 | S47: 82905000 | T47: 97412000 | U47: 90222000 | V47: 97494000 | W47: 88840000 | X47: 91238000 | Y47: 95185000 | Z47: 90485000 | AA47: 47947000 | AB47: 85083000 | AC47: 98607000 | AD47: 78052000 | AE47: 65465000 | AF47: 74948000 | AG47: 52907000 | AH47: 68349000 | AI47: 52414000 | AJ47: 42968000 | AK47: 27483000 | AL47: 17378000 | AM47: 18825000 | AN47: 22899000 | AO47: 51314000 | AP47: 55637000 | AQ47: 87315000 | AR47: 88289000 | AS47: 94206000 | AT47: 96326000 | AU47: 71265000 | AV47: 84217000 | AW47: 76393000 | AX47: 76376000 | AY47: 53165000 | AZ47: 61445000 | BA47: 85328000 | BB47: 83050000 | BC47: 93469000 | BD47: 92818000 | BE47: 99974000 | BF47: 91445000 | BG47: 76805000 | BH47: 99563000 | BI47: 100347000 | BJ47: 124491000 | BK47: 107924000 | BL47: 19237000 | BM47: 17953000 | BN47: 31229000 | BO47: 57912000 | BP47: 48878000 | BQ47: =BP47-BO47 -> -9034000 | BR47: vnd
A48: P/c bữa ăn OT | B48: 78086000 | C48: 44065000 | D48: 36282000 | E48: 114103000 | F48: 89926000 | G48: 114303000 | H48: 121410000 | I48: 85200000 | J48: 105237000 | K48: 146687000 | L48: 43956000 | M48: 34860000 | N48: 29494000 | O48: 13772000 | P48: 23048000 | Q48: 36102000 | R48: 26783000 | S48: 31629000 | T48: 30949000 | U48: 14633000 | V48: 25378000 | W48: 33540000 | X48: 28272000 | Y48: 20619000 | Z48: 16084000 | AA48: 3241000 | AB48: 28866000 | AC48: 16275000 | AD48: 1710000 | AE48: 8323000 | AF48: 5250000 | AG48: 95000 | AH48: 1712000 | AI48: 908000 | AJ48: 60000 | AK48: 87000 | AL48: 110000 | AM48: 4508000 | AN48: 10639000 | AO48: 19569000 | AP48: 17283000 | AQ48: 34825000 | AR48: 44854000 | AS48: 25854000 | AT48: 20579000 | AU48: 32669000 | AV48: 5078000 | AW48: 6269000 | AX48: 8390000 | AY48: 767000 | AZ48: 13071000 | BA48: 24206000 | BB48: 17419000 | BC48: 20582000 | BD48: 23309000 | BE48: 5709000 | BF48: 8383000 | BG48: 10571000 | BH48: 15392000 | BI48: 17213000 | BJ48: 13443000 | BK48: 16453000 | BL48: 76900000 | BM48: 186101000 | BN48: 110664000 | BO48: 113785000 | BP48: 156212000 | BQ48: =BP48-BO48 -> 42427000 | BR48: vnd
A49: Số giờ nghỉ không việc | B49: 0 | C49: 0 | D49: 0 | E49: 0 | F49: 0 | G49: 0 | H49: 0 | I49: 0 | J49: 0 | K49: 0 | L49: 0 | M49: 0 | N49: 0 | O49: 0 | P49: 0 | Q49: 0 | R49: 0 | S49: 0 | T49: 0 | U49: 0 | V49: 0 | W49: 0 | X49: 0 | Y49: 0 | Z49: 0 | AA49: 0 | AB49: 0 | AC49: 0 | AD49: 0 | AE49: 0 | AF49: 0 | AG49: 0 | AH49: 0 | AI49: 0 | AJ49: 0 | AK49: 0 | AL49: 0 | AM49: 2324 | AN49: 0 | AO49: 0 | AP49: 0 | AQ49: 0 | AR49: 0 | AS49: 0 | AT49: 0 | AU49: 0 | AV49: 0 | AW49: 0 | AX49: 0 | AY49: 1560 | AZ49: 0 | BA49: 0 | BB49: 0 | BC49: 0 | BD49: 0 | BE49: 0 | BF49: 0 | BG49: 0 | BH49: 0 | BI49: 0 | BJ49: 0 | BK49: 0 | BL49: 0 | BM49: 0 | BN49: 0 | BO49: 0 | BP49: 0 | BQ49: =BP49-BO49 -> 0
A50: Lương nghỉ không việc | B50: 0 | C50: 0 | D50: 0 | E50: 0 | F50: 0 | G50: 0 | H50: 0 | I50: 0 | J50: 0 | K50: 0 | L50: 0 | M50: 0 | N50: 0 | O50: 0 | P50: 0 | Q50: 0 | R50: 0 | S50: 0 | T50: 0 | U50: 0 | V50: 0 | W50: 0 | X50: 0 | Y50: 0 | Z50: 0 | AA50: 0 | AB50: 0 | AC50: 0 | AD50: 0 | AE50: 0 | AF50: 0 | AG50: 0 | AH50: 0 | AI50: 0 | AJ50: 0 | AK50: 0 | AL50: 0 | AM50: 55950300 | AN50: 0 | AO50: 0 | AP50: 0 | AQ50: 0 | AR50: 0 | AS50: 0 | AT50: 0 | AU50: 0 | AV50: 0 | AW50: 0 | AX50: 0 | AY50: 39804046 | AZ50: 0 | BA50: 0 | BB50: 0 | BC50: 0 | BD50: 0 | BE50: 0 | BF50: 0 | BG50: 0 | BH50: 0 | BI50: 0 | BJ50: 0 | BK50: 0 | BL50: 0 | BM50: 0 | BN50: 0 | BO50: 0 | BP50: 0 | BQ50: =BP50-BO50 -> 0 | BR50: vnd
A51: Lương làm thêm TO | B51: 0 | C51: 0 | D51: 0 | E51: 0 | F51: 0 | G51: 0 | H51: 0 | I51: 0 | J51: 0 | K51: 0 | L51: 0 | M51: 0 | N51: 0 | O51: 0 | P51: 0 | Q51: 0 | R51: 0 | S51: 0 | T51: 0 | U51: 0 | V51: 0 | W51: 0 | X51: 0 | Y51: 0 | Z51: 0 | AA51: 0 | AB51: 0 | AC51: 0 | AD51: 0 | AE51: 0 | AF51: 0 | AG51: 0 | AH51: 0 | AI51: 0 | AJ51: 0 | AK51: 0 | AL51: 0 | AM51: 0 | AN51: 0 | AO51: 0 | AP51: 0 | AQ51: 0 | AR51: 0 | AS51: 0 | AT51: 0 | AU51: 0 | AV51: 0 | AW51: 0 | AX51: 0 | AY51: 0 | AZ51: 0 | BA51: 0 | BB51: 0 | BC51: 0 | BD51: 0 | BE51: 0 | BF51: 0 | BG51: 0 | BH51: 0 | BI51: 0 | BJ51: 0 | BK51: 0 | BL51: 0 | BM51: 0 | BN51: 0 | BO51: 0 | BP51: 0 | BQ51: =BP51-BO51 -> 0
A52: Phụ cấp khác | B52: -4682615.4 | C52: -3178461.5 | D52: -5100000 | E52: 5849324.5 | F52: 5997750 | G52: 8462153.8 | H52: 3738797.5 | I52: 3.1372308e+08 | J52: 6.0197692e+08 | K52: 6.4320215e+08 | L52: 27793846 | M52: 5331539.2 | N52: 6497230.8 | O52: 78464000 | P52: -1515538.5 | Q52: 1802692.3 | R52: 3544428 | S52: 4001818.2 | T52: -2130000 | U52: 111458476 | V52: 55139231 | W52: 58507261 | X52: 56176924 | Y52: 52515385 | Z52: 66730770 | AA52: 1.4425932e+08 | AB52: 54517839 | AC52: 54961376 | AD52: 51536154 | AE52: 46585385 | AF52: 44962838 | AG52: 64909181 | AH52: 35670385 | AI52: 36579999 | AJ52: 620503669 | AK52: 523852050 | AL52: 14220000 | AM52: 74892143 | AN52: 31127558 | AO52: 56131095 | AP52: 88347319 | AQ52: 97131495 | AR52: 1.2591312e+08 | AS52: 15709217 | AT52: 8383024.5 | AU52: 3132859.8 | AV52: 2947376.7 | AW52: 2335384 | AX52: 48380958 | AY52: 27678227 | AZ52: 2343916.7 | BA52: 8966633 | BB52: 18252865 | BC52: 10267019 | BD52: 10843810 | BE52: 15608724 | BF52: 1.7891805e+08 | BG52: 78855338 | BH52: 94255976 | BI52: 91215798 | BJ52: 1.8627512e+08 | BK52: -97223.923 | BL52: 12436820 | BM52: -528355 | BN52: 25903834 | BO52: 20341723 | BP52: 53756141 | BQ52: =BP52-BO52 -> 33414419 | BR52: vnd
A53: Phí dịch vụ thời gian TO | B53: 0 | C53: 0 | D53: 0 | E53: 0 | F53: 0 | G53: 0 | H53: 0 | I53: 0 | J53: 0 | K53: 0 | L53: 0 | M53: 0 | N53: 0 | O53: 0 | P53: 0 | Q53: 0 | R53: 0 | S53: 0 | T53: 0 | U53: 0 | V53: 0 | W53: 0 | X53: 0 | Y53: 0 | Z53: 0 | AA53: 0 | AB53: 0 | AC53: 0 | AD53: 0 | AE53: 0 | AF53: 0 | AG53: 0 | AH53: 0 | AI53: 0 | AJ53: 0 | AK53: 0 | AL53: 0 | AM53: 0 | AN53: 0 | AO53: 0 | AP53: 0 | AQ53: 0 | AR53: 0 | AS53: 0 | AT53: 0 | AU53: 0 | AV53: 0 | AW53: 0 | AX53: 0 | AY53: 0 | AZ53: 0 | BA53: 0 | BB53: 0 | BC53: 0 | BD53: 0 | BE53: 0 | BF53: 0 | BG53: 0 | BH53: 0 | BI53: 0 | BJ53: 0 | BK53: 0 | BL53: 0 | BM53: 0 | BN53: 0 | BO53: 0 | BP53: 0 | BQ53: =BP53-BO53 -> 0
A54: ESD | B54: 6518400 | C54: 6405600 | D54: 5024400 | E54: 7549200 | F54: 7572000 | G54: 8106000 | H54: 7894800 | I54: 7594800 | J54: 6237600 | K54: 6712800 | L54: 5360400 | M54: 5402400 | N54: 6159600 | O54: 5751600 | P54: 5217600 | Q54: 6061200 | R54: 5535600 | S54: 5227200 | T54: 5596800 | U54: 5121600 | V54: 5696400 | W54: 5893200 | X54: 5142000 | Y54: 5408400 | Z54: 5246400 | AA54: 5792400 | AB54: 4671600 | AC54: 5318400 | AD54: 5058000 | AE54: 5086800 | AF54: 4249200 | AG54: 3212400 | AH54: 4009200 | AI54: 3369600 | AJ54: 2607600 | AK54: 1651200 | AL54: 1128000 | AM54: 1167600 | AN54: 2102400 | AO54: 2857200 | AP54: 3796800 | AQ54: 5320800 | AR54: 4792800 | AS54: 5293200 | AT54: 5238000 | AU54: 4807200 | AV54: 4700400 | AW54: 4245600 | AX54: 4388400 | AY54: 4704000 | AZ54: 3927600 | BA54: 4671600 | BB54: 5473200 | BC54: 5664000 | BD54: 5134800 | BE54: 5522400 | BF54: 4987200 | BG54: 5179200 | BH54: 5438400 | BI54: 5419200 | BJ54: 6146400 | BK54: 5666400 | BL54: 5790000 | BM54: 6463200 | BN54: 0 | BO54: 0 | BP54: 0 | BQ54: =BP54-BO54 -> 0 | BR54: vnd
A55: ESD OT | B55: 196800 | C55: 111600 | D55: 440400 | E55: 244800 | F55: 231600 | G55: 321600 | H55: 397200 | I55: 381600 | J55: 321600 | K55: 3600 | L55: 2602800 | M55: 2214000 | N55: 1729200 | O55: 826800 | P55: 1406400 | Q55: 2004000 | R55: 1161600 | S55: 1479600 | T55: 1642800 | U55: 820800 | V55: 1363200 | W55: 1712400 | X55: 1551600 | Y55: 1040400 | Z55: 778800 | AA55: 32400 | AB55: 1606800 | AC55: 938400 | AD55: 102000 | AE55: 388800 | AF55: 314400 | AG55: 6000 | AH55: 85200 | AI55: 40800 | AJ55: 3600 | AK55: 4800 | AL55: 6000 | AM55: 256800 | AN55: 559200 | AO55: 1106400 | AP55: 880800 | AQ55: 1731600 | AR55: 2467200 | AS55: 1443600 | AT55: 1138800 | AU55: 1572000 | AV55: 274800 | AW55: 348000 | AX55: 463200 | AY55: 39600 | AZ55: 728400 | BA55: 1318800 | BB55: 774000 | BC55: 1032000 | BD55: 1263600 | BE55: 301200 | BF55: 448800 | BG55: 361200 | BH55: 824400 | BI55: 913200 | BJ55: 606000 | BK55: 501600 | BL55: 168000 | BM55: 552000 | BN55: 0 | BO55: 0 | BP55: 0 | BQ55: =BP55-BO55 -> 0 | BR55: vnd
A56: Phí dịch vụ | B56: 59014498 | C56: 60093136 | D56: 53334967 | E56: 67070324 | F56: 71366912 | G56: 76292499 | H56: 74573357 | I56: 68829392 | J56: 59179931 | K56: 61536269 | L56: 66531827 | M56: 75736049 | N56: 80600555 | O56: 75986137 | P56: 71838347 | Q56: 76915512 | R56: 77657626 | S56: 69499669 | T56: 74448176 | U56: 72379006 | V56: 73613552 | W56: 76886999 | X56: 74408002 | Y56: 72553435 | Z56: 70404068 | AA56: 65724900 | AB56: 70363219 | AC56: 70318366 | AD56: 66918729 | AE56: 61063282 | AF56: 58261697 | AG56: 48963258 | AH56: 48479750 | AI56: 47834914 | AJ56: 39059580 | AK56: 20707500 | AL56: 16092688 | AM56: 15778909 | AN56: 25476405 | AO56: 40718793 | AP56: 50714790 | AQ56: 65482804 | AR56: 72686697 | AS56: 68776028 | AT56: 71495528 | AU56: 65569740 | AV56: 62368907 | AW56: 61597938 | AX56: 60577825 | AY56: 55306190 | AZ56: 56535531 | BA56: 66627448 | BB56: 70733995 | BC56: 75292700 | BD56: 75193084 | BE56: 74190373 | BF56: 71930709 | BG56: 67992304 | BH56: 73788958 | BI56: 83588758 | BJ56: 94652302 | BK56: 90012343 | BL56: 83347729 | BM56: 98130176 | BN56: 1.0766047e+08 | BO56: 1.2355748e+08 | BP56: 1.3401662e+08 | BQ56: =BP56-BO56 -> 10459139 | BR56: vnd
A57: Phí dịch vụ OT | B57: 16163135 | C57: 9172971 | D57: 10088726 | E57: 22396000 | F57: 18397282 | G57: 22916124 | H57: 24071786 | I57: 19317327 | J57: 21581412 | K57: 37017092 | L57: 19688635 | M57: 22896165 | N57: 20043004 | O57: 9465470 | P57: 16485814 | Q57: 25597857 | R57: 15970737 | S57: 20350123 | T57: 21583336 | U57: 10735384 | V57: 18048261 | W57: 23178619 | X57: 20362518 | Y57: 13791077 | Z57: 10302987 | AA57: 1199002 | AB57: 20925944 | AC57: 12164286 | AD57: 1358126 | AE57: 5589127 | AF57: 4144189.5 | AG57: 88001 | AH57: 1191094 | AI57: 583000 | AJ57: 49500 | AK57: 66000 | AL57: 86563 | AM57: 3459844 | AN57: 7907188.2 | AO57: 14960410 | AP57: 12505628 | AQ57: 24509660 | AR57: 33822193 | AS57: 19476979 | AT57: 15393594 | AU57: 22539283 | AV57: 3804970 | AW57: 4812407 | AX57: 6380844.5 | AY57: 560719 | AZ57: 9983095 | BA57: 18068657 | BB57: 11470345 | BC57: 14372346 | BD57: 17324281 | BE57: 4231470 | BF57: 6206469 | BG57: 5878314 | BH57: 11392689 | BI57: 12931077 | BJ57: 9685953.9 | BK57: 9299127.4 | BL57: 11247611 | BM57: 29664164 | BN57: 20878125 | BO57: 21463958 | BP57: 29568717 | BQ57: =BP57-BO57 -> 8104759.6 | BR57: vnd
A58: Bù-trừ ESD | B58: 0 | C58: 48800 | D58: 0 | E58: 0 | F58: 0 | G58: 0 | H58: 0 | I58: 0 | J58: 0 | K58: 0 | L58: 0 | M58: 0 | N58: 0 | O58: 0 | P58: 0 | Q58: 0 | R58: 0 | S58: 0 | T58: 0 | U58: 0 | V58: 0 | W58: 0 | X58: 0 | Y58: 0 | Z58: 0 | AA58: 0 | AB58: 0 | AC58: 0 | AD58: 0 | AE58: 0 | AF58: 0 | AG58: 0 | AH58: 0 | AI58: 0 | AJ58: 0 | AK58: 0 | AL58: 0 | AM58: 0 | AN58: 0 | AO58: 0 | AP58: 0 | AQ58: 0 | AR58: 0 | AS58: 0 | AT58: 0 | AU58: 0 | AV58: 0 | AW58: 0 | AX58: 0 | AY58: 0 | AZ58: 0 | BA58: 0 | BB58: 0 | BC58: 0 | BD58: 0 | BE58: 0 | BF58: 0 | BG58: 0 | BH58: 0 | BI58: 0 | BJ58: 0 | BK58: 0 | BL58: 0 | BM58: 0 | BN58: 0 | BO58: 0 | BP58: 0 | BQ58: =BP58-BO58 -> 0 | BR58: vnd
A59: Bù-trừ lương tháng trước | B59: 11222596 | C59: 3113076.9 | D59: 426983.17 | E59: 5592788.5 | F59: 9411057.7 | G59: 1338221.2 | H59: 11250000 | I59: 7297215.5 | J59: 5333653.8 | K59: 233978000 | L59: 13913301 | M59: 2019230.8 | N59: 1.1158592e+08 | O59: 13267133 | P59: 0 | Q59: 1200000 | R59: 17697115 | S59: 11433217 | T59: 2.8053418e+08 | U59: 5343750 | V59: 3469614 | W59: 7209616 | X59: 1736250 | Y59: 175000 | Z59: 300000 | AA59: 750000 | AB59: 0 | AC59: 5612500 | AD59: 8484134 | AE59: 525000 | AF59: 79989784 | AG59: 462993 | AH59: 0 | AI59: 0 | AJ59: 325000 | AK59: 1320000 | AL59: 325000 | AM59: 0 | AN59: 925000 | AO59: 500000 | AP59: 650000 | AQ59: 1875000 | AR59: 2225000 | AS59: 0 | AT59: 1523076.9 | AU59: 1120673.1 | AV59: 4482692.5 | AW59: 93392.923 | AX59: 320204.37 | AY59: 1408845.7 | AZ59: 0 | BA59: 0 | BB59: 835961.54 | BC59: 1440865.4 | BD59: 987259 | BE59: 5389379.4 | BF59: 693750 | BG59: 346875 | BH59: 0 | BI59: 827163.46 | BJ59: 960576.92 | BK59: 0 | BL59: 1900481 | BM59: 1084616 | BN59: 283654 | BO59: 2559975 | BP59: 1616827 | BQ59: =BP59-BO59 -> -943148 | BR59: vnd
A60: BHXH, BHYT, BHTN&BNN (NSDLĐ) | B60: 190339500 | C60: 222331500 | D60: 206496750 | E60: 209786250 | F60: 264525250 | G60: 261880750 | H60: 287863500 | I60: 261114000 | J60: 221917500 | K60: 212436000 | L60: 226320000 | M60: 247320000 | N60: 279320000 | O60: 294840000 | P60: 268750000 | Q60: 259827000 | R60: 294127000 | S60: 2.6943e+08 | T60: 2.8019e+08 | U60: 2.86098e+08 | V60: 2.819775e+08 | W60: 3.032975e+08 | X60: 306791025 | Y60: 296729025 | Z60: 292310775 | AA60: 287838775 | AB60: 271985750 | AC60: 287637750 | AD60: 274221750 | AE60: 246228750 | AF60: 245110750 | AG60: 196531500 | AH60: 195413500 | AI60: 188830845 | AJ60: 159970750 | AK60: 65865250 | AL60: 64747250 | AM60: 64725750 | AN60: 94911750 | AO60: 142985750 | AP60: 206711750 | AQ60: 246959750 | AR60: 297871750 | AS60: 298129750 | AT60: 313878500 | AU60: 286100500 | AV60: 274168000 | AW60: 265793750 | AX60: 262235500 | AY60: 257150750 | AZ60: 248776500 | BA60: 272093250 | BB60: 302451250 | BC60: 334174500 | BD60: 307761750 | BE60: 321532500 | BF60: 311965000 | BG60: 297409500 | BH60: 326273250 | BI60: 355029500 | BJ60: 415455250 | BK60: 420421750 | BL60: 415831500 | BM60: 442448500 | BN60: 383044000 | BO60: 439890000 | BP60: 477084500 | BQ60: =BP60-BO60 -> 37194500 | BR60: vnd
A61: BHXH, BHYT, BHTN&BNN (NLĐ) | B61: 93172500 | C61: 108580500 | D61: 100847250 | E61: 102453750 | F61: 129186750 | G61: 127895250 | H61: 140584500 | I61: 130557000 | J61: 110958750 | K61: 106218000 | L61: 118818000 | M61: 129843000 | N61: 146643000 | O61: 154791000 | P61: 141093750 | Q61: 136409175 | R61: 154416675 | S61: 1.4145075e+08 | T61: 1.4709975e+08 | U61: 1.46538e+08 | V61: 1.444275e+08 | W61: 1.553475e+08 | X61: 149828175 | Y61: 144914175 | Z61: 142756425 | AA61: 140572425 | AB61: 132830250 | AC61: 140474250 | AD61: 133922250 | AE61: 120251250 | AF61: 119705250 | AG61: 95980500 | AH61: 95434500 | AI61: 92219715 | AJ61: 78125250 | AK61: 32166750 | AL61: 31620750 | AM61: 31610250 | AN61: 46352250 | AO61: 69830250 | AP61: 100952250 | AQ61: 120608250 | AR61: 145472250 | AS61: 145598250 | AT61: 153289500 | AU61: 139723500 | AV61: 133896000 | AW61: 129806250 | AX61: 128068500 | AY61: 125585250 | AZ61: 121495500 | BA61: 132882750 | BB61: 147708750 | BC61: 163201500 | BD61: 150302250 | BE61: 157027500 | BF61: 152355000 | BG61: 145246500 | BH61: 159342750 | BI61: 173386500 | BJ61: 202896750 | BK61: 205322250 | BL61: 203080500 | BM61: 216079500 | BN61: 187068000 | BO61: 214830000 | BP61: 232348500 | BQ61: =BP61-BO61 -> 17518500 | BR61: vnd
A62: Ma chay cưới hỏi (giờ) | B62: 77.5 | C62: 40 | D62: 40 | E62: 40 | F62: 24 | G62: 32 | H62: 0 | I62: 0 | J62: 8 | K62: 0 | L62: 24 | M62: 0 | N62: 24 | O62: 12 | P62: 12 | Q62: 36 | R62: 84 | S62: 36 | T62: 144 | U62: 24 | V62: 84 | W62: 180 | X62: 36 | Y62: 48 | Z62: 156 | AA62: 0 | AB62: 0 | AC62: 24 | AD62: 84 | AE62: 96 | AF62: 24 | AG62: 12 | AH62: 144 | AI62: 0 | AJ62: 60 | AK62: 0 | AL62: 12 | AM62: 84 | AN62: 12 | AO62: 0 | AP62: 12 | AQ62: 48 | AR62: 24 | AS62: 48 | AT62: 108 | AU62: 48 | AV62: 0 | AW62: 48 | AX62: 60 | AY62: 108 | AZ62: 36 | BA62: 48 | BB62: 72 | BC62: 8 | BD62: 72 | BE62: 36 | BF62: 108 | BG62: 12 | BH62: 0 | BI62: 0 | BJ62: 60 | BK62: 0 | BL62: 28 | BM62: 0 | BN62: 26 | BO62: 28 | BP62: 20 | BQ62: =BP62-BO62 -> -8 | BR62: hours
A63: Ma chay cưới hỏi | B63: 1803846.2 | C63: 942307.69 | D63: 965384.62 | E63: 980769.23 | F63: 588461.54 | G63: 769230.77 | H63: 0 | I63: 0 | J63: 192307.69 | K63: 0 | L63: 576923.08 | M63: 0 | N63: 576923.08 | O63: 308653.85 | P63: 300000 | Q63: 900000 | R63: 2160576.9 | S63: 900000 | T63: 3617307.7 | U63: 605769.23 | V63: 2333653.8 | W63: 4500000 | X63: 900000 | Y63: 1200000 | Z63: 3900000 | AA63: 0 | AB63: 0 | AC63: 600000 | AD63: 2134615.4 | AE63: 2400000 | AF63: 600000 | AG63: 300000 | AH63: 3600000 | AI63: 0 | AJ63: 1500000 | AK63: 0 | AL63: 300000 | AM63: 2100000 | AN63: 300000 | AO63: 0 | AP63: 300000 | AQ63: 1225961.5 | AR63: 600000 | AS63: 1298076.9 | AT63: 2893269.2 | AU63: 1280769.2 | AV63: 0 | AW63: 1298076.9 | AX63: 1606730.8 | AY63: 2881730.8 | AZ63: 975000 | BA63: 1298076.9 | BB63: 1921153.8 | BC63: 213461.54 | BD63: 1921153.8 | BE63: 960576.92 | BF63: 2899038.5 | BG63: 320192.31 | BH63: 0 | BI63: 0 | BJ63: 1600961.5 | BK63: 0 | BL63: 794230.77 | BM63: 0 | BN63: 737500 | BO63: 794230.77 | BP63: 567307.69 | BQ63: =BP63-BO63 -> -226923.08 | BR63: vnd
A64: Phép năm nhân viên đã sử dụng (giờ) | B64: 513.25 | C64: 515 | D64: 1626.25 | E64: 622 | F64: 1026.5 | G64: 854.5 | H64: 726.5 | I64: 841.75 | J64: 204.5 | K64: 116.75 | L64: 2025 | M64: 1111.5 | N64: 1673.25 | O64: 2859.5 | P64: 4732 | Q64: 1199.25 | R64: 2241.5 | S64: 1500.75 | T64: 1303.75 | U64: 1428.75 | V64: 1476.25 | W64: 1436.5 | X64: 997.75 | Y64: 1270.75 | Z64: 1538 | AA64: 7608.5 | AB64: 476.25 | AC64: 760.25 | AD64: 1419.5 | AE64: 1312.5 | AF64: 1632.75 | AG64: 1109.5 | AH64: 1147 | AI64: 544.25 | AJ64: 833.75 | AK64: 681 | AL64: 773.75 | AM64: 392.25 | AN64: 777.25 | AO64: 221.5 | AP64: 318.25 | AQ64: 406 | AR64: 449.5 | AS64: 639.5 | AT64: 736.5 | AU64: 1393.5 | AV64: 1266.5 | AW64: 866.75 | AX64: 1973 | AY64: 1782.5 | AZ64: 4768.75 | BA64: 410.5 | BB64: 686.25 | BC64: 1522.25 | BD64: 1180.25 | BE64: 1116 | BF64: 722.25 | BG64: 1810 | BH64: 908.25 | BI64: 1065.25 | BJ64: 1207.5 | BK64: 954 | BL64: 7125.25 | BM64: 656.5 | BN64: 786.25 | BO64: 1200.25 | BP64: 944.25 | BQ64: =BP64-BO64 -> -256 | BR64: hours
A65: Phép năm nhân viên đã sử dụng | B65: 12117909 | C65: 12588161 | D65: 39567308 | E65: 15539904 | F65: 25316046 | G65: 20844471 | H65: 17823197 | I65: 20490084 | J65: 4943269.2 | K65: 2985336.5 | L65: 49050000 | M65: 27197656 | N65: 40975841 | O65: 72437440 | P65: 1.1927404e+08 | Q65: 30371514 | R65: 56715745 | S65: 37784026 | T65: 33138629 | U65: 36262824 | V65: 37455841 | W65: 36354332 | X65: 25089724 | Y65: 32248678 | Z65: 38874591 | AA65: 1.9102899e+08 | AB65: 12004447 | AC65: 19179507 | AD65: 35683534 | AE65: 32940625 | AF65: 41071274 | AG65: 28024880 | AH65: 28823918 | AI65: 13677284 | AJ65: 20968510 | AK65: 17198798 | AL65: 19543389 | AM65: 10058894 | AN65: 19643570 | AO65: 5561778.8 | AP65: 8203004.8 | AQ65: 10250841 | AR65: 11354928 | AS65: 17297716 | AT65: 19801502 | AU65: 37491406 | AV65: 34093750 | AW65: 23251743 | AX65: 52916406 | AY65: 47789483 | AZ65: 1.2802734e+08 | BA65: 11135637 | BB65: 18402644 | BC65: 41038522 | BD65: 32730228 | BE65: 30057091 | BF65: 19729868 | BG65: 49262440 | BH65: 24431671 | BI65: 28799579 | BJ65: 33338401 | BK65: 26775300 | BL65: 2.0724603e+08 | BM65: 21389063 | BN65: 25489062 | BO65: 35879567 | BP65: 28527644 | BQ65: =BP65-BO65 -> -7351923.1 | BR65: vnd
... A67: Phép năm còn lại | B67: 21230.77 | C67: 1033802.9 | D67: 9360598.6 | E67: 5628204 | F67: 14933408 | G67: 12996178 | H67: 2694228 | I67: 31050086 | J67: 32508301 | K67: 2519229 | L67: 10489657 | M67: 12926675 | N67: 5901920 | O67: 7107500 | P67: 10425601 | Q67: 6648608 | R67: 5991801 | S67: 6573282 | T67: 6547999 | U67: 63376917 | V67: 3355997 | W67: 7046278 | X67: 7086497 | Y67: 6723061 | Z67: 804499 | AA67: 1596064.4 | AB67: 3292498 | AC67: 4696553 | AD67: 14016692 | AE67: 811749 | AF67: 25811408 | AG67: 1541339 | AH67: 555177 | AI67: 4354495 | AJ67: 51296266 | AK67: 48194584 | AL67: 319274 | AM67: 0 | AN67: 1917998 | AO67: 303000 | AP67: 514499 | AQ67: 1740999 | AR67: 2323818 | AS67: 5106475 | AT67: 16586881 | AU67: 5001666 | AV67: 3669626 | AW67: 1729036 | AX67: 2958531 | AY67: 454406.25 | AZ67: 2384842 | BA67: 4239075 | BB67: 1883261 | BC67: 10774294 | BD67: 9266801 | BE67: 2892134 | BF67: 8303834 | BG67: 7587955 | BH67: 1461943 | BI67: 19524294 | BJ67: 26401030 | BK67: 4727411.1 | BL67: 13578783 | BM67: 114194280 | BN67: 5248424 | BO67: 12297189 | BP67: 16208795 | BQ67: =BP67-BO67 -> 3911606 | BR67: vnd
A68: Tổng chi phí phải trả cho NCC | B68: 2.3151999e+09 | C68: 2.0986515e+09 | D68: 1.9008524e+09 | E68: 2.9162007e+09 | F68: 2.8390964e+09 | G68: 3.1780981e+09 | H68: 3.322688e+09 | I68: 3.1019262e+09 | J68: 3.378125e+09 | K68: 4.4218316e+09 | L68: 2.9834205e+09 | M68: 3.4170697e+09 | N68: 3.6984456e+09 | O68: 3.0067675e+09 | P68: 2.9031138e+09 | Q68: 3.717708e+09 | R68: 3.1637836e+09 | S68: 3.2410612e+09 | T68: 3.7992663e+09 | U68: 3.0374593e+09 | V68: 3.2644781e+09 | W68: 3.7074844e+09 | X68: 3.432903e+09 | Y68: 3.1071311e+09 | Z68: 2.9860541e+09 | AA68: 2.2022281e+09 | AB68: 3.2450968e+09 | AC68: 3.0551722e+09 | AD68: 2.2654723e+09 | AE68: 2.2350685e+09 | AF68: 2362947058 | AG68: 1618435738 | AH68: 1687525290 | AI68: 1653282090 | AJ68: 1924332765 | AK68: 1238643555 | AL68: 552905582 | AM68: 777416172 | AN68: 1113614410 | AO68: 2025188733 | AP68: 2237423199 | AQ68: 3271681168 | AR68: 4123245457 | AS68: 3343975132 | AT68: 3268364708 | AU68: 3388566477 | AV68: 2362243766 | AW68: 2334754482 | AX68: 2554457286 | AY68: 1935476192 | AZ68: 2340235265 | BA68: 3233404316 | BB68: 2948983606 | BC68: 3290716275 | BD68: 3528483977 | BE68: 2819339052 | BF68: 2989277793 | BG68: 2769823344 | BH68: 3263128570 | BI68: 3723560130 | BJ68: 4.1579569e+09 | BK68: 3817957946 | BL68: 3565406438 | BM68: 5229386403 | BN68: 3771835924 | BO68: 4.3194807e+09 | BP68: 5.1046923e+09 | BQ68: =BP68-BO68 -> 7.8521153e+08 | BR68: vnd | BW68: =BQ68/BO68 -> 0.18178378
A69: Nhân viên thực lãnh | B69: 1955863000 | C69: 1699654000 | D69: 1550047000 | E69: 2518261000 | F69: 2368535000 | G69: 2680680000 | H69: 2787305000 | I69: 2614132000 | J69: 2957921000 | K69: 3997913000 | L69: 2544099000 | M69: 2933701000 | N69: 3163990000 | O69: 2465063000 | P69: 2398287000 | Q69: 3210972000 | R69: 2614901000 | S69: 2733584000 | T69: 3268708000 | U69: 2515714000 | V69: 2739313000 | W69: 3141138000 | X69: 2874780000 | Y69: 2572654000 | Z69: 2464214000 | AA69: 1701062000 | AB69: 2742665000 | AC69: 2538287000 | AD69: 1783885000 | AE69: 1796456000 | AF69: 1930256000 | AG69: 1273614000 | AH69: 1342902000 | AI69: 1320365000 | AJ69: 1644492000 | AK69: 1118172000 | AL69: 439210000 | AM69: 657219000 | AN69: 937044000 | AO69: 1752719000 | AP69: 1861836000 | AQ69: 2807330000 | AR69: 3566103000 | AS69: 2805255000 | AT69: 2707936000 | AU69: 2868254000 | AV69: 1883033000 | AW69: 1868156000 | AX69: 2092336000 | AY69: 1489972000 | AZ69: 1898784000 | BA69: 2737743000 | BB69: 2410366000 | BC69: 2696981000 | BD69: 2974085000 | BE69: 2255783000 | BF69: 2441376000 | BG69: 2247764000 | BH69: 2681270000 | BI69: 3085845000 | BJ69: 3414608000 | BK69: 3062433000 | BL69: 2833770000 | BM69: 4417904576 | BN69: 3025099472 | BO69: 3467075806 | BP69: 4.1125179e+09 | BQ69: =BP69-BO69 -> 6.4544213e+08 | BR69: vnd | BW69: =BQ69/BO69 -> 0.18616326

Sheet Oct21 vs.Sep21
A1: Month | B1: Count | C1: DepartmentCode | D1: EmployeeID | E1: Global code | F1: FullName | I1: CostCenter | J1: Working hour | K1: Lương cơ bản | L1: Số ngày công chuẩn | M1: Số giờ công chuẩn | N1: Số ngày làm việc được trả lương | O1: Số giờ làm việc được trả lương | P1: Overtime 150% (hour) | Q1: Overtime 175% (hour) | R1: Overtime 200% (hour) | S1: Overtime 210% (hour) | U1: Overtime 270% (hour) | W1: Overtime 390% (hour) | X1: Overtime 100% (hour) | Y1: Night shift (day) | Z1: Day Off | AA1: Số giờ làm thêm T.O | AB1: Lương tháng 12-2020 | AC1: Overtime 150% (vnd) | AD1: Overtime 175% (vnd) | AE1: Overtime 200% (vnd) | AF1: Overtime 210% (vnd) | AH1: Overtime 270% (vnd) | AJ1: Overtime 390% (hour) | AK1: Overtime 100% (vnd) | AL1: Night allowance (vnd) | AM1: Phụ cấp đi lại | AN1: Phụ cấp nhà ở | AO1: Thưởng hiệu suất | AP1: NVXS&TB tháng | AQ1: Thưởng TRP | AR1: Thưởng quý 4-2020 | AS1: Lương tháng 13 | AT1: Thưởng ca ngày (12h) | AU1: Thưởng ca đêm (12h) | AV1: Ca 2 | AW1: P/c ca 2 | AX1: Ca 3 | AY1: P/c ca 3 | BD1: Sat/Sun transportation | BG1: P/c bữa ăn ca chính 10-2020 | BH1: P/c bữa ăn OT 10-2020 | BI1: Số ngày nghỉ không việc | BJ1: Lương nghỉ không việc | BK1: Lương làm thêm TO | BL1: Phụ cấp khác | BM1: Phí dịch vụ thời gian TO | BN1: ESD | BO1: ESD OT | BP1: Phí dịch vụ | BQ1: Phí dịch vụ OT | BR1: Bù-trừ ESD | BS1: Bù-trừ (11-2020) | BT1: BHXH, BHYT, BHTN&BNN (NSDLĐ) | BU1: BHXH, BHYT, BHTN&BNN (NLĐ) | BV1: Ma chay cưới hỏi (giờ) | BW1: Ma chay cưới hỏi | BX1: Phép năm nhân viên đã sử dụng (giờ) | BY1: Phép năm nhân viên đã sử dụng | BZ1: Phép năm còn lại (giờ) | CA1: Phép năm còn lại | CB1: Tổng chi phí phải trả cho NCC | CC1: Nhân viên thực lãnh | CD1: Notes | CE1: Agency
K2: 2755200000 | L2: 0 | M2: 94224 | N2: 0 | O2: 70177.715 | P2: 11557.75 | Q2: 0 | R2: 3387.75 | S2: 0 | T2: 0 | U2: 616 | V2: 0 | W2: 0 | X2: 0 | Y2: 2190.3683 | Z2: 363 | AA2: 0 | AB2: 2.0543648e+09 | AC2: 4.9316481e+08 | AD2: 0 | AE2: 1.9483149e+08 | AF2: 0 | AG2: 0 | AH2: 50671923 | AI2: 0 | AJ2: 0 | AK2: 0 | AL2: 1.4911353e+08 | AM2: 1.1063146e+08 | AN2: 55243028 | AO2: 169846362 | AP2: 1110000 | AQ2: 2.6111093e+08 | AR2: 83317235 | AS2: 0 | AT2: 0 | AU2: 1.6153966e+08 | AV2: 0 | AW2: 0 | AX2: 492.7478 | AY2: 55907923 | AZ2: 0 | BA2: 0 | BB2: 5743 | BC2: 1.629024e+08 | BD2: 10980000 | BE2: 12002864 | BF2: 41450000 | BG2: 48878000 | BH2: 156212000 | BI2: 0 | BJ2: 0 | BK2: 0 | BL2: 53756141 | BM2: 0 | BN2: 0 | BO2: 0 | BP2: 1.3401662e+08 | BQ2: 29568717 | BR2: 0 | BS2: 1616827 | BT2: 477084500 | BU2: 232348500 | BV2: 20 | BW2: 567307.69 | BX2: 944.25 | BY2: 28527644 | BZ2: 499.83 | CA2: 16208795 | CB2: 5.1046923e+09 | CC2: 4.1125179e+09 | CD2: 0 | CE2: 0 | CH2: 0 | CI2: 34994000 | CJ2: 84162000 | CK2: 0 | CL2: 2.4774734e+08

Sheet June
D1: Còn làm việc | F1: Mới gia nhập | H1: Nghỉ việc | J1: Tổng nhân viên thời vụ
A2: Agency | B2: DepartmentCode | C2: CostCenter | D2: Tổng chi phí phải trả cho NCC | E2: Số lượng NV | F2: Tổng chi phí phải trả cho NCC | G2: Số lượng NV | H2: Tổng chi phí phải trả cho NCC | I2: Số lượng NV | J2: Tổng chi phí phải trả cho NCC | K2: Số lượng NV
A3: MEKONG SUBLABOR | B3: LG | C3: VN1006 | D3: =SUMIFS('06-2026'!$CB$7:$CB$463,'06-2026'!$C$7:$C$463,$B3,'06-2026'!$A$7:$A$463,"Out",'06-2026'!$I$7:$I$463,$C3,'06-2026'!$CE$7:$CE$463,$A3) -> 0 | E3: =COUNTIFS('06-2026'!$C$7:$C$463,$B3,'06-2026'!$A$7:$A$463,"Out",'06-2026'!$I$7:$I$463,$C3,'06-2026'!$CE$7:$CE$463,$A3) -> 0 | F3: =SUMIFS('06-2026'!$CB$7:$CB$463,'06-2026'!$C$7:$C$463,$B3,'06-2026'!$A$7:$A$463,"Out-New",'06-2026'!$I$7:$I$463,$C3,'06-2026'!$CE$7:$CE$463,$A3) -> 0 | G3: =COUNTIFS('06-2026'!$C$7:$C$463,$B3,'06-2026'!$A$7:$A$463,"Out-New",'06-2026'!$I$7:$I$463,$C3,'06-2026'!$CE$7:$CE$463,$A3) -> 0 | H3: =SUMIFS('06-2026'!$CB$7:$CB$463,'06-2026'!$C$7:$C$463,$B3,'06-2026'!$A$7:$A$463,"Termination",'06-2026'!$I$7:$I$463,$C3,'06-2026'!$CE$7:$CE$463,$A3) -> 16202924 | I3: =COUNTIFS('06-2026'!$C$7:$C$463,$B3,'06-2026'!$A$7:$A$463,"Termination",'06-2026'!$I$7:$I$463,$C3,'06-2026'!$CE$7:$CE$463,$A3) -> 1 | J3: =SUM(D3,F3,H3) -> 16202924 | K3: =SUM(E3,G3,I3) -> 1
A4: =A3 -> MEKONG SUBLABOR | B4: PL | C4: VN1033 | D4: =SUMIFS('06-2026'!$CB$7:$CB$463,'06-2026'!$C$7:$C$463,$B4,'06-2026'!$A$7:$A$463,"Out",'06-2026'!$I$7:$I$463,$C4,'06-2026'!$CE$7:$CE$463,$A4) -> 17498466 | E4: =COUNTIFS('06-2026'!$C$7:$C$463,$B4,'06-2026'!$A$7:$A$463,"Out",'06-2026'!$I$7:$I$463,$C4,'06-2026'!$CE$7:$CE$463,$A4) -> 1 | F4: =SUMIFS('06-2026'!$CB$7:$CB$463,'06-2026'!$C$7:$C$463,$B4,'06-2026'!$A$7:$A$463,"Out-New",'06-2026'!$I$7:$I$463,$C4,'06-2026'!$CE$7:$CE$463,$A4) -> 0 | G4: =COUNTIFS('06-2026'!$C$7:$C$463,$B4,'06-2026'!$A$7:$A$463,"Out-New",'06-2026'!$I$7:$I$463,$C4,'06-2026'!$CE$7:$CE$463,$A4) -> 0 | H4: =SUMIFS('06-2026'!$CB$7:$CB$463,'06-2026'!$C$7:$C$463,$B4,'06-2026'!$A$7:$A$463,"Termination",'06-2026'!$I$7:$I$463,$C4,'06-2026'!$CE$7:$CE$463,$A4) -> 0 | I4: =COUNTIFS('06-2026'!$C$7:$C$463,$B4,'06-2026'!$A$7:$A$463,"Termination",'06-2026'!$I$7:$I$463,$C4,'06-2026'!$CE$7:$CE$463,$A4) -> 0 | J4: =SUM(D4,F4,H4) -> 17498466 | K4: =SUM(E4,G4,I4) -> 1
A5: =A4 -> MEKONG SUBLABOR | B5: LG | C5: VN1042 | D5: =SUMIFS('06-2026'!$CB$7:$CB$463,'06-2026'!$C$7:$C$463,$B5,'06-2026'!$A$7:$A$463,"Out",'06-2026'!$I$7:$I$463,$C5,'06-2026'!$CE$7:$CE$463,$A5) -> 73950375 | E5: =COUNTIFS('06-2026'!$C$7:$C$463,$B5,'06-2026'!$A$7:$A$463,"Out",'06-2026'!$I$7:$I$463,$C5,'06-2026'!$CE$7:$CE$463,$A5) -> 6 | F5: =SUMIFS('06-2026'!$CB$7:$CB$463,'06-2026'!$C$7:$C$463,$B5,'06-2026'!$A$7:$A$463,"Out-New",'06-2026'!$I$7:$I$463,$C5,'06-2026'!$CE$7:$CE$463,$A5) -> 0 | G5: =COUNTIFS('06-2026'!$C$7:$C$463,$B5,'06-2026'!$A$7:$A$463,"Out-New",'06-2026'!$I$7:$I$463,$C5,'06-2026'!$CE$7:$CE$463,$A5) -> 0 | H5: =SUMIFS('06-2026'!$CB$7:$CB$463,'06-2026'!$C$7:$C$463,$B5,'06-2026'!$A$7:$A$463,"Termination",'06-2026'!$I$7:$I$463,$C5,'06-2026'!$CE$7:$CE$463,$A5) -> 3896830 | I5: =COUNTIFS('06-2026'!$C$7:$C$463,$B5,'06-2026'!$A$7:$A$463,"Termination",'06-2026'!$I$7:$I$463,$C5,'06-2026'!$CE$7:$CE$463,$A5) -> 2 | J5: =SUM(D5,F5,H5) -> 77847205 | K5: =SUM(E5,G5,I5) -> 8
A6: =A5 -> MEKONG SUBLABOR | B6: LG Total | D6: =SUM(D3:D5) -> 91448841 | E6: =SUM(E3:E5) -> 7 | F6: =SUM(F3:F5) -> 0 | G6: =SUM(G3:G5) -> 0 | H6: =SUM(H3:H5) -> 20099754 | I6: =SUM(I3:I5) -> 3 | J6: =SUM(J3:J5) -> 111548595 | K6: =SUM(K3:K5) -> 10
A7: =A6 -> MEKONG SUBLABOR | B7: ME | C7: VN1002 | D7: =SUMIFS('06-2026'!$CB$7:$CB$463,'06-2026'!$C$7:$C$463,$B7,'06-2026'!$A$7:$A$463,"Out",'06-2026'!$I$7:$I$463,$C7,'06-2026'!$CE$7:$CE$463,$A7) -> 0 | E7: =COUNTIFS('06-2026'!$C$7:$C$463,$B7,'06-2026'!$A$7:$A$463,"Out",'06-2026'!$I$7:$I$463,$C7,'06-2026'!$CE$7:$CE$463,$A7) -> 0 | F7: =SUMIFS('06-2026'!$CB$7:$CB$463,'06-2026'!$C$7:$C$463,$B7,'06-2026'!$A$7:$A$463,"Out-New",'06-2026'!$I$7:$I$463,$C7,'06-2026'!$CE$7:$CE$463,$A7) -> 0 | G7: =COUNTIFS('06-2026'!$C$7:$C$463,$B7,'06-2026'!$A$7:$A$463,"Out-New",'06-2026'!$I$7:$I$463,$C7,'06-2026'!$CE$7:$CE$463,$A7) -> 0 | H7: =SUMIFS('06-2026'!$CB$7:$CB$463,'06-2026'!$C$7:$C$463,$B7,'06-2026'!$A$7:$A$463,"Termination",'06-2026'!$I$7:$I$463,$C7,'06-2026'!$CE$7:$CE$463,$A7) -> 0 | I7: =COUNTIFS('06-2026'!$C$7:$C$463,$B7,'06-2026'!$A$7:$A$463,"Termination",'06-2026'!$I$7:$I$463,$C7,'06-2026'!$CE$7:$CE$463,$A7) -> 0 | J7: =SUM(D7,F7,H7) -> 0 | K7: =SUM(E7,G7,I7) -> 0
A8: =A7 -> MEKONG SUBLABOR | B8: =B7 -> ME | C8: VN1006 | D8: =SUMIFS('06-2026'!$CB$7:$CB$463,'06-2026'!$C$7:$C$463,$B8,'06-2026'!$A$7:$A$463,"Out",'06-2026'!$I$7:$I$463,$C8,'06-2026'!$CE$7:$CE$463,$A8) -> 0 | E8: =COUNTIFS('06-2026'!$C$7:$C$463,$B8,'06-2026'!$A$7:$A$463,"Out",'06-2026'!$I$7:$I$463,$C8,'06-2026'!$CE$7:$CE$463,$A8) -> 0 | F8: =SUMIFS('06-2026'!$CB$7:$CB$463,'06-2026'!$C$7:$C$463,$B8,'06-2026'!$A$7:$A$463,"Out-New",'06-2026'!$I$7:$I$463,$C8,'06-2026'!$CE$7:$CE$463,$A8) -> 0 | G8: =COUNTIFS('06-2026'!$C$7:$C$463,$B8,'06-2026'!$A$7:$A$463,"Out-New",'06-2026'!$I$7:$I$463,$C8,'06-2026'!$CE$7:$CE$463,$A8) -> 0 | H8: =SUMIFS('06-2026'!$CB$7:$CB$463,'06-2026'!$C$7:$C$463,$B8,'06-2026'!$A$7:$A$463,"Termination",'06-2026'!$I$7:$I$463,$C8,'06-2026'!$CE$7:$CE$463,$A8) -> 0 | I8: =COUNTIFS('06-2026'!$C$7:$C$463,$B8,'06-2026'!$A$7:$A$463,"Termination",'06-2026'!$I$7:$I$463,$C8,'06-2026'!$CE$7:$CE$463,$A8) -> 0 | J8: =SUM(D8,F8,H8) -> 0 | K8: =SUM(E8,G8,I8) -> 0
A9: =A8 -> MEKONG SUBLABOR | B9: =B8 -> ME | C9: VN1021 | D9: =SUMIFS('06-2026'!$CB$7:$CB$463,'06-2026'!$C$7:$C$463,$B9,'06-2026'!$A$7:$A$463,"Out",'06-2026'!$I$7:$I$463,$C9,'06-2026'!$CE$7:$CE$463,$A9) -> 0 | E9: =COUNTIFS('06-2026'!$C$7:$C$463,$B9,'06-2026'!$A$7:$A$463,"Out",'06-2026'!$I$7:$I$463,$C9,'06-2026'!$CE$7:$CE$463,$A9) -> 0 | F9: =SUMIFS('06-2026'!$CB$7:$CB$463,'06-2026'!$C$7:$C$463,$B9,'06-2026'!$A$7:$A$463,"Out-New",'06-2026'!$I$7:$I$463,$C9,'06-2026'!$CE$7:$CE$463,$A9) -> 0 | G9: =COUNTIFS('06-2026'!$C$7:$C$463,$B9,'06-2026'!$A$7:$A$463,"Out-New",'06-2026'!$I$7:$I$463,$C9,'06-2026'!$CE$7:$CE$463,$A9) -> 0 | H9: =SUMIFS('06-2026'!$CB$7:$CB$463,'06-2026'!$C$7:$C$463,$B9,'06-2026'!$A$7:$A$463,"Termination",'06-2026'!$I$7:$I$463,$C9,'06-2026'!$CE$7:$CE$463,$A9) -> 0 | I9: =COUNTIFS('06-2026'!$C$7:$C$463,$B9,'06-2026'!$A$7:$A$463,"Termination",'06-2026'!$I$7:$I$463,$C9,'06-2026'!$CE$7:$CE$463,$A9) -> 0 | J9: =SUM(D9,F9,H9) -> 0 | K9: =SUM(E9,G9,I9) -> 0
A10: =A9 -> MEKONG SUBLABOR | B10: ME Total | D10: =SUM(D7:D9) -> 0 | E10: =SUM(E7:E9) -> 0 | F10: =SUM(F7:F9) -> 0 | G10: =SUM(G7:G9) -> 0 | H10: =SUM(H7:H9) -> 0 | I10: =SUM(I7:I9) -> 0 | J10: =SUM(J7:J9) -> 0 | K10: =SUM(K7:K9) -> 0
A11: =A10 -> MEKONG SUBLABOR | B11: MM | C11: VN1054 | D11: =SUMIFS('06-2026'!$CB$7:$CB$463,'06-2026'!$C$7:$C$463,$B11,'06-2026'!$A$7:$A$463,"Out",'06-2026'!$I$7:$I$463,$C11,'06-2026'!$CE$7:$CE$463,$A11) -> 13858560 | E11: =COUNTIFS('06-2026'!$C$7:$C$463,$B11,'06-2026'!$A$7:$A$463,"Out",'06-2026'!$I$7:$I$463,$C11,'06-2026'!$CE$7:$CE$463,$A11) -> 1 | F11: =SUMIFS('06-2026'!$CB$7:$CB$463,'06-2026'!$C$7:$C$463,$B11,'06-2026'!$A$7:$A$463,"Out-New",'06-2026'!$I$7:$I$463,$C11,'06-2026'!$CE$7:$CE$463,$A11) -> 0 | G11: =COUNTIFS('06-2026'!$C$7:$C$463,$B11,'06-2026'!$A$7:$A$463,"Out-New",'06-2026'!$I$7:$I$463,$C11,'06-2026'!$CE$7:$CE$463,$A11) -> 0 | H11: =SUMIFS('06-2026'!$CB$7:$CB$463,'06-2026'!$C$7:$C$463,$B11,'06-2026'!$A$7:$A$463,"Termination",'06-2026'!$I$7:$I$463,$C11,'06-2026'!$CE$7:$CE$463,$A11) -> 0 | I11: =COUNTIFS('06-2026'!$C$7:$C$463,$B11,'06-2026'!$A$7:$A$463,"Termination",'06-2026'!$I$7:$I$463,$C11,'06-2026'!$CE$7:$CE$463,$A11) -> 0 | J11: =SUM(D11,F11,H11) -> 13858560 | K11: =SUM(E11,G11,I11) -> 1
A12: =A11 -> MEKONG SUBLABOR | B12: MM Total | D12: =D11 -> 13858560 | E12: =E11 -> 1 | F12: =F11 -> 0 | G12: =G11 -> 0 | H12: =H11 -> 0 | I12: =I11 -> 0 | J12: =J11 -> 13858560 | K12: =K11 -> 1
A13: =A12 -> MEKONG SUBLABOR | B13: FIN | C13: VN7040 | D13: =SUMIFS('06-2026'!$CB$7:$CB$463,'06-2026'!$C$7:$C$463,$B13,'06-2026'!$A$7:$A$463,"Out",'06-2026'!$I$7:$I$463,$C13,'06-2026'!$CE$7:$CE$463,$A13) -> 0 | E13: =COUNTIFS('06-2026'!$C$7:$C$463,$B13,'06-2026'!$A$7:$A$463,"Out",'06-2026'!$I$7:$I$463,$C13,'06-2026'!$CE$7:$CE$463,$A13) -> 0 | F13: =SUMIFS('06-2026'!$CB$7:$CB$463,'06-2026'!$C$7:$C$463,$B13,'06-2026'!$A$7:$A$463,"Out-New",'06-2026'!$I$7:$I$463,$C13,'06-2026'!$CE$7:$CE$463,$A13) -> 0 | G13: =COUNTIFS('06-2026'!$C$7:$C$463,$B13,'06-2026'!$A$7:$A$463,"Out-New",'06-2026'!$I$7:$I$463,$C13,'06-2026'!$CE$7:$CE$463,$A13) -> 0 | H13: =SUMIFS('06-2026'!$CB$7:$CB$463,'06-2026'!$C$7:$C$463,$B13,'06-2026'!$A$7:$A$463,"Termination",'06-2026'!$I$7:$I$463,$C13,'06-2026'!$CE$7:$CE$463,$A13) -> 0 | I13: =COUNTIFS('06-2026'!$C$7:$C$463,$B13,'06-2026'!$A$7:$A$463,"Termination",'06-2026'!$I$7:$I$463,$C13,'06-2026'!$CE$7:$CE$463,$A13) -> 0 | J13: =SUM(D13,F13,H13) -> 0 | K13: =SUM(E13,G13,I13) -> 0
A14: =A13 -> MEKONG SUBLABOR | B14: FIN | C14: VN7043 | D14: =SUMIFS('06-2026'!$CB$7:$CB$463,'06-2026'!$C$7:$C$463,$B14,'06-2026'!$A$7:$A$463,"Out",'06-2026'!$I$7:$I$463,$C14,'06-2026'!$CE$7:$CE$463,$A14) -> 0 | E14: =COUNTIFS('06-2026'!$C$7:$C$463,$B14,'06-2026'!$A$7:$A$463,"Out",'06-2026'!$I$7:$I$463,$C14,'06-2026'!$CE$7:$CE$463,$A14) -> 0 | F14: =SUMIFS('06-2026'!$CB$7:$CB$463,'06-2026'!$C$7:$C$463,$B14,'06-2026'!$A$7:$A$463,"Out-New",'06-2026'!$I$7:$I$463,$C14,'06-2026'!$CE$7:$CE$463,$A14) -> 0 | G14: =COUNTIFS('06-2026'!$C$7:$C$463,$B14,'06-2026'!$A$7:$A$463,"Out-New",'06-2026'!$I$7:$I$463,$C14,'06-2026'!$CE$7:$CE$463,$A14) -> 0 | H14: =SUMIFS('06-2026'!$CB$7:$CB$463,'06-2026'!$C$7:$C$463,$B14,'06-2026'!$A$7:$A$463,"Termination",'06-2026'!$I$7:$I$463,$C14,'06-2026'!$CE$7:$CE$463,$A14) -> 0 | I14: =COUNTIFS('06-2026'!$C$7:$C$463,$B14,'06-2026'!$A$7:$A$463,"Termination",'06-2026'!$I$7:$I$463,$C14,'06-2026'!$CE$7:$CE$463,$A14) -> 0 | J14: =SUM(D14,F14,H14) -> 0 | K14: =SUM(E14,G14,I14) -> 0
A15: =A13 -> MEKONG SUBLABOR | B15: FIN Total | D15: =SUM(D13:D14) -> 0 | E15: =SUM(E13:E14) -> 0 | F15: =SUM(F13:F14) -> 0 | G15: =SUM(G13:G14) -> 0 | H15: =SUM(H13:H14) -> 0 | I15: =SUM(I13:I14) -> 0 | J15: =SUM(J13:J14) -> 0 | K15: =SUM(K13:K14) -> 0
A16: =A15 -> MEKONG SUBLABOR | B16: PD | C16: VN1001 | D16: =SUMIFS('06-2026'!$CB$7:$CB$463,'06-2026'!$C$7:$C$463,$B16,'06-2026'!$A$7:$A$463,"Out",'06-2026'!$I$7:$I$463,$C16,'06-2026'!$CE$7:$CE$463,$A16) -> 5.5380531e+08 | E16: =COUNTIFS('06-2026'!$C$7:$C$463,$B16,'06-2026'!$A$7:$A$463,"Out",'06-2026'!$I$7:$I$463,$C16,'06-2026'!$CE$7:$CE$463,$A16) -> 35 | F16: =SUMIFS('06-2026'!$CB$7:$CB$463,'06-2026'!$C$7:$C$463,$B16,'06-2026'!$A$7:$A$463,"Out-New",'06-2026'!$I$7:$I$463,$C16,'06-2026'!$CE$7:$CE$463,$A16) -> 0 | G16: =COUNTIFS('06-2026'!$C$7:$C$463,$B16,'06-2026'!$A$7:$A$463,"Out-New",'06-2026'!$I$7:$I$463,$C16,'06-2026'!$CE$7:$CE$463,$A16) -> 0 | H16: =SUMIFS('06-2026'!$CB$7:$CB$463,'06-2026'!$C$7:$C$463,$B16,'06-2026'!$A$7:$A$463,"Termination",'06-2026'!$I$7:$I$463,$C16,'06-2026'!$CE$7:$CE$463,$A16) -> 37394117 | I16: =COUNTIFS('06-2026'!$C$7:$C$463,$B16,'06-2026'!$A$7:$A$463,"Termination",'06-2026'!$I$7:$I$463,$C16,'06-2026'!$CE$7:$CE$463,$A16) -> 4 | J16: =SUM(D16,F16,H16) -> 5.9119943e+08 | K16: =SUM(E16,G16,I16) -> 39
A17: =A16 -> MEKONG SUBLABOR | B17: =B16 -> PD | C17: VN1002 | D17: =SUMIFS('06-2026'!$CB$7:$CB$463,'06-2026'!$C$7:$C$463,$B17,'06-2026'!$A$7:$A$463,"Out",'06-2026'!$I$7:$I$463,$C17,'06-2026'!$CE$7:$CE$463,$A17) -> 15256364 | E17: =COUNTIFS('06-2026'!$C$7:$C$463,$B17,'06-2026'!$A$7:$A$463,"Out",'06-2026'!$I$7:$I$463,$C17,'06-2026'!$CE$7:$CE$463,$A17) -> 1 | F17: =SUMIFS('06-2026'!$CB$7:$CB$463,'06-2026'!$C$7:$C$463,$B17,'06-2026'!$A$7:$A$463,"Out-New",'06-2026'!$I$7:$I$463,$C17,'06-2026'!$CE$7:$CE$463,$A17) -> 0 | G17: =COUNTIFS('06-2026'!$C$7:$C$463,$B17,'06-2026'!$A$7:$A$463,"Out-New",'06-2026'!$I$7:$I$463,$C17,'06-2026'!$CE$7:$CE$463,$A17) -> 0 | H17: =SUMIFS('06-2026'!$CB$7:$CB$463,'06-2026'!$C$7:$C$463,$B17,'06-2026'!$A$7:$A$463,"Termination",'06-2026'!$I$7:$I$463,$C17,'06-2026'!$CE$7:$CE$463,$A17) -> 12198197 | I17: =COUNTIFS('06-2026'!$C$7:$C$463,$B17,'06-2026'!$A$7:$A$463,"Termination",'06-2026'!$I$7:$I$463,$C17,'06-2026'!$CE$7:$CE$463,$A17) -> 1 | J17: =SUM(D17,F17,H17) -> 27454561 | K17: =SUM(E17,G17,I17) -> 2
A18: =A17 -> MEKONG SUBLABOR | B18: =B17 -> PD | C18: VN1003 | D18: =SUMIFS('06-2026'!$CB$7:$CB$463,'06-2026'!$C$7:$C$463,$B18,'06-2026'!$A$7:$A$463,"Out",'06-2026'!$I$7:$I$463,$C18,'06-2026'!$CE$7:$CE$463,$A18) -> 433580093 | E18: =COUNTIFS('06-2026'!$C$7:$C$463,$B18,'06-2026'!$A$7:$A$463,"Out",'06-2026'!$I$7:$I$463,$C18,'06-2026'!$CE$7:$CE$463,$A18) -> 32 | F18: =SUMIFS('06-2026'!$CB$7:$CB$463,'06-2026'!$C$7:$C$463,$B18,'06-2026'!$A$7:$A$463,"Out-New",'06-2026'!$I$7:$I$463,$C18,'06-2026'!$CE$7:$CE$463,$A18) -> 0 | G18: =COUNTIFS('06-2026'!$C$7:$C$463,$B18,'06-2026'!$A$7:$A$463,"Out-New",'06-2026'!$I$7:$I$463,$C18,'06-2026'!$CE$7:$CE$463,$A18) -> 0 | H18: =SUMIFS('06-2026'!$CB$7:$CB$463,'06-2026'!$C$7:$C$463,$B18,'06-2026'!$A$7:$A$463,"Termination",'06-2026'!$I$7:$I$463,$C18,'06-2026'!$CE$7:$CE$463,$A18) -> 13746673 | I18: =COUNTIFS('06-2026'!$C$7:$C$463,$B18,'06-2026'!$A$7:$A$463,"Termination",'06-2026'!$I$7:$I$463,$C18,'06-2026'!$CE$7:$CE$463,$A18) -> 2 | J18: =SUM(D18,F18,H18) -> 447326766 | K18: =SUM(E18,G18,I18) -> 34
A19: =A18 -> MEKONG SUBLABOR | B19: =B18 -> PD | C19: VN1004 | D19: =SUMIFS('06-2026'!$CB$7:$CB$463,'06-2026'!$C$7:$C$463,$B19,'06-2026'!$A$7:$A$463,"Out",'06-2026'!$I$7:$I$463,$C19,'06-2026'!$CE$7:$CE$463,$A19) -> 0 | E19: =COUNTIFS('06-2026'!$C$7:$C$463,$B19,'06-2026'!$A$7:$A$463,"Out",'06-2026'!$I$7:$I$463,$C19,'06-2026'!$CE$7:$CE$463,$A19) -> 0 | F19: =SUMIFS('06-2026'!$CB$7:$CB$463,'06-2026'!$C$7:$C$463,$B19,'06-2026'!$A$7:$A$463,"Out-New",'06-2026'!$I$7:$I$463,$C19,'06-2026'!$CE$7:$CE$463,$A19) -> 0 | G19: =COUNTIFS('06-2026'!$C$7:$C$463,$B19,'06-2026'!$A$7:$A$463,"Out-New",'06-2026'!$I$7:$I$463,$C19,'06-2026'!$CE$7:$CE$463,$A19) -> 0 | H19: =SUMIFS('06-2026'!$CB$7:$CB$463,'06-2026'!$C$7:$C$463,$B19,'06-2026'!$A$7:$A$463,"Termination",'06-2026'!$I$7:$I$463,$C19,'06-2026'!$CE$7:$CE$463,$A19) -> 0 | I19: =COUNTIFS('06-2026'!$C$7:$C$463,$B19,'06-2026'!$A$7:$A$463,"Termination",'06-2026'!$I$7:$I$463,$C19,'06-2026'!$CE$7:$CE$463,$A19) -> 0 | J19: =SUM(D19,F19,H19) -> 0 | K19: =SUM(E19,G19,I19) -> 0
A20: =A19 -> MEKONG SUBLABOR | B20: =B19 -> PD | C20: VN1005 | D20: =SUMIFS('06-2026'!$CB$7:$CB$463,'06-2026'!$C$7:$C$463,$B20,'06-2026'!$A$7:$A$463,"Out",'06-2026'!$I$7:$I$463,$C20,'06-2026'!$CE$7:$CE$463,$A20) -> 17725900 | E20: =COUNTIFS('06-2026'!$C$7:$C$463,$B20,'06-2026'!$A$7:$A$463,"Out",'06-2026'!$I$7:$I$463,$C20,'06-2026'!$CE$7:$CE$463,$A20) -> 1 | F20: =SUMIFS('06-2026'!$CB$7:$CB$463,'06-2026'!$C$7:$C$463,$B20,'06-2026'!$A$7:$A$463,"Out-New",'06-2026'!$I$7:$I$463,$C20,'06-2026'!$CE$7:$CE$463,$A20) -> 0 | G20: =COUNTIFS('06-2026'!$C$7:$C$463,$B20,'06-2026'!$A$7:$A$463,"Out-New",'06-2026'!$I$7:$I$463,$C20,'06-2026'!$CE$7:$CE$463,$A20) -> 0 | H20: =SUMIFS('06-2026'!$CB$7:$CB$463,'06-2026'!$C$7:$C$463,$B20,'06-2026'!$A$7:$A$463,"Termination",'06-2026'!$I$7:$I$463,$C20,'06-2026'!$CE$7:$CE$463,$A20) -> 0 | I20: =COUNTIFS('06-2026'!$C$7:$C$463,$B20,'06-2026'!$A$7:$A$463,"Termination",'06-2026'!$I$7:$I$463,$C20,'06-2026'!$CE$7:$CE$463,$A20) -> 0 | J20: =SUM(D20,F20,H20) -> 17725900 | K20: =SUM(E20,G20,I20) -> 1
A21: =A19 -> MEKONG SUBLABOR | B21: =B19 -> PD | C21: VN1006 | D21: =SUMIFS('06-2026'!$CB$7:$CB$463,'06-2026'!$C$7:$C$463,$B21,'06-2026'!$A$7:$A$463,"Out",'06-2026'!$I$7:$I$463,$C21,'06-2026'!$CE$7:$CE$463,$A21) -> 160157545 | E21: =COUNTIFS('06-2026'!$C$7:$C$463,$B21,'06-2026'!$A$7:$A$463,"Out",'06-2026'!$I$7:$I$463,$C21,'06-2026'!$CE$7:$CE$463,$A21) -> 14 | F21: =SUMIFS('06-2026'!$CB$7:$CB$463,'06-2026'!$C$7:$C$463,$B21,'06-2026'!$A$7:$A$463,"Out-New",'06-2026'!$I$7:$I$463,$C21,'06-2026'!$CE$7:$CE$463,$A21) -> 0 | G21: =COUNTIFS('06-2026'!$C$7:$C$463,$B21,'06-2026'!$A$7:$A$463,"Out-New",'06-2026'!$I$7:$I$463,$C21,'06-2026'!$CE$7:$CE$463,$A21) -> 0 | H21: =SUMIFS('06-2026'!$CB$7:$CB$463,'06-2026'!$C$7:$C$463,$B21,'06-2026'!$A$7:$A$463,"Termination",'06-2026'!$I$7:$I$463,$C21,'06-2026'!$CE$7:$CE$463,$A21) -> 17986669 | I21: =COUNTIFS('06-2026'!$C$7:$C$463,$B21,'06-2026'!$A$7:$A$463,"Termination",'06-2026'!$I$7:$I$463,$C21,'06-2026'!$CE$7:$CE$463,$A21) -> 2 | J21: =SUM(D21,F21,H21) -> 178144214 | K21: =SUM(E21,G21,I21) -> 16
A22: =A20 -> MEKONG SUBLABOR | B22: =B20 -> PD | C22: VN1007 | D22: =SUMIFS('06-2026'!$CB$7:$CB$463,'06-2026'!$C$7:$C$463,$B22,'06-2026'!$A$7:$A$463,"Out",'06-2026'!$I$7:$I$463,$C22,'06-2026'!$CE$7:$CE$463,$A22) -> 0 | E22: =COUNTIFS('06-2026'!$C$7:$C$463,$B22,'06-2026'!$A$7:$A$463,"Out",'06-2026'!$I$7:$I$463,$C22,'06-2026'!$CE$7:$CE$463,$A22) -> 0 | F22: =SUMIFS('06-2026'!$CB$7:$CB$463,'06-2026'!$C$7:$C$463,$B22,'06-2026'!$A$7:$A$463,"Out-New",'06-2026'!$I$7:$I$463,$C22,'06-2026'!$CE$7:$CE$463,$A22) -> 0 | G22: =COUNTIFS('06-2026'!$C$7:$C$463,$B22,'06-2026'!$A$7:$A$463,"Out-New",'06-2026'!$I$7:$I$463,$C22,'06-2026'!$CE$7:$CE$463,$A22) -> 0 | H22: =SUMIFS('06-2026'!$CB$7:$CB$463,'06-2026'!$C$7:$C$463,$B22,'06-2026'!$A$7:$A$463,"Termination",'06-2026'!$I$7:$I$463,$C22,'06-2026'!$CE$7:$CE$463,$A22) -> 0 | I22: =COUNTIFS('06-2026'!$C$7:$C$463,$B22,'06-2026'!$A$7:$A$463,"Termination",'06-2026'!$I$7:$I$463,$C22,'06-2026'!$CE$7:$CE$463,$A22) -> 0 | J22: =SUM(D22,F22,H22) -> 0 | K22: =SUM(E22,G22,I22) -> 0
A23: =A21 -> MEKONG SUBLABOR | B23: =B21 -> PD | C23: VN1008 | D23: =SUMIFS('06-2026'!$CB$7:$CB$463,'06-2026'!$C$7:$C$463,$B23,'06-2026'!$A$7:$A$463,"Out",'06-2026'!$I$7:$I$463,$C23,'06-2026'!$CE$7:$CE$463,$A23) -> 27026044 | E23: =COUNTIFS('06-2026'!$C$7:$C$463,$B23,'06-2026'!$A$7:$A$463,"Out",'06-2026'!$I$7:$I$463,$C23,'06-2026'!$CE$7:$CE$463,$A23) -> 2 | F23: =SUMIFS('06-2026'!$CB$7:$CB$463,'06-2026'!$C$7:$C$463,$B23,'06-2026'!$A$7:$A$463,"Out-New",'06-2026'!$I$7:$I$463,$C23,'06-2026'!$CE$7:$CE$463,$A23) -> 0 | G23: =COUNTIFS('06-2026'!$C$7:$C$463,$B23,'06-2026'!$A$7:$A$463,"Out-New",'06-2026'!$I$7:$I$463,$C23,'06-2026'!$CE$7:$CE$463,$A23) -> 0 | H23: =SUMIFS('06-2026'!$CB$7:$CB$463,'06-2026'!$C$7:$C$463,$B23,'06-2026'!$A$7:$A$463,"Termination",'06-2026'!$I$7:$I$463,$C23,'06-2026'!$CE$7:$CE$463,$A23) -> 0 | I23: =COUNTIFS('06-2026'!$C$7:$C$463,$B23,'06-2026'!$A$7:$A$463,"Termination",'06-2026'!$I$7:$I$463,$C23,'06-2026'!$CE$7:$CE$463,$A23) -> 0 | J23: =SUM(D23,F23,H23) -> 27026044 | K23: =SUM(E23,G23,I23) -> 2
A24: =A20 -> MEKONG SUBLABOR | B24: =B20 -> PD | C24: VN1022 | D24: =SUMIFS('06-2026'!$CB$7:$CB$463,'06-2026'!$C$7:$C$463,$B24,'06-2026'!$A$7:$A$463,"Out",'06-2026'!$I$7:$I$463,$C24,'06-2026'!$CE$7:$CE$463,$A24) -> 0 | E24: =COUNTIFS('06-2026'!$C$7:$C$463,$B24,'06-2026'!$A$7:$A$463,"Out",'06-2026'!$I$7:$I$463,$C24,'06-2026'!$CE$7:$CE$463,$A24) -> 0 | F24: =SUMIFS('06-2026'!$CB$7:$CB$463,'06-2026'!$C$7:$C$463,$B24,'06-2026'!$A$7:$A$463,"Out-New",'06-2026'!$I$7:$I$463,$C24,'06-2026'!$CE$7:$CE$463,$A24) -> 0 | G24: =COUNTIFS('06-2026'!$C$7:$C$463,$B24,'06-2026'!$A$7:$A$463,"Out-New",'06-2026'!$I$7:$I$463,$C24,'06-2026'!$CE$7:$CE$463,$A24) -> 0 | H24: =SUMIFS('06-2026'!$CB$7:$CB$463,'06-2026'!$C$7:$C$463,$B24,'06-2026'!$A$7:$A$463,"Termination",'06-2026'!$I$7:$I$463,$C24,'06-2026'!$CE$7:$CE$463,$A24) -> 0 | I24: =COUNTIFS('06-2026'!$C$7:$C$463,$B24,'06-2026'!$A$7:$A$463,"Termination",'06-2026'!$I$7:$I$463,$C24,'06-2026'!$CE$7:$CE$463,$A24) -> 0 | J24: =SUM(D24,F24,H24) -> 0 | K24: =SUM(E24,G24,I24) -> 0
A25: =A21 -> MEKONG SUBLABOR | B25: R&D | C25: VN3001 | D25: =SUMIFS('06-2026'!$CB$7:$CB$463,'06-2026'!$C$7:$C$463,$B25,'06-2026'!$A$7:$A$463,"Out",'06-2026'!$I$7:$I$463,$C25,'06-2026'!$CE$7:$CE$463,$A25) -> 35408362 | E25: =COUNTIFS('06-2026'!$C$7:$C$463,$B25,'06-2026'!$A$7:$A$463,"Out",'06-2026'!$I$7:$I$463,$C25,'06-2026'!$CE$7:$CE$463,$A25) -> 3 | F25: =SUMIFS('06-2026'!$CB$7:$CB$463,'06-2026'!$C$7:$C$463,$B25,'06-2026'!$A$7:$A$463,"Out-New",'06-2026'!$I$7:$I$463,$C25,'06-2026'!$CE$7:$CE$463,$A25) -> 0 | G25: =COUNTIFS('06-2026'!$C$7:$C$463,$B25,'06-2026'!$A$7:$A$463,"Out-New",'06-2026'!$I$7:$I$463,$C25,'06-2026'!$CE$7:$CE$463,$A25) -> 0 | H25: =SUMIFS('06-2026'!$CB$7:$CB$463,'06-2026'!$C$7:$C$463,$B25,'06-2026'!$A$7:$A$463,"Termination",'06-2026'!$I$7:$I$463,$C25,'06-2026'!$CE$7:$CE$463,$A25) -> 10674154 | I25: =COUNTIFS('06-2026'!$C$7:$C$463,$B25,'06-2026'!$A$7:$A$463,"Termination",'06-2026'!$I$7:$I$463,$C25,'06-2026'!$CE$7:$CE$463,$A25) -> 1 | J25: =SUM(D25,F25,H25) -> 46082516 | K25: =SUM(E25,G25,I25) -> 4
A26: =A24 -> MEKONG SUBLABOR | B26: PD Total | D26: =SUM(D16:D25) -> 1.2429596e+09 | E26: =SUM(E16:E25) -> 88 | F26: =SUM(F16:F25) -> 0 | G26: =SUM(G16:G25) -> 0 | H26: =SUM(H16:H25) -> 91999810 | I26: =SUM(I16:I25) -> 10 | J26: =SUM(J16:J25) -> 1.3349594e+09 | K26: =SUM(K16:K25) -> 98
A27: =A26 -> MEKONG SUBLABOR | B27: QA | C27: VN3007 | D27: =SUMIFS('06-2026'!$CB$7:$CB$463,'06-2026'!$C$7:$C$463,$B27,'06-2026'!$A$7:$A$463,"Out",'06-2026'!$I$7:$I$463,$C27,'06-2026'!$CE$7:$CE$463,$A27) -> 0 | E27: =COUNTIFS('06-2026'!$C$7:$C$463,$B27,'06-2026'!$A$7:$A$463,"Out",'06-2026'!$I$7:$I$463,$C27,'06-2026'!$CE$7:$CE$463,$A27) -> 0 | F27: =SUMIFS('06-2026'!$CB$7:$CB$463,'06-2026'!$C$7:$C$463,$B27,'06-2026'!$A$7:$A$463,"Out-New",'06-2026'!$I$7:$I$463,$C27,'06-2026'!$CE$7:$CE$463,$A27) -> 0 | G27: =COUNTIFS('06-2026'!$C$7:$C$463,$B27,'06-2026'!$A$7:$A$463,"Out-New",'06-2026'!$I$7:$I$463,$C27,'06-2026'!$CE$7:$CE$463,$A27) -> 0 | H27: =SUMIFS('06-2026'!$CB$7:$CB$463,'06-2026'!$C$7:$C$463,$B27,'06-2026'!$A$7:$A$463,"Termination",'06-2026'!$I$7:$I$463,$C27,'06-2026'!$CE$7:$CE$463,$A27) -> 0 | I27: =COUNTIFS('06-2026'!$C$7:$C$463,$B27,'06-2026'!$A$7:$A$463,"Termination",'06-2026'!$I$7:$I$463,$C27,'06-2026'!$CE$7:$CE$463,$A27) -> 0 | J27: =SUM(D27,F27,H27) -> 0 | K27: =SUM(E27,G27,I27) -> 0
A28: =A27 -> MEKONG SUBLABOR | B28: QA | C28: VN1022 | D28: =SUMIFS('06-2026'!$CB$7:$CB$463,'06-2026'!$C$7:$C$463,$B28,'06-2026'!$A$7:$A$463,"Out",'06-2026'!$I$7:$I$463,$C28,'06-2026'!$CE$7:$CE$463,$A28) -> 0 | E28: =COUNTIFS('06-2026'!$C$7:$C$463,$B28,'06-2026'!$A$7:$A$463,"Out",'06-2026'!$I$7:$I$463,$C28,'06-2026'!$CE$7:$CE$463,$A28) -> 0 | F28: =SUMIFS('06-2026'!$CB$7:$CB$463,'06-2026'!$C$7:$C$463,$B28,'06-2026'!$A$7:$A$463,"Out-New",'06-2026'!$I$7:$I$463,$C28,'06-2026'!$CE$7:$CE$463,$A28) -> 0 | G28: =COUNTIFS('06-2026'!$C$7:$C$463,$B28,'06-2026'!$A$7:$A$463,"Out-New",'06-2026'!$I$7:$I$463,$C28,'06-2026'!$CE$7:$CE$463,$A28) -> 0 | H28: =SUMIFS('06-2026'!$CB$7:$CB$463,'06-2026'!$C$7:$C$463,$B28,'06-2026'!$A$7:$A$463,"Termination",'06-2026'!$I$7:$I$463,$C28,'06-2026'!$CE$7:$CE$463,$A28) -> 0 | I28: =COUNTIFS('06-2026'!$C$7:$C$463,$B28,'06-2026'!$A$7:$A$463,"Termination",'06-2026'!$I$7:$I$463,$C28,'06-2026'!$CE$7:$CE$463,$A28) -> 0 | J28: =SUM(D28,F28,H28) -> 0 | K28: =SUM(E28,G28,I28) -> 0
A29: =A28 -> MEKONG SUBLABOR | B29: QA | C29: VN1003 | D29: =SUMIFS('06-2026'!$CB$7:$CB$463,'06-2026'!$C$7:$C$463,$B29,'06-2026'!$A$7:$A$463,"Out",'06-2026'!$I$7:$I$463,$C29,'06-2026'!$CE$7:$CE$463,$A29) -> 0 | E29: =COUNTIFS('06-2026'!$C$7:$C$463,$B29,'06-2026'!$A$7:$A$463,"Out",'06-2026'!$I$7:$I$463,$C29,'06-2026'!$CE$7:$CE$463,$A29) -> 0 | F29: =SUMIFS('06-2026'!$CB$7:$CB$463,'06-2026'!$C$7:$C$463,$B29,'06-2026'!$A$7:$A$463,"Out-New",'06-2026'!$I$7:$I$463,$C29,'06-2026'!$CE$7:$CE$463,$A29) -> 0 | G29: =COUNTIFS('06-2026'!$C$7:$C$463,$B29,'06-2026'!$A$7:$A$463,"Out-New",'06-2026'!$I$7:$I$463,$C29,'06-2026'!$CE$7:$CE$463,$A29) -> 0 | H29: =SUMIFS('06-2026'!$CB$7:$CB$463,'06-2026'!$C$7:$C$463,$B29,'06-2026'!$A$7:$A$463,"Termination",'06-2026'!$I$7:$I$463,$C29,'06-2026'!$CE$7:$CE$463,$A29) -> 0 | I29: =COUNTIFS('06-2026'!$C$7:$C$463,$B29,'06-2026'!$A$7:$A$463,"Termination",'06-2026'!$I$7:$I$463,$C29,'06-2026'!$CE$7:$CE$463,$A29) -> 0 | J29: =SUM(D29,F29,H29) -> 0 | K29: =SUM(E29,G29,I29) -> 0
A30: =A29 -> MEKONG SUBLABOR | B30: QA | C30: VN1071 | D30: =SUMIFS('06-2026'!$CB$7:$CB$463,'06-2026'!$C$7:$C$463,$B30,'06-2026'!$A$7:$A$463,"Out",'06-2026'!$I$7:$I$463,$C30,'06-2026'!$CE$7:$CE$463,$A30) -> 0 | E30: =COUNTIFS('06-2026'!$C$7:$C$463,$B30,'06-2026'!$A$7:$A$463,"Out",'06-2026'!$I$7:$I$463,$C30,'06-2026'!$CE$7:$CE$463,$A30) -> 0 | F30: =SUMIFS('06-2026'!$CB$7:$CB$463,'06-2026'!$C$7:$C$463,$B30,'06-2026'!$A$7:$A$463,"Out-New",'06-2026'!$I$7:$I$463,$C30,'06-2026'!$CE$7:$CE$463,$A30) -> 0 | G30: =COUNTIFS('06-2026'!$C$7:$C$463,$B30,'06-2026'!$A$7:$A$463,"Out-New",'06-2026'!$I$7:$I$463,$C30,'06-2026'!$CE$7:$CE$463,$A30) -> 0 | H30: =SUMIFS('06-2026'!$CB$7:$CB$463,'06-2026'!$C$7:$C$463,$B30,'06-2026'!$A$7:$A$463,"Termination",'06-2026'!$I$7:$I$463,$C30,'06-2026'!$CE$7:$CE$463,$A30) -> 0 | I30: =COUNTIFS('06-2026'!$C$7:$C$463,$B30,'06-2026'!$A$7:$A$463,"Termination",'06-2026'!$I$7:$I$463,$C30,'06-2026'!$CE$7:$CE$463,$A30) -> 0 | J30: =SUM(D30,F30,H30) -> 0 | K30: =SUM(E30,G30,I30) -> 0
A31: =A28 -> MEKONG SUBLABOR | B31: QA Total | D31: =SUM(D27:D30) -> 0 | E31: =SUM(E27:E30) -> 0 | F31: =SUM(F27:F30) -> 0 | G31: =SUM(G27:G30) -> 0 | H31: =SUM(H27:H30) -> 0 | I31: =SUM(I27:I30) -> 0 | J31: =SUM(J27:J30) -> 0 | K31: =SUM(K27:K30) -> 0
A32: MEKONG SUBLABOR Total | D32: =SUM(D6,D10,D12,D15,D26) -> 1.348267e+09 | E32: =SUM(E6,E10,E12,E15,E26,E31) -> 96 | F32: =SUM(F6,F10,F12,F15,F26) -> 0 | G32: =SUM(G6,G10,G12,G15,G26) -> 0 | H32: =SUM(H6,H10,H12,H15,H26) -> 112099564 | I32: =SUM(I6,I10,I12,I15,I26,I31) -> 13 | J32: =SUM(J6,J10,J12,J15,J26,J31) -> 1.4603666e+09 | K32: =SUM(K6,K10,K12,K15,K26,K31) -> 109
A33: ANNK-HR | B33: LG | C33: VN1005 | D33: =SUMIFS('06-2026'!$CB$7:$CB$463,'06-2026'!$C$7:$C$463,$B33,'06-2026'!$A$7:$A$463,"Out",'06-2026'!$I$7:$I$463,$C33,'06-2026'!$CE$7:$CE$463,$A33) -> 0 | E33: =COUNTIFS('06-2026'!$C$7:$C$463,$B33,'06-2026'!$A$7:$A$463,"Out",'06-2026'!$I$7:$I$463,$C33,'06-2026'!$CE$7:$CE$463,$A33) -> 0 | F33: =SUMIFS('06-2026'!$CB$7:$CB$463,'06-2026'!$C$7:$C$463,$B33,'06-2026'!$A$7:$A$463,"Out-New",'06-2026'!$I$7:$I$463,$C33,'06-2026'!$CE$7:$CE$463,$A33) -> 0 | G33: =COUNTIFS('06-2026'!$C$7:$C$463,$B33,'06-2026'!$A$7:$A$463,"Out-New",'06-2026'!$I$7:$I$463,$C33,'06-2026'!$CE$7:$CE$463,$A33) -> 0 | H33: =SUMIFS('06-2026'!$CB$7:$CB$463,'06-2026'!$C$7:$C$463,$B33,'06-2026'!$A$7:$A$463,"Termination",'06-2026'!$I$7:$I$463,$C33,'06-2026'!$CE$7:$CE$463,$A33) -> 0 | I33: =COUNTIFS('06-2026'!$C$7:$C$463,$B33,'06-2026'!$A$7:$A$463,"Termination",'06-2026'!$I$7:$I$463,$C33,'06-2026'!$CE$7:$CE$463,$A33) -> 0 | J33: =SUM(D33,F33,H33) -> 0 | K33: =SUM(E33,G33,I33) -> 0
A34: =A33 -> ANNK-HR | B34: LG | C34: VN1006 | D34: =SUMIFS('06-2026'!$CB$7:$CB$463,'06-2026'!$C$7:$C$463,$B34,'06-2026'!$A$7:$A$463,"Out",'06-2026'!$I$7:$I$463,$C34,'06-2026'!$CE$7:$CE$463,$A34) -> 0 | E34: =COUNTIFS('06-2026'!$C$7:$C$463,$B34,'06-2026'!$A$7:$A$463,"Out",'06-2026'!$I$7:$I$463,$C34,'06-2026'!$CE$7:$CE$463,$A34) -> 0 | F34: =SUMIFS('06-2026'!$CB$7:$CB$463,'06-2026'!$C$7:$C$463,$B34,'06-2026'!$A$7:$A$463,"Out-New",'06-2026'!$I$7:$I$463,$C34,'06-2026'!$CE$7:$CE$463,$A34) -> 0 | G34: =COUNTIFS('06-2026'!$C$7:$C$463,$B34,'06-2026'!$A$7:$A$463,"Out-New",'06-2026'!$I$7:$I$463,$C34,'06-2026'!$CE$7:$CE$463,$A34) -> 0 | H34: =SUMIFS('06-2026'!$CB$7:$CB$463,'06-2026'!$C$7:$C$463,$B34,'06-2026'!$A$7:$A$463,"Termination",'06-2026'!$I$7:$I$463,$C34,'06-2026'!$CE$7:$CE$463,$A34) -> 0 | I34: =COUNTIFS('06-2026'!$C$7:$C$463,$B34,'06-2026'!$A$7:$A$463,"Termination",'06-2026'!$I$7:$I$463,$C34,'06-2026'!$CE$7:$CE$463,$A34) -> 0 | J34: =SUM(D34,F34,H34) -> 0 | K34: =SUM(E34,G34,I34) -> 0
A35: =A34 -> ANNK-HR | B35: =B33 -> LG | C35: VN1033 | D35: =SUMIFS('06-2026'!$CB$7:$CB$463,'06-2026'!$C$7:$C$463,$B35,'06-2026'!$A$7:$A$463,"Out",'06-2026'!$I$7:$I$463,$C35,'06-2026'!$CE$7:$CE$463,$A35) -> 0 | E35: =COUNTIFS('06-2026'!$C$7:$C$463,$B35,'06-2026'!$A$7:$A$463,"Out",'06-2026'!$I$7:$I$463,$C35,'06-2026'!$CE$7:$CE$463,$A35) -> 0 | F35: =SUMIFS('06-2026'!$CB$7:$CB$463,'06-2026'!$C$7:$C$463,$B35,'06-2026'!$A$7:$A$463,"Out-New",'06-2026'!$I$7:$I$463,$C35,'06-2026'!$CE$7:$CE$463,$A35) -> 0 | G35: =COUNTIFS('06-2026'!$C$7:$C$463,$B35,'06-2026'!$A$7:$A$463,"Out-New",'06-2026'!$I$7:$I$463,$C35,'06-2026'!$CE$7:$CE$463,$A35) -> 0 | H35: =SUMIFS('06-2026'!$CB$7:$CB$463,'06-2026'!$C$7:$C$463,$B35,'06-2026'!$A$7:$A$463,"Termination",'06-2026'!$I$7:$I$463,$C35,'06-2026'!$CE$7:$CE$463,$A35) -> 0 | I35: =COUNTIFS('06-2026'!$C$7:$C$463,$B35,'06-2026'!$A$7:$A$463,"Termination",'06-2026'!$I$7:$I$463,$C35,'06-2026'!$CE$7:$CE$463,$A35) -> 0 | J35: =SUM(D35,F35,H35) -> 0 | K35: =SUM(E35,G35,I35) -> 0
A36: =A35 -> ANNK-HR | B36: =B35 -> LG | C36: VN1042 | D36: =SUMIFS('06-2026'!$CB$7:$CB$463,'06-2026'!$C$7:$C$463,$B36,'06-2026'!$A$7:$A$463,"Out",'06-2026'!$I$7:$I$463,$C36,'06-2026'!$CE$7:$CE$463,$A36) -> 51364961 | E36: =COUNTIFS('06-2026'!$C$7:$C$463,$B36,'06-2026'!$A$7:$A$463,"Out",'06-2026'!$I$7:$I$463,$C36,'06-2026'!$CE$7:$CE$463,$A36) -> 4 | F36: =SUMIFS('06-2026'!$CB$7:$CB$463,'06-2026'!$C$7:$C$463,$B36,'06-2026'!$A$7:$A$463,"Out-New",'06-2026'!$I$7:$I$463,$C36,'06-2026'!$CE$7:$CE$463,$A36) -> 0 | G36: =COUNTIFS('06-2026'!$C$7:$C$463,$B36,'06-2026'!$A$7:$A$463,"Out-New",'06-2026'!$I$7:$I$463,$C36,'06-2026'!$CE$7:$CE$463,$A36) -> 0 | H36: =SUMIFS('06-2026'!$CB$7:$CB$463,'06-2026'!$C$7:$C$463,$B36,'06-2026'!$A$7:$A$463,"Termination",'06-2026'!$I$7:$I$463,$C36,'06-2026'!$CE$7:$CE$463,$A36) -> 3360197 | I36: =COUNTIFS('06-2026'!$C$7:$C$463,$B36,'06-2026'!$A$7:$A$463,"Termination",'06-2026'!$I$7:$I$463,$C36,'06-2026'!$CE$7:$CE$463,$A36) -> 2 | J36: =SUM(D36,F36,H36) -> 54725158 | K36: =SUM(E36,G36,I36) -> 6
A37: =A36 -> ANNK-HR | B37: LG Total | D37: =SUM(D33:D36) -> 51364961 | E37: =SUM(E33:E36) -> 4 | F37: =SUM(F33:F36) -> 0 | G37: =SUM(G33:G36) -> 0 | H37: =SUM(H33:H36) -> 3360197 | I37: =SUM(I33:I36) -> 2 | J37: =SUM(J33:J36) -> 54725158 | K37: =SUM(K33:K36) -> 6
A38: =A37 -> ANNK-HR | B38: ME | C38: VN1024 | D38: =SUMIFS('06-2026'!$CB$7:$CB$463,'06-2026'!$C$7:$C$463,$B38,'06-2026'!$A$7:$A$463,"Out",'06-2026'!$I$7:$I$463,$C38,'06-2026'!$CE$7:$CE$463,$A38) -> 0 | E38: =COUNTIFS('06-2026'!$C$7:$C$463,$B38,'06-2026'!$A$7:$A$463,"Out",'06-2026'!$I$7:$I$463,$C38,'06-2026'!$CE$7:$CE$463,$A38) -> 0 | F38: =SUMIFS('06-2026'!$CB$7:$CB$463,'06-2026'!$C$7:$C$463,$B38,'06-2026'!$A$7:$A$463,"Out-New",'06-2026'!$I$7:$I$463,$C38,'06-2026'!$CE$7:$CE$463,$A38) -> 0 | G38: =COUNTIFS('06-2026'!$C$7:$C$463,$B38,'06-2026'!$A$7:$A$463,"Out-New",'06-2026'!$I$7:$I$463,$C38,'06-2026'!$CE$7:$CE$463,$A38) -> 0 | H38: =SUMIFS('06-2026'!$CB$7:$CB$463,'06-2026'!$C$7:$C$463,$B38,'06-2026'!$A$7:$A$463,"Termination",'06-2026'!$I$7:$I$463,$C38,'06-2026'!$CE$7:$CE$463,$A38) -> 17541136 | I38: =COUNTIFS('06-2026'!$C$7:$C$463,$B38,'06-2026'!$A$7:$A$463,"Termination",'06-2026'!$I$7:$I$463,$C38,'06-2026'!$CE$7:$CE$463,$A38) -> 1 | J38: =SUM(D38,F38,H38) -> 17541136 | K38: =SUM(E38,G38,I38) -> 1
A39: =A38 -> ANNK-HR | B39: ME Total | D39: =D38 -> 0 | E39: =E38 -> 0 | F39: =F38 -> 0 | G39: =G38 -> 0 | H39: =H38 -> 17541136 | I39: =I38 -> 1 | J39: =J38 -> 17541136 | K39: =K38 -> 1
A40: =A39 -> ANNK-HR | B40: Gpr | C40: VN1052 | D40: =SUMIFS('06-2026'!$CB$7:$CB$463,'06-2026'!$C$7:$C$463,$B40,'06-2026'!$A$7:$A$463,"Out",'06-2026'!$I$7:$I$463,$C40,'06-2026'!$CE$7:$CE$463,$A40) -> 15395874 | E40: =COUNTIFS('06-2026'!$C$7:$C$463,$B40,'06-2026'!$A$7:$A$463,"Out",'06-2026'!$I$7:$I$463,$C40,'06-2026'!$CE$7:$CE$463,$A40) -> 1 | F40: =SUMIFS('06-2026'!$CB$7:$CB$463,'06-2026'!$C$7:$C$463,$B40,'06-2026'!$A$7:$A$463,"Out-New",'06-2026'!$I$7:$I$463,$C40,'06-2026'!$CE$7:$CE$463,$A40) -> 0 | G40: =COUNTIFS('06-2026'!$C$7:$C$463,$B40,'06-2026'!$A$7:$A$463,"Out-New",'06-2026'!$I$7:$I$463,$C40,'06-2026'!$CE$7:$CE$463,$A40) -> 0 | H40: =SUMIFS('06-2026'!$CB$7:$CB$463,'06-2026'!$C$7:$C$463,$B40,'06-2026'!$A$7:$A$463,"Termination",'06-2026'!$I$7:$I$463,$C40,'06-2026'!$CE$7:$CE$463,$A40) -> 0 | I40: =COUNTIFS('06-2026'!$C$7:$C$463,$B40,'06-2026'!$A$7:$A$463,"Termination",'06-2026'!$I$7:$I$463,$C40,'06-2026'!$CE$7:$CE$463,$A40) -> 0 | J40: =SUM(D40,F40,H40) -> 15395874 | K40: =SUM(E40,G40,I40) -> 1
A41: =A40 -> ANNK-HR | B41: Gpr Total | D41: =D40 -> 15395874 | E41: =E40 -> 1 | F41: =F40 -> 0 | G41: =G40 -> 0 | H41: =H40 -> 0 | I41: =I40 -> 0 | J41: =J40 -> 15395874 | K41: =K40 -> 1
A42: =A41 -> ANNK-HR | B42: MM | C42: VN1054 | D42: =SUMIFS('06-2026'!$CB$7:$CB$463,'06-2026'!$C$7:$C$463,$B42,'06-2026'!$A$7:$A$463,"Out",'06-2026'!$I$7:$I$463,$C42,'06-2026'!$CE$7:$CE$463,$A42) -> 0 | E42: =COUNTIFS('06-2026'!$C$7:$C$463,$B42,'06-2026'!$A$7:$A$463,"Out",'06-2026'!$I$7:$I$463,$C42,'06-2026'!$CE$7:$CE$463,$A42) -> 0 | F42: =SUMIFS('06-2026'!$CB$7:$CB$463,'06-2026'!$C$7:$C$463,$B42,'06-2026'!$A$7:$A$463,"Out-New",'06-2026'!$I$7:$I$463,$C42,'06-2026'!$CE$7:$CE$463,$A42) -> 0 | G42: =COUNTIFS('06-2026'!$C$7:$C$463,$B42,'06-2026'!$A$7:$A$463,"Out-New",'06-2026'!$I$7:$I$463,$C42,'06-2026'!$CE$7:$CE$463,$A42) -> 0 | H42: =SUMIFS('06-2026'!$CB$7:$CB$463,'06-2026'!$C$7:$C$463,$B42,'06-2026'!$A$7:$A$463,"Termination",'06-2026'!$I$7:$I$463,$C42,'06-2026'!$CE$7:$CE$463,$A42) -> 0 | I42: =COUNTIFS('06-2026'!$C$7:$C$463,$B42,'06-2026'!$A$7:$A$463,"Termination",'06-2026'!$I$7:$I$463,$C42,'06-2026'!$CE$7:$CE$463,$A42) -> 0 | J42: =SUM(D42,F42,H42) -> 0 | K42: =SUM(E42,G42,I42) -> 0
A43: =A42 -> ANNK-HR | B43: MM Total | D43: =D42 -> 0 | E43: =E42 -> 0 | F43: =F42 -> 0 | G43: =G42 -> 0 | H43: =H42 -> 0 | I43: =I42 -> 0 | J43: =J42 -> 0 | K43: =K42 -> 0
A44: =A43 -> ANNK-HR | B44: HRA | C44: VN7010 | D44: =SUMIFS('06-2026'!$CB$7:$CB$463,'06-2026'!$C$7:$C$463,$B44,'06-2026'!$A$7:$A$463,"Out",'06-2026'!$I$7:$I$463,$C44,'06-2026'!$CE$7:$CE$463,$A44) -> 0 | E44: =COUNTIFS('06-2026'!$C$7:$C$463,$B44,'06-2026'!$A$7:$A$463,"Out",'06-2026'!$I$7:$I$463,$C44,'06-2026'!$CE$7:$CE$463,$A44) -> 0 | F44: =SUMIFS('06-2026'!$CB$7:$CB$463,'06-2026'!$C$7:$C$463,$B44,'06-2026'!$A$7:$A$463,"Out-New",'06-2026'!$I$7:$I$463,$C44,'06-2026'!$CE$7:$CE$463,$A44) -> 0 | G44: =COUNTIFS('06-2026'!$C$7:$C$463,$B44,'06-2026'!$A$7:$A$463,"Out-New",'06-2026'!$I$7:$I$463,$C44,'06-2026'!$CE$7:$CE$463,$A44) -> 0 | H44: =SUMIFS('06-2026'!$CB$7:$CB$463,'06-2026'!$C$7:$C$463,$B44,'06-2026'!$A$7:$A$463,"Termination",'06-2026'!$I$7:$I$463,$C44,'06-2026'!$CE$7:$CE$463,$A44) -> 7504544 | I44: =COUNTIFS('06-2026'!$C$7:$C$463,$B44,'06-2026'!$A$7:$A$463,"Termination",'06-2026'!$I$7:$I$463,$C44,'06-2026'!$CE$7:$CE$463,$A44) -> 1 | J44: =SUM(D44,F44,H44) -> 7504544 | K44: =SUM(E44,G44,I44) -> 1
A45: =A44 -> ANNK-HR | B45: HRA Total | D45: =D44 -> 0 | E45: =E44 -> 0 | F45: =F44 -> 0 | G45: =G44 -> 0 | H45: =H44 -> 7504544 | I45: =I44 -> 1 | J45: =J44 -> 7504544 | K45: =K44 -> 1
A46: =A45 -> ANNK-HR | B46: FIN | C46: VN7040 | D46: =SUMIFS('06-2026'!$CB$7:$CB$463,'06-2026'!$C$7:$C$463,$B46,'06-2026'!$A$7:$A$463,"Out",'06-2026'!$I$7:$I$463,$C46,'06-2026'!$CE$7:$CE$463,$A46) -> 20252250 | E46: =COUNTIFS('06-2026'!$C$7:$C$463,$B46,'06-2026'!$A$7:$A$463,"Out",'06-2026'!$I$7:$I$463,$C46,'06-2026'!$CE$7:$CE$463,$A46) -> 1 | F46: =SUMIFS('06-2026'!$CB$7:$CB$463,'06-2026'!$C$7:$C$463,$B46,'06-2026'!$A$7:$A$463,"Out-New",'06-2026'!$I$7:$I$463,$C46,'06-2026'!$CE$7:$CE$463,$A46) -> 0 | G46: =COUNTIFS('06-2026'!$C$7:$C$463,$B46,'06-2026'!$A$7:$A$463,"Out-New",'06-2026'!$I$7:$I$463,$C46,'06-2026'!$CE$7:$CE$463,$A46) -> 0 | H46: =SUMIFS('06-2026'!$CB$7:$CB$463,'06-2026'!$C$7:$C$463,$B46,'06-2026'!$A$7:$A$463,"Termination",'06-2026'!$I$7:$I$463,$C46,'06-2026'!$CE$7:$CE$463,$A46) -> 0 | I46: =COUNTIFS('06-2026'!$C$7:$C$463,$B46,'06-2026'!$A$7:$A$463,"Termination",'06-2026'!$I$7:$I$463,$C46,'06-2026'!$CE$7:$CE$463,$A46) -> 0 | J46: =SUM(D46,F46,H46) -> 20252250 | K46: =SUM(E46,G46,I46) -> 1
A47: =A46 -> ANNK-HR | B47: FIN | C47: VN7043 | D47: =SUMIFS('06-2026'!$CB$7:$CB$463,'06-2026'!$C$7:$C$463,$B47,'06-2026'!$A$7:$A$463,"Out",'06-2026'!$I$7:$I$463,$C47,'06-2026'!$CE$7:$CE$463,$A47) -> 0 | E47: =COUNTIFS('06-2026'!$C$7:$C$463,$B47,'06-2026'!$A$7:$A$463,"Out",'06-2026'!$I$7:$I$463,$C47,'06-2026'!$CE$7:$CE$463,$A47) -> 0 | F47: =SUMIFS('06-2026'!$CB$7:$CB$463,'06-2026'!$C$7:$C$463,$B47,'06-2026'!$A$7:$A$463,"Out-New",'06-2026'!$I$7:$I$463,$C47,'06-2026'!$CE$7:$CE$463,$A47) -> 0 | G47: =COUNTIFS('06-2026'!$C$7:$C$463,$B47,'06-2026'!$A$7:$A$463,"Out-New",'06-2026'!$I$7:$I$463,$C47,'06-2026'!$CE$7:$CE$463,$A47) -> 0 | H47: =SUMIFS('06-2026'!$CB$7:$CB$463,'06-2026'!$C$7:$C$463,$B47,'06-2026'!$A$7:$A$463,"Termination",'06-2026'!$I$7:$I$463,$C47,'06-2026'!$CE$7:$CE$463,$A47) -> 12968015 | I47: =COUNTIFS('06-2026'!$C$7:$C$463,$B47,'06-2026'!$A$7:$A$463,"Termination",'06-2026'!$I$7:$I$463,$C47,'06-2026'!$CE$7:$CE$463,$A47) -> 1 | J47: =SUM(D47,F47,H47) -> 12968015 | K47: =SUM(E47,G47,I47) -> 1
A48: =A47 -> ANNK-HR | B48: FIN Total | D48: =SUM(D46:D47) -> 20252250 | E48: =SUM(E46:E47) -> 1 | F48: =SUM(F46:F47) -> 0 | G48: =SUM(G46:G47) -> 0 | H48: =SUM(H46:H47) -> 12968015 | I48: =SUM(I46:I47) -> 1 | J48: =SUM(J46:J47) -> 33220265 | K48: =SUM(K46:K47) -> 2
A49: =A48 -> ANNK-HR | B49: PD | C49: VN1001 | D49: =SUMIFS('06-2026'!$CB$7:$CB$463,'06-2026'!$C$7:$C$463,$B49,'06-2026'!$A$7:$A$463,"Out",'06-2026'!$I$7:$I$463,$C49,'06-2026'!$CE$7:$CE$463,$A49) -> 213429679 | E49: =COUNTIFS('06-2026'!$C$7:$C$463,$B49,'06-2026'!$A$7:$A$463,"Out",'06-2026'!$I$7:$I$463,$C49,'06-2026'!$CE$7:$CE$463,$A49) -> 16 | F49: =SUMIFS('06-2026'!$CB$7:$CB$463,'06-2026'!$C$7:$C$463,$B49,'06-2026'!$A$7:$A$463,"Out-New",'06-2026'!$I$7:$I$463,$C49,'06-2026'!$CE$7:$CE$463,$A49) -> 0 | G49: =COUNTIFS('06-2026'!$C$7:$C$463,$B49,'06-2026'!$A$7:$A$463,"Out-New",'06-2026'!$I$7:$I$463,$C49,'06-2026'!$CE$7:$CE$463,$A49) -> 0 | H49: =SUMIFS('06-2026'!$CB$7:$CB$463,'06-2026'!$C$7:$C$463,$B49,'06-2026'!$A$7:$A$463,"Termination",'06-2026'!$I$7:$I$463,$C49,'06-2026'!$CE$7:$CE$463,$A49) -> 1066080 | I49: =COUNTIFS('06-2026'!$C$7:$C$463,$B49,'06-2026'!$A$7:$A$463,"Termination",'06-2026'!$I$7:$I$463,$C49,'06-2026'!$CE$7:$CE$463,$A49) -> 3 | J49: =SUM(D49,F49,H49) -> 214495759 | K49: =SUM(E49,G49,I49) -> 19
A50: =A49 -> ANNK-HR | B50: =B49 -> PD | C50: VN1002 | D50: =SUMIFS('06-2026'!$CB$7:$CB$463,'06-2026'!$C$7:$C$463,$B50,'06-2026'!$A$7:$A$463,"Out",'06-2026'!$I$7:$I$463,$C50,'06-2026'!$CE$7:$CE$463,$A50) -> 14058471 | E50: =COUNTIFS('06-2026'!$C$7:$C$463,$B50,'06-2026'!$A$7:$A$463,"Out",'06-2026'!$I$7:$I$463,$C50,'06-2026'!$CE$7:$CE$463,$A50) -> 1 | F50: =SUMIFS('06-2026'!$CB$7:$CB$463,'06-2026'!$C$7:$C$463,$B50,'06-2026'!$A$7:$A$463,"Out-New",'06-2026'!$I$7:$I$463,$C50,'06-2026'!$CE$7:$CE$463,$A50) -> 0 | G50: =COUNTIFS('06-2026'!$C$7:$C$463,$B50,'06-2026'!$A$7:$A$463,"Out-New",'06-2026'!$I$7:$I$463,$C50,'06-2026'!$CE$7:$CE$463,$A50) -> 0 | H50: =SUMIFS('06-2026'!$CB$7:$CB$463,'06-2026'!$C$7:$C$463,$B50,'06-2026'!$A$7:$A$463,"Termination",'06-2026'!$I$7:$I$463,$C50,'06-2026'!$CE$7:$CE$463,$A50) -> 0 | I50: =COUNTIFS('06-2026'!$C$7:$C$463,$B50,'06-2026'!$A$7:$A$463,"Termination",'06-2026'!$I$7:$I$463,$C50,'06-2026'!$CE$7:$CE$463,$A50) -> 0 | J50: =SUM(D50,F50,H50) -> 14058471 | K50: =SUM(E50,G50,I50) -> 1
A51: =A50 -> ANNK-HR | B51: =B50 -> PD | C51: VN1003 | D51: =SUMIFS('06-2026'!$CB$7:$CB$463,'06-2026'!$C$7:$C$463,$B51,'06-2026'!$A$7:$A$463,"Out",'06-2026'!$I$7:$I$463,$C51,'06-2026'!$CE$7:$CE$463,$A51) -> 220872645 | E51: =COUNTIFS('06-2026'!$C$7:$C$463,$B51,'06-2026'!$A$7:$A$463,"Out",'06-2026'!$I$7:$I$463,$C51,'06-2026'!$CE$7:$CE$463,$A51) -> 17 | F51: =SUMIFS('06-2026'!$CB$7:$CB$463,'06-2026'!$C$7:$C$463,$B51,'06-2026'!$A$7:$A$463,"Out-New",'06-2026'!$I$7:$I$463,$C51,'06-2026'!$CE$7:$CE$463,$A51) -> 0 | G51: =COUNTIFS('06-2026'!$C$7:$C$463,$B51,'06-2026'!$A$7:$A$463,"Out-New",'06-2026'!$I$7:$I$463,$C51,'06-2026'!$CE$7:$CE$463,$A51) -> 0 | H51: =SUMIFS('06-2026'!$CB$7:$CB$463,'06-2026'!$C$7:$C$463,$B51,'06-2026'!$A$7:$A$463,"Termination",'06-2026'!$I$7:$I$463,$C51,'06-2026'!$CE$7:$CE$463,$A51) -> 30464902 | I51: =COUNTIFS('06-2026'!$C$7:$C$463,$B51,'06-2026'!$A$7:$A$463,"Termination",'06-2026'!$I$7:$I$463,$C51,'06-2026'!$CE$7:$CE$463,$A51) -> 6 | J51: =SUM(D51,F51,H51) -> 251337547 | K51: =SUM(E51,G51,I51) -> 23
A52: =A51 -> ANNK-HR | B52: =B50 -> PD | C52: VN1004 | D52: =SUMIFS('06-2026'!$CB$7:$CB$463,'06-2026'!$C$7:$C$463,$B52,'06-2026'!$A$7:$A$463,"Out",'06-2026'!$I$7:$I$463,$C52,'06-2026'!$CE$7:$CE$463,$A52) -> 16193989 | E52: =COUNTIFS('06-2026'!$C$7:$C$463,$B52,'06-2026'!$A$7:$A$463,"Out",'06-2026'!$I$7:$I$463,$C52,'06-2026'!$CE$7:$CE$463,$A52) -> 1 | F52: =SUMIFS('06-2026'!$CB$7:$CB$463,'06-2026'!$C$7:$C$463,$B52,'06-2026'!$A$7:$A$463,"Out-New",'06-2026'!$I$7:$I$463,$C52,'06-2026'!$CE$7:$CE$463,$A52) -> 0 | G52: =COUNTIFS('06-2026'!$C$7:$C$463,$B52,'06-2026'!$A$7:$A$463,"Out-New",'06-2026'!$I$7:$I$463,$C52,'06-2026'!$CE$7:$CE$463,$A52) -> 0 | H52: =SUMIFS('06-2026'!$CB$7:$CB$463,'06-2026'!$C$7:$C$463,$B52,'06-2026'!$A$7:$A$463,"Termination",'06-2026'!$I$7:$I$463,$C52,'06-2026'!$CE$7:$CE$463,$A52) -> 0 | I52: =COUNTIFS('06-2026'!$C$7:$C$463,$B52,'06-2026'!$A$7:$A$463,"Termination",'06-2026'!$I$7:$I$463,$C52,'06-2026'!$CE$7:$CE$463,$A52) -> 0 | J52: =SUM(D52,F52,H52) -> 16193989 | K52: =SUM(E52,G52,I52) -> 1
A53: =A52 -> ANNK-HR | B53: =B50 -> PD | C53: VN1005 | D53: =SUMIFS('06-2026'!$CB$7:$CB$463,'06-2026'!$C$7:$C$463,$B53,'06-2026'!$A$7:$A$463,"Out",'06-2026'!$I$7:$I$463,$C53,'06-2026'!$CE$7:$CE$463,$A53) -> 14821013 | E53: =COUNTIFS('06-2026'!$C$7:$C$463,$B53,'06-2026'!$A$7:$A$463,"Out",'06-2026'!$I$7:$I$463,$C53,'06-2026'!$CE$7:$CE$463,$A53) -> 1 | F53: =SUMIFS('06-2026'!$CB$7:$CB$463,'06-2026'!$C$7:$C$463,$B53,'06-2026'!$A$7:$A$463,"Out-New",'06-2026'!$I$7:$I$463,$C53,'06-2026'!$CE$7:$CE$463,$A53) -> 0 | G53: =COUNTIFS('06-2026'!$C$7:$C$463,$B53,'06-2026'!$A$7:$A$463,"Out-New",'06-2026'!$I$7:$I$463,$C53,'06-2026'!$CE$7:$CE$463,$A53) -> 0 | H53: =SUMIFS('06-2026'!$CB$7:$CB$463,'06-2026'!$C$7:$C$463,$B53,'06-2026'!$A$7:$A$463,"Termination",'06-2026'!$I$7:$I$463,$C53,'06-2026'!$CE$7:$CE$463,$A53) -> 0 | I53: =COUNTIFS('06-2026'!$C$7:$C$463,$B53,'06-2026'!$A$7:$A$463,"Termination",'06-2026'!$I$7:$I$463,$C53,'06-2026'!$CE$7:$CE$463,$A53) -> 0 | J53: =SUM(D53,F53,H53) -> 14821013 | K53: =SUM(E53,G53,I53) -> 1
A54: =A53 -> ANNK-HR | B54: =B51 -> PD | C54: VN1006 | D54: =SUMIFS('06-2026'!$CB$7:$CB$463,'06-2026'!$C$7:$C$463,$B54,'06-2026'!$A$7:$A$463,"Out",'06-2026'!$I$7:$I$463,$C54,'06-2026'!$CE$7:$CE$463,$A54) -> 226430202 | E54: =COUNTIFS('06-2026'!$C$7:$C$463,$B54,'06-2026'!$A$7:$A$463,"Out",'06-2026'!$I$7:$I$463,$C54,'06-2026'!$CE$7:$CE$463,$A54) -> 16 | F54: =SUMIFS('06-2026'!$CB$7:$CB$463,'06-2026'!$C$7:$C$463,$B54,'06-2026'!$A$7:$A$463,"Out-New",'06-2026'!$I$7:$I$463,$C54,'06-2026'!$CE$7:$CE$463,$A54) -> 0 | G54: =COUNTIFS('06-2026'!$C$7:$C$463,$B54,'06-2026'!$A$7:$A$463,"Out-New",'06-2026'!$I$7:$I$463,$C54,'06-2026'!$CE$7:$CE$463,$A54) -> 0 | H54: =SUMIFS('06-2026'!$CB$7:$CB$463,'06-2026'!$C$7:$C$463,$B54,'06-2026'!$A$7:$A$463,"Termination",'06-2026'!$I$7:$I$463,$C54,'06-2026'!$CE$7:$CE$463,$A54) -> 1144063 | I54: =COUNTIFS('06-2026'!$C$7:$C$463,$B54,'06-2026'!$A$7:$A$463,"Termination",'06-2026'!$I$7:$I$463,$C54,'06-2026'!$CE$7:$CE$463,$A54) -> 2 | J54: =SUM(D54,F54,H54) -> 227574265 | K54: =SUM(E54,G54,I54) -> 18
A55: =A54 -> ANNK-HR | B55: PD | C55: VN1007 | D55: =SUMIFS('06-2026'!$CB$7:$CB$463,'06-2026'!$C$7:$C$463,$B55,'06-2026'!$A$7:$A$463,"Out",'06-2026'!$I$7:$I$463,$C55,'06-2026'!$CE$7:$CE$463,$A55) -> 0 | E55: =COUNTIFS('06-2026'!$C$7:$C$463,$B55,'06-2026'!$A$7:$A$463,"Out",'06-2026'!$I$7:$I$463,$C55,'06-2026'!$CE$7:$CE$463,$A55) -> 0 | F55: =SUMIFS('06-2026'!$CB$7:$CB$463,'06-2026'!$C$7:$C$463,$B55,'06-2026'!$A$7:$A$463,"Out-New",'06-2026'!$I$7:$I$463,$C55,'06-2026'!$CE$7:$CE$463,$A55) -> 0 | G55: =COUNTIFS('06-2026'!$C$7:$C$463,$B55,'06-2026'!$A$7:$A$463,"Out-New",'06-2026'!$I$7:$I$463,$C55,'06-2026'!$CE$7:$CE$463,$A55) -> 0 | H55: =SUMIFS('06-2026'!$CB$7:$CB$463,'06-2026'!$C$7:$C$463,$B55,'06-2026'!$A$7:$A$463,"Termination",'06-2026'!$I$7:$I$463,$C55,'06-2026'!$CE$7:$CE$463,$A55) -> 0 | I55: =COUNTIFS('06-2026'!$C$7:$C$463,$B55,'06-2026'!$A$7:$A$463,"Termination",'06-2026'!$I$7:$I$463,$C55,'06-2026'!$CE$7:$CE$463,$A55) -> 0 | J55: =SUM(D55,F55,H55) -> 0 | K55: =SUM(E55,G55,I55) -> 0
A56: =A55 -> ANNK-HR | B56: =B53 -> PD | C56: VN1008 | D56: =SUMIFS('06-2026'!$CB$7:$CB$463,'06-2026'!$C$7:$C$463,$B56,'06-2026'!$A$7:$A$463,"Out",'06-2026'!$I$7:$I$463,$C56,'06-2026'!$CE$7:$CE$463,$A56) -> 20885528 | E56: =COUNTIFS('06-2026'!$C$7:$C$463,$B56,'06-2026'!$A$7:$A$463,"Out",'06-2026'!$I$7:$I$463,$C56,'06-2026'!$CE$7:$CE$463,$A56) -> 2 | F56: =SUMIFS('06-2026'!$CB$7:$CB$463,'06-2026'!$C$7:$C$463,$B56,'06-2026'!$A$7:$A$463,"Out-New",'06-2026'!$I$7:$I$463,$C56,'06-2026'!$CE$7:$CE$463,$A56) -> 0 | G56: =COUNTIFS('06-2026'!$C$7:$C$463,$B56,'06-2026'!$A$7:$A$463,"Out-New",'06-2026'!$I$7:$I$463,$C56,'06-2026'!$CE$7:$CE$463,$A56) -> 0 | H56: =SUMIFS('06-2026'!$CB$7:$CB$463,'06-2026'!$C$7:$C$463,$B56,'06-2026'!$A$7:$A$463,"Termination",'06-2026'!$I$7:$I$463,$C56,'06-2026'!$CE$7:$CE$463,$A56) -> 0 | I56: =COUNTIFS('06-2026'!$C$7:$C$463,$B56,'06-2026'!$A$7:$A$463,"Termination",'06-2026'!$I$7:$I$463,$C56,'06-2026'!$CE$7:$CE$463,$A56) -> 0 | J56: =SUM(D56,F56,H56) -> 20885528 | K56: =SUM(E56,G56,I56) -> 2
A57: =A56 -> ANNK-HR | B57: =B53 -> PD | C57: VN1021 | D57: =SUMIFS('06-2026'!$CB$7:$CB$463,'06-2026'!$C$7:$C$463,$B57,'06-2026'!$A$7:$A$463,"Out",'06-2026'!$I$7:$I$463,$C57,'06-2026'!$CE$7:$CE$463,$A57) -> 0 | E57: =COUNTIFS('06-2026'!$C$7:$C$463,$B57,'06-2026'!$A$7:$A$463,"Out",'06-2026'!$I$7:$I$463,$C57,'06-2026'!$CE$7:$CE$463,$A57) -> 0 | F57: =SUMIFS('06-2026'!$CB$7:$CB$463,'06-2026'!$C$7:$C$463,$B57,'06-2026'!$A$7:$A$463,"Out-New",'06-2026'!$I$7:$I$463,$C57,'06-2026'!$CE$7:$CE$463,$A57) -> 0 | G57: =COUNTIFS('06-2026'!$C$7:$C$463,$B57,'06-2026'!$A$7:$A$463,"Out-New",'06-2026'!$I$7:$I$463,$C57,'06-2026'!$CE$7:$CE$463,$A57) -> 0 | H57: =SUMIFS('06-2026'!$CB$7:$CB$463,'06-2026'!$C$7:$C$463,$B57,'06-2026'!$A$7:$A$463,"Termination",'06-2026'!$I$7:$I$463,$C57,'06-2026'!$CE$7:$CE$463,$A57) -> 0 | I57: =COUNTIFS('06-2026'!$C$7:$C$463,$B57,'06-2026'!$A$7:$A$463,"Termination",'06-2026'!$I$7:$I$463,$C57,'06-2026'!$CE$7:$CE$463,$A57) -> 0 | J57: =SUM(D57,F57,H57) -> 0 | K57: =SUM(E57,G57,I57) -> 0
A58: =A57 -> ANNK-HR | B58: =B54 -> PD | C58: VN1022 | D58: =SUMIFS('06-2026'!$CB$7:$CB$463,'06-2026'!$C$7:$C$463,$B58,'06-2026'!$A$7:$A$463,"Out",'06-2026'!$I$7:$I$463,$C58,'06-2026'!$CE$7:$CE$463,$A58) -> 0 | E58: =COUNTIFS('06-2026'!$C$7:$C$463,$B58,'06-2026'!$A$7:$A$463,"Out",'06-2026'!$I$7:$I$463,$C58,'06-2026'!$CE$7:$CE$463,$A58) -> 0 | F58: =SUMIFS('06-2026'!$CB$7:$CB$463,'06-2026'!$C$7:$C$463,$B58,'06-2026'!$A$7:$A$463,"Out-New",'06-2026'!$I$7:$I$463,$C58,'06-2026'!$CE$7:$CE$463,$A58) -> 0 | G58: =COUNTIFS('06-2026'!$C$7:$C$463,$B58,'06-2026'!$A$7:$A$463,"Out-New",'06-2026'!$I$7:$I$463,$C58,'06-2026'!$CE$7:$CE$463,$A58) -> 0 | H58: =SUMIFS('06-2026'!$CB$7:$CB$463,'06-2026'!$C$7:$C$463,$B58,'06-2026'!$A$7:$A$463,"Termination",'06-2026'!$I$7:$I$463,$C58,'06-2026'!$CE$7:$CE$463,$A58) -> 0 | I58: =COUNTIFS('06-2026'!$C$7:$C$463,$B58,'06-2026'!$A$7:$A$463,"Termination",'06-2026'!$I$7:$I$463,$C58,'06-2026'!$CE$7:$CE$463,$A58) -> 0 | J58: =SUM(D58,F58,H58) -> 0 | K58: =SUM(E58,G58,I58) -> 0
A59: =A58 -> ANNK-HR | B59: R&D | C59: VN3001 | D59: =SUMIFS('06-2026'!$CB$7:$CB$463,'06-2026'!$C$7:$C$463,$B59,'06-2026'!$A$7:$A$463,"Out",'06-2026'!$I$7:$I$463,$C59,'06-2026'!$CE$7:$CE$463,$A59) -> 91747077 | E59: =COUNTIFS('06-2026'!$C$7:$C$463,$B59,'06-2026'!$A$7:$A$463,"Out",'06-2026'!$I$7:$I$463,$C59,'06-2026'!$CE$7:$CE$463,$A59) -> 7 | F59: =SUMIFS('06-2026'!$CB$7:$CB$463,'06-2026'!$C$7:$C$463,$B59,'06-2026'!$A$7:$A$463,"Out-New",'06-2026'!$I$7:$I$463,$C59,'06-2026'!$CE$7:$CE$463,$A59) -> 0 | G59: =COUNTIFS('06-2026'!$C$7:$C$463,$B59,'06-2026'!$A$7:$A$463,"Out-New",'06-2026'!$I$7:$I$463,$C59,'06-2026'!$CE$7:$CE$463,$A59) -> 0 | H59: =SUMIFS('06-2026'!$CB$7:$CB$463,'06-2026'!$C$7:$C$463,$B59,'06-2026'!$A$7:$A$463,"Termination",'06-2026'!$I$7:$I$463,$C59,'06-2026'!$CE$7:$CE$463,$A59) -> 11866590 | I59: =COUNTIFS('06-2026'!$C$7:$C$463,$B59,'06-2026'!$A$7:$A$463,"Termination",'06-2026'!$I$7:$I$463,$C59,'06-2026'!$CE$7:$CE$463,$A59) -> 1 | J59: =SUM(D59,F59,H59) -> 103613667 | K59: =SUM(E59,G59,I59) -> 8
A60: =A59 -> ANNK-HR | B60: PD Total | D60: =SUM(D49:D59) -> 8.184386e+08 | E60: =SUM(E49:E59) -> 61 | F60: =SUM(F49:F59) -> 0 | G60: =SUM(G49:G59) -> 0 | H60: =SUM(H49:H59) -> 44541635 | I60: =SUM(I49:I59) -> 12 | J60: =SUM(J49:J59) -> 8.6298024e+08 | K60: =SUM(K49:K59) -> 73
A61: =A60 -> ANNK-HR | B61: QA | C61: VN3007 | D61: =SUMIFS('06-2026'!$CB$7:$CB$463,'06-2026'!$C$7:$C$463,$B61,'06-2026'!$A$7:$A$463,"Out",'06-2026'!$I$7:$I$463,$C61,'06-2026'!$CE$7:$CE$463,$A61) -> 0 | E61: =COUNTIFS('06-2026'!$C$7:$C$463,$B61,'06-2026'!$A$7:$A$463,"Out",'06-2026'!$I$7:$I$463,$C61,'06-2026'!$CE$7:$CE$463,$A61) -> 0 | F61: =SUMIFS('06-2026'!$CB$7:$CB$463,'06-2026'!$C$7:$C$463,$B61,'06-2026'!$A$7:$A$463,"Out-New",'06-2026'!$I$7:$I$463,$C61,'06-2026'!$CE$7:$CE$463,$A61) -> 0 | G61: =COUNTIFS('06-2026'!$C$7:$C$463,$B61,'06-2026'!$A$7:$A$463,"Out-New",'06-2026'!$I$7:$I$463,$C61,'06-2026'!$CE$7:$CE$463,$A61) -> 0 | H61: =SUMIFS('06-2026'!$CB$7:$CB$463,'06-2026'!$C$7:$C$463,$B61,'06-2026'!$A$7:$A$463,"Termination",'06-2026'!$I$7:$I$463,$C61,'06-2026'!$CE$7:$CE$463,$A61) -> 0 | I61: =COUNTIFS('06-2026'!$C$7:$C$463,$B61,'06-2026'!$A$7:$A$463,"Termination",'06-2026'!$I$7:$I$463,$C61,'06-2026'!$CE$7:$CE$463,$A61) -> 0 | J61: =SUM(D61,F61,H61) -> 0 | K61: =SUM(E61,G61,I61) -> 0
A62: =A61 -> ANNK-HR | B62: QA | C62: VN1022 | D62: =SUMIFS('06-2026'!$CB$7:$CB$463,'06-2026'!$C$7:$C$463,$B62,'06-2026'!$A$7:$A$463,"Out",'06-2026'!$I$7:$I$463,$C62,'06-2026'!$CE$7:$CE$463,$A62) -> 0 | E62: =COUNTIFS('06-2026'!$C$7:$C$463,$B62,'06-2026'!$A$7:$A$463,"Out",'06-2026'!$I$7:$I$463,$C62,'06-2026'!$CE$7:$CE$463,$A62) -> 0 | F62: =SUMIFS('06-2026'!$CB$7:$CB$463,'06-2026'!$C$7:$C$463,$B62,'06-2026'!$A$7:$A$463,"Out-New",'06-2026'!$I$7:$I$463,$C62,'06-2026'!$CE$7:$CE$463,$A62) -> 0 | G62: =COUNTIFS('06-2026'!$C$7:$C$463,$B62,'06-2026'!$A$7:$A$463,"Out-New",'06-2026'!$I$7:$I$463,$C62,'06-2026'!$CE$7:$CE$463,$A62) -> 0 | H62: =SUMIFS('06-2026'!$CB$7:$CB$463,'06-2026'!$C$7:$C$463,$B62,'06-2026'!$A$7:$A$463,"Termination",'06-2026'!$I$7:$I$463,$C62,'06-2026'!$CE$7:$CE$463,$A62) -> 0 | I62: =COUNTIFS('06-2026'!$C$7:$C$463,$B62,'06-2026'!$A$7:$A$463,"Termination",'06-2026'!$I$7:$I$463,$C62,'06-2026'!$CE$7:$CE$463,$A62) -> 0 | J62: =SUM(D62,F62,H62) -> 0 | K62: =SUM(E62,G62,I62) -> 0
A63: =A62 -> ANNK-HR | B63: QA | C63: VN1071 | D63: =SUMIFS('06-2026'!$CB$7:$CB$463,'06-2026'!$C$7:$C$463,$B63,'06-2026'!$A$7:$A$463,"Out",'06-2026'!$I$7:$I$463,$C63,'06-2026'!$CE$7:$CE$463,$A63) -> 0 | E63: =COUNTIFS('06-2026'!$C$7:$C$463,$B63,'06-2026'!$A$7:$A$463,"Out",'06-2026'!$I$7:$I$463,$C63,'06-2026'!$CE$7:$CE$463,$A63) -> 0 | F63: =SUMIFS('06-2026'!$CB$7:$CB$463,'06-2026'!$C$7:$C$463,$B63,'06-2026'!$A$7:$A$463,"Out-New",'06-2026'!$I$7:$I$463,$C63,'06-2026'!$CE$7:$CE$463,$A63) -> 0 | G63: =COUNTIFS('06-2026'!$C$7:$C$463,$B63,'06-2026'!$A$7:$A$463,"Out-New",'06-2026'!$I$7:$I$463,$C63,'06-2026'!$CE$7:$CE$463,$A63) -> 0 | H63: =SUMIFS('06-2026'!$CB$7:$CB$463,'06-2026'!$C$7:$C$463,$B63,'06-2026'!$A$7:$A$463,"Termination",'06-2026'!$I$7:$I$463,$C63,'06-2026'!$CE$7:$CE$463,$A63) -> 0 | I63: =COUNTIFS('06-2026'!$C$7:$C$463,$B63,'06-2026'!$A$7:$A$463,"Termination",'06-2026'!$I$7:$I$463,$C63,'06-2026'!$CE$7:$CE$463,$A63) -> 0 | J63: =SUM(D63,F63,H63) -> 0 | K63: =SUM(E63,G63,I63) -> 0
A64: =A63 -> ANNK-HR | B64: QA Total | D64: =SUM(D61:D63) -> 0 | E64: =SUM(E61:E63) -> 0 | F64: =SUM(F61:F63) -> 0 | G64: =SUM(G61:G63) -> 0 | H64: =SUM(H61:H63) -> 0 | I64: =SUM(I61:I63) -> 0 | J64: =SUM(J61:J63) -> 0 | K64: =SUM(K61:K63) -> 0
A65: ANNK-HR Total | D65: =SUM(D37,D43,D48,D60,D64,D45,D39,D41) -> 9.0545169e+08 | E65: =SUM(E37,E43,E48,E60,E64,E45,E39,E41) -> 67 | F65: =SUM(F37,F43,F48,F60,F64,F45,F39,F41) -> 0 | G65: =SUM(G37,G43,G48,G60,G64,G45,G39,G41) -> 0 | H65: =SUM(H37,H43,H48,H60,H64,H45,H39,H41) -> 85915527 | I65: =SUM(I37,I43,I48,I60,I64,I45,I39,I41) -> 17 | J65: =SUM(J37,J43,J48,J60,J64,J45,J39,J41) -> 9.9136722e+08 | K65: =SUM(K37,K43,K48,K60,K64,K45,K39,K41) -> 84
A66: Nhân Kiệt | B66: LG | C66: VN1006 | D66: =SUMIFS('06-2026'!$CB$7:$CB$463,'06-2026'!$C$7:$C$463,$B66,'06-2026'!$A$7:$A$463,"Out",'06-2026'!$I$7:$I$463,$C66,'06-2026'!$CE$7:$CE$463,$A66) -> 0 | E66: =COUNTIFS('06-2026'!$C$7:$C$463,$B66,'06-2026'!$A$7:$A$463,"Out",'06-2026'!$I$7:$I$463,$C66,'06-2026'!$CE$7:$CE$463,$A66) -> 0 | F66: =SUMIFS('06-2026'!$CB$7:$CB$463,'06-2026'!$C$7:$C$463,$B66,'06-2026'!$A$7:$A$463,"Out-New",'06-2026'!$I$7:$I$463,$C66,'06-2026'!$CE$7:$CE$463,$A66) -> 0 | G66: =COUNTIFS('06-2026'!$C$7:$C$463,$B66,'06-2026'!$A$7:$A$463,"Out-New",'06-2026'!$I$7:$I$463,$C66,'06-2026'!$CE$7:$CE$463,$A66) -> 0 | H66: =SUMIFS('06-2026'!$CB$7:$CB$463,'06-2026'!$C$7:$C$463,$B66,'06-2026'!$A$7:$A$463,"Termination",'06-2026'!$I$7:$I$463,$C66,'06-2026'!$CE$7:$CE$463,$A66) -> 0 | I66: =COUNTIFS('06-2026'!$C$7:$C$463,$B66,'06-2026'!$A$7:$A$463,"Termination",'06-2026'!$I$7:$I$463,$C66,'06-2026'!$CE$7:$CE$463,$A66) -> 0 | J66: =SUM(D66,F66,H66) -> 0 | K66: =SUM(E66,G66,I66) -> 0
A67: =A66 -> Nhân Kiệt | B67: =B66 -> LG | C67: VN1033 | D67: =SUMIFS('06-2026'!$CB$7:$CB$463,'06-2026'!$C$7:$C$463,$B67,'06-2026'!$A$7:$A$463,"Out",'06-2026'!$I$7:$I$463,$C67,'06-2026'!$CE$7:$CE$463,$A67) -> 0 | E67: =COUNTIFS('06-2026'!$C$7:$C$463,$B67,'06-2026'!$A$7:$A$463,"Out",'06-2026'!$I$7:$I$463,$C67,'06-2026'!$CE$7:$CE$463,$A67) -> 0 | F67: =SUMIFS('06-2026'!$CB$7:$CB$463,'06-2026'!$C$7:$C$463,$B67,'06-2026'!$A$7:$A$463,"Out-New",'06-2026'!$I$7:$I$463,$C67,'06-2026'!$CE$7:$CE$463,$A67) -> 0 | G67: =COUNTIFS('06-2026'!$C$7:$C$463,$B67,'06-2026'!$A$7:$A$463,"Out-New",'06-2026'!$I$7:$I$463,$C67,'06-2026'!$CE$7:$CE$463,$A67) -> 0 | H67: =SUMIFS('06-2026'!$CB$7:$CB$463,'06-2026'!$C$7:$C$463,$B67,'06-2026'!$A$7:$A$463,"Termination",'06-2026'!$I$7:$I$463,$C67,'06-2026'!$CE$7:$CE$463,$A67) -> 0 | I67: =COUNTIFS('06-2026'!$C$7:$C$463,$B67,'06-2026'!$A$7:$A$463,"Termination",'06-2026'!$I$7:$I$463,$C67,'06-2026'!$CE$7:$CE$463,$A67) -> 0 | J67: =SUM(D67,F67,H67) -> 0 | K67: =SUM(E67,G67,I67) -> 0
A68: =A67 -> Nhân Kiệt | B68: =B67 -> LG | C68: VN1042 | D68: =SUMIFS('06-2026'!$CB$7:$CB$463,'06-2026'!$C$7:$C$463,$B68,'06-2026'!$A$7:$A$463,"Out",'06-2026'!$I$7:$I$463,$C68,'06-2026'!$CE$7:$CE$463,$A68) -> 31038162 | E68: =COUNTIFS('06-2026'!$C$7:$C$463,$B68,'06-2026'!$A$7:$A$463,"Out",'06-2026'!$I$7:$I$463,$C68,'06-2026'!$CE$7:$CE$463,$A68) -> 2 | F68: =SUMIFS('06-2026'!$CB$7:$CB$463,'06-2026'!$C$7:$C$463,$B68,'06-2026'!$A$7:$A$463,"Out-New",'06-2026'!$I$7:$I$463,$C68,'06-2026'!$CE$7:$CE$463,$A68) -> 0 | G68: =COUNTIFS('06-2026'!$C$7:$C$463,$B68,'06-2026'!$A$7:$A$463,"Out-New",'06-2026'!$I$7:$I$463,$C68,'06-2026'!$CE$7:$CE$463,$A68) -> 0 | H68: =SUMIFS('06-2026'!$CB$7:$CB$463,'06-2026'!$C$7:$C$463,$B68,'06-2026'!$A$7:$A$463,"Termination",'06-2026'!$I$7:$I$463,$C68,'06-2026'!$CE$7:$CE$463,$A68) -> 0 | I68: =COUNTIFS('06-2026'!$C$7:$C$463,$B68,'06-2026'!$A$7:$A$463,"Termination",'06-2026'!$I$7:$I$463,$C68,'06-2026'!$CE$7:$CE$463,$A68) -> 0 | J68: =SUM(D68,F68,H68) -> 31038162 | K68: =SUM(E68,G68,I68) -> 2
A69: =A68 -> Nhân Kiệt | B69: LG Total | D69: =SUM(D66:D68) -> 31038162 | E69: =SUM(E66:E68) -> 2 | F69: =SUM(F66:F68) -> 0 | G69: =SUM(G66:G68) -> 0 | H69: =SUM(H66:H68) -> 0 | I69: =SUM(I66:I68) -> 0 | J69: =SUM(J66:J68) -> 31038162 | K69: =SUM(K66:K68) -> 2
A70: =A69 -> Nhân Kiệt | B70: ME | C70: VN1002 | D70: =SUMIFS('06-2026'!$CB$7:$CB$463,'06-2026'!$C$7:$C$463,$B70,'06-2026'!$A$7:$A$463,"Out",'06-2026'!$I$7:$I$463,$C70,'06-2026'!$CE$7:$CE$463,$A70) -> 0 | E70: =COUNTIFS('06-2026'!$C$7:$C$463,$B70,'06-2026'!$A$7:$A$463,"Out",'06-2026'!$I$7:$I$463,$C70,'06-2026'!$CE$7:$CE$463,$A70) -> 0 | F70: =SUMIFS('06-2026'!$CB$7:$CB$463,'06-2026'!$C$7:$C$463,$B70,'06-2026'!$A$7:$A$463,"Out-New",'06-2026'!$I$7:$I$463,$C70,'06-2026'!$CE$7:$CE$463,$A70) -> 0 | G70: =COUNTIFS('06-2026'!$C$7:$C$463,$B70,'06-2026'!$A$7:$A$463,"Out-New",'06-2026'!$I$7:$I$463,$C70,'06-2026'!$CE$7:$CE$463,$A70) -> 0 | H70: =SUMIFS('06-2026'!$CB$7:$CB$463,'06-2026'!$C$7:$C$463,$B70,'06-2026'!$A$7:$A$463,"Termination",'06-2026'!$I$7:$I$463,$C70,'06-2026'!$CE$7:$CE$463,$A70) -> 0 | I70: =COUNTIFS('06-2026'!$C$7:$C$463,$B70,'06-2026'!$A$7:$A$463,"Termination",'06-2026'!$I$7:$I$463,$C70,'06-2026'!$CE$7:$CE$463,$A70) -> 0 | J70: =SUM(D70,F70,H70) -> 0 | K70: =SUM(E70,G70,I70) -> 0
A71: =A70 -> Nhân Kiệt | B71: =B70 -> ME | C71: VN1006 | D71: =SUMIFS('06-2026'!$CB$7:$CB$463,'06-2026'!$C$7:$C$463,$B71,'06-2026'!$A$7:$A$463,"Out",'06-2026'!$I$7:$I$463,$C71,'06-2026'!$CE$7:$CE$463,$A71) -> 0 | E71: =COUNTIFS('06-2026'!$C$7:$C$463,$B71,'06-2026'!$A$7:$A$463,"Out",'06-2026'!$I$7:$I$463,$C71,'06-2026'!$CE$7:$CE$463,$A71) -> 0 | F71: =SUMIFS('06-2026'!$CB$7:$CB$463,'06-2026'!$C$7:$C$463,$B71,'06-2026'!$A$7:$A$463,"Out-New",'06-2026'!$I$7:$I$463,$C71,'06-2026'!$CE$7:$CE$463,$A71) -> 0 | G71: =COUNTIFS('06-2026'!$C$7:$C$463,$B71,'06-2026'!$A$7:$A$463,"Out-New",'06-2026'!$I$7:$I$463,$C71,'06-2026'!$CE$7:$CE$463,$A71) -> 0 | H71: =SUMIFS('06-2026'!$CB$7:$CB$463,'06-2026'!$C$7:$C$463,$B71,'06-2026'!$A$7:$A$463,"Termination",'06-2026'!$I$7:$I$463,$C71,'06-2026'!$CE$7:$CE$463,$A71) -> 0 | I71: =COUNTIFS('06-2026'!$C$7:$C$463,$B71,'06-2026'!$A$7:$A$463,"Termination",'06-2026'!$I$7:$I$463,$C71,'06-2026'!$CE$7:$CE$463,$A71) -> 0 | J71: =SUM(D71,F71,H71) -> 0 | K71: =SUM(E71,G71,I71) -> 0
A72: =A71 -> Nhân Kiệt | B72: =B71 -> ME | C72: VN1021 | D72: =SUMIFS('06-2026'!$CB$7:$CB$463,'06-2026'!$C$7:$C$463,$B72,'06-2026'!$A$7:$A$463,"Out",'06-2026'!$I$7:$I$463,$C72,'06-2026'!$CE$7:$CE$463,$A72) -> 0 | E72: =COUNTIFS('06-2026'!$C$7:$C$463,$B72,'06-2026'!$A$7:$A$463,"Out",'06-2026'!$I$7:$I$463,$C72,'06-2026'!$CE$7:$CE$463,$A72) -> 0 | F72: =SUMIFS('06-2026'!$CB$7:$CB$463,'06-2026'!$C$7:$C$463,$B72,'06-2026'!$A$7:$A$463,"Out-New",'06-2026'!$I$7:$I$463,$C72,'06-2026'!$CE$7:$CE$463,$A72) -> 0 | G72: =COUNTIFS('06-2026'!$C$7:$C$463,$B72,'06-2026'!$A$7:$A$463,"Out-New",'06-2026'!$I$7:$I$463,$C72,'06-2026'!$CE$7:$CE$463,$A72) -> 0 | H72: =SUMIFS('06-2026'!$CB$7:$CB$463,'06-2026'!$C$7:$C$463,$B72,'06-2026'!$A$7:$A$463,"Termination",'06-2026'!$I$7:$I$463,$C72,'06-2026'!$CE$7:$CE$463,$A72) -> 0 | I72: =COUNTIFS('06-2026'!$C$7:$C$463,$B72,'06-2026'!$A$7:$A$463,"Termination",'06-2026'!$I$7:$I$463,$C72,'06-2026'!$CE$7:$CE$463,$A72) -> 0 | J72: =SUM(D72,F72,H72) -> 0 | K72: =SUM(E72,G72,I72) -> 0
A73: =A72 -> Nhân Kiệt | B73: =B72 -> ME | C73: VN1024 | D73: =SUMIFS('06-2026'!$CB$7:$CB$463,'06-2026'!$C$7:$C$463,$B73,'06-2026'!$A$7:$A$463,"Out",'06-2026'!$I$7:$I$463,$C73,'06-2026'!$CE$7:$CE$463,$A73) -> 0 | E73: =COUNTIFS('06-2026'!$C$7:$C$463,$B73,'06-2026'!$A$7:$A$463,"Out",'06-2026'!$I$7:$I$463,$C73,'06-2026'!$CE$7:$CE$463,$A73) -> 0 | F73: =SUMIFS('06-2026'!$CB$7:$CB$463,'06-2026'!$C$7:$C$463,$B73,'06-2026'!$A$7:$A$463,"Out-New",'06-2026'!$I$7:$I$463,$C73,'06-2026'!$CE$7:$CE$463,$A73) -> 0 | G73: =COUNTIFS('06-2026'!$C$7:$C$463,$B73,'06-2026'!$A$7:$A$463,"Out-New",'06-2026'!$I$7:$I$463,$C73,'06-2026'!$CE$7:$CE$463,$A73) -> 0 | H73: =SUMIFS('06-2026'!$CB$7:$CB$463,'06-2026'!$C$7:$C$463,$B73,'06-2026'!$A$7:$A$463,"Termination",'06-2026'!$I$7:$I$463,$C73,'06-2026'!$CE$7:$CE$463,$A73) -> 0 | I73: =COUNTIFS('06-2026'!$C$7:$C$463,$B73,'06-2026'!$A$7:$A$463,"Termination",'06-2026'!$I$7:$I$463,$C73,'06-2026'!$CE$7:$CE$463,$A73) -> 0 | J73: =SUM(D73,F73,H73) -> 0 | K73: =SUM(E73,G73,I73) -> 0
A74: =A72 -> Nhân Kiệt | B74: ME Total | D74: =SUM(D70:D73) -> 0 | E74: =SUM(E70:E73) -> 0 | F74: =SUM(F70:F73) -> 0 | G74: =SUM(G70:G73) -> 0 | H74: =SUM(H70:H73) -> 0 | I74: =SUM(I70:I73) -> 0 | J74: =SUM(J70:J73) -> 0 | K74: =SUM(K70:K73) -> 0
A75: =A74 -> Nhân Kiệt | B75: MM | C75: VN1054 | D75: =SUMIFS('06-2026'!$CB$7:$CB$463,'06-2026'!$C$7:$C$463,$B75,'06-2026'!$A$7:$A$463,"Out",'06-2026'!$I$7:$I$463,$C75,'06-2026'!$CE$7:$CE$463,$A75) -> 0 | E75: =COUNTIFS('06-2026'!$C$7:$C$463,$B75,'06-2026'!$A$7:$A$463,"Out",'06-2026'!$I$7:$I$463,$C75,'06-2026'!$CE$7:$CE$463,$A75) -> 0 | F75: =SUMIFS('06-2026'!$CB$7:$CB$463,'06-2026'!$C$7:$C$463,$B75,'06-2026'!$A$7:$A$463,"Out-New",'06-2026'!$I$7:$I$463,$C75,'06-2026'!$CE$7:$CE$463,$A75) -> 0 | G75: =COUNTIFS('06-2026'!$C$7:$C$463,$B75,'06-2026'!$A$7:$A$463,"Out-New",'06-2026'!$I$7:$I$463,$C75,'06-2026'!$CE$7:$CE$463,$A75) -> 0 | H75: =SUMIFS('06-2026'!$CB$7:$CB$463,'06-2026'!$C$7:$C$463,$B75,'06-2026'!$A$7:$A$463,"Termination",'06-2026'!$I$7:$I$463,$C75,'06-2026'!$CE$7:$CE$463,$A75) -> 0 | I75: =COUNTIFS('06-2026'!$C$7:$C$463,$B75,'06-2026'!$A$7:$A$463,"Termination",'06-2026'!$I$7:$I$463,$C75,'06-2026'!$CE$7:$CE$463,$A75) -> 0 | J75: =SUM(D75,F75,H75) -> 0 | K75: =SUM(E75,G75,I75) -> 0
A76: =A75 -> Nhân Kiệt | B76: MM Total | D76: =D75 -> 0 | E76: =E75 -> 0 | F76: =F75 -> 0 | G76: =G75 -> 0 | H76: =H75 -> 0 | I76: =I75 -> 0 | J76: =J75 -> 0 | K76: =K75 -> 0
A77: =A76 -> Nhân Kiệt | B77: FIN | C77: VN7040 | D77: =SUMIFS('06-2026'!$CB$7:$CB$463,'06-2026'!$C$7:$C$463,$B77,'06-2026'!$A$7:$A$463,"Out",'06-2026'!$I$7:$I$463,$C77,'06-2026'!$CE$7:$CE$463,$A77) -> 0 | E77: =COUNTIFS('06-2026'!$C$7:$C$463,$B77,'06-2026'!$A$7:$A$463,"Out",'06-2026'!$I$7:$I$463,$C77,'06-2026'!$CE$7:$CE$463,$A77) -> 0 | F77: =SUMIFS('06-2026'!$CB$7:$CB$463,'06-2026'!$C$7:$C$463,$B77,'06-2026'!$A$7:$A$463,"Out-New",'06-2026'!$I$7:$I$463,$C77,'06-2026'!$CE$7:$CE$463,$A77) -> 0 | G77: =COUNTIFS('06-2026'!$C$7:$C$463,$B77,'06-2026'!$A$7:$A$463,"Out-New",'06-2026'!$I$7:$I$463,$C77,'06-2026'!$CE$7:$CE$463,$A77) -> 0 | H77: =SUMIFS('06-2026'!$CB$7:$CB$463,'06-2026'!$C$7:$C$463,$B77,'06-2026'!$A$7:$A$463,"Termination",'06-2026'!$I$7:$I$463,$C77,'06-2026'!$CE$7:$CE$463,$A77) -> 0 | I77: =COUNTIFS('06-2026'!$C$7:$C$463,$B77,'06-2026'!$A$7:$A$463,"Termination",'06-2026'!$I$7:$I$463,$C77,'06-2026'!$CE$7:$CE$463,$A77) -> 0 | J77: =SUM(D77,F77,H77) -> 0 | K77: =SUM(E77,G77,I77) -> 0
A78: =A77 -> Nhân Kiệt | B78: FIN | C78: VN7043 | D78: =SUMIFS('06-2026'!$CB$7:$CB$463,'06-2026'!$C$7:$C$463,$B78,'06-2026'!$A$7:$A$463,"Out",'06-2026'!$I$7:$I$463,$C78,'06-2026'!$CE$7:$CE$463,$A78) -> 0 | E78: =COUNTIFS('06-2026'!$C$7:$C$463,$B78,'06-2026'!$A$7:$A$463,"Out",'06-2026'!$I$7:$I$463,$C78,'06-2026'!$CE$7:$CE$463,$A78) -> 0 | F78: =SUMIFS('06-2026'!$CB$7:$CB$463,'06-2026'!$C$7:$C$463,$B78,'06-2026'!$A$7:$A$463,"Out-New",'06-2026'!$I$7:$I$463,$C78,'06-2026'!$CE$7:$CE$463,$A78) -> 0 | G78: =COUNTIFS('06-2026'!$C$7:$C$463,$B78,'06-2026'!$A$7:$A$463,"Out-New",'06-2026'!$I$7:$I$463,$C78,'06-2026'!$CE$7:$CE$463,$A78) -> 0 | H78: =SUMIFS('06-2026'!$CB$7:$CB$463,'06-2026'!$C$7:$C$463,$B78,'06-2026'!$A$7:$A$463,"Termination",'06-2026'!$I$7:$I$463,$C78,'06-2026'!$CE$7:$CE$463,$A78) -> 0 | I78: =COUNTIFS('06-2026'!$C$7:$C$463,$B78,'06-2026'!$A$7:$A$463,"Termination",'06-2026'!$I$7:$I$463,$C78,'06-2026'!$CE$7:$CE$463,$A78) -> 0 | J78: =SUM(D78,F78,H78) -> 0 | K78: =SUM(E78,G78,I78) -> 0
A79: =A77 -> Nhân Kiệt | B79: FIN Total | D79: =SUM(D77:D78) -> 0 | E79: =SUM(E77:E78) -> 0 | F79: =SUM(F77:F78) -> 0 | G79: =SUM(G77:G78) -> 0 | H79: =SUM(H77:H78) -> 0 | I79: =SUM(I77:I78) -> 0 | J79: =SUM(J77:J78) -> 0 | K79: =SUM(K77:K78) -> 0
A80: =A79 -> Nhân Kiệt | B80: GPr | C80: VN1052 | D80: =SUMIFS('06-2026'!$CB$7:$CB$463,'06-2026'!$C$7:$C$463,$B80,'06-2026'!$A$7:$A$463,"Out",'06-2026'!$I$7:$I$463,$C80,'06-2026'!$CE$7:$CE$463,$A80) -> 0 | E80: =COUNTIFS('06-2026'!$C$7:$C$463,$B80,'06-2026'!$A$7:$A$463,"Out",'06-2026'!$I$7:$I$463,$C80,'06-2026'!$CE$7:$CE$463,$A80) -> 0 | F80: =SUMIFS('06-2026'!$CB$7:$CB$463,'06-2026'!$C$7:$C$463,$B80,'06-2026'!$A$7:$A$463,"Out-New",'06-2026'!$I$7:$I$463,$C80,'06-2026'!$CE$7:$CE$463,$A80) -> 0 | G80: =COUNTIFS('06-2026'!$C$7:$C$463,$B80,'06-2026'!$A$7:$A$463,"Out-New",'06-2026'!$I$7:$I$463,$C80,'06-2026'!$CE$7:$CE$463,$A80) -> 0 | H80: =SUMIFS('06-2026'!$CB$7:$CB$463,'06-2026'!$C$7:$C$463,$B80,'06-2026'!$A$7:$A$463,"Termination",'06-2026'!$I$7:$I$463,$C80,'06-2026'!$CE$7:$CE$463,$A80) -> 0 | I80: =COUNTIFS('06-2026'!$C$7:$C$463,$B80,'06-2026'!$A$7:$A$463,"Termination",'06-2026'!$I$7:$I$463,$C80,'06-2026'!$CE$7:$CE$463,$A80) -> 0 | J80: =SUM(D80,F80,H80) -> 0 | K80: =SUM(E80,G80,I80) -> 0
A81: =A80 -> Nhân Kiệt | B81: Grp Total | D81: =D80 -> 0 | E81: =E80 -> 0 | F81: =F80 -> 0 | G81: =G80 -> 0 | H81: =H80 -> 0 | I81: =I80 -> 0 | J81: =J80 -> 0 | K81: =K80 -> 0
A82: =A79 -> Nhân Kiệt | B82: PD | C82: VN1001 | D82: =SUMIFS('06-2026'!$CB$7:$CB$463,'06-2026'!$C$7:$C$463,$B82,'06-2026'!$A$7:$A$463,"Out",'06-2026'!$I$7:$I$463,$C82,'06-2026'!$CE$7:$CE$463,$A82) -> 1.0935924e+08 | E82: =COUNTIFS('06-2026'!$C$7:$C$463,$B82,'06-2026'!$A$7:$A$463,"Out",'06-2026'!$I$7:$I$463,$C82,'06-2026'!$CE$7:$CE$463,$A82) -> 8 | F82: =SUMIFS('06-2026'!$CB$7:$CB$463,'06-2026'!$C$7:$C$463,$B82,'06-2026'!$A$7:$A$463,"Out-New",'06-2026'!$I$7:$I$463,$C82,'06-2026'!$CE$7:$CE$463,$A82) -> 0 | G82: =COUNTIFS('06-2026'!$C$7:$C$463,$B82,'06-2026'!$A$7:$A$463,"Out-New",'06-2026'!$I$7:$I$463,$C82,'06-2026'!$CE$7:$CE$463,$A82) -> 0 | H82: =SUMIFS('06-2026'!$CB$7:$CB$463,'06-2026'!$C$7:$C$463,$B82,'06-2026'!$A$7:$A$463,"Termination",'06-2026'!$I$7:$I$463,$C82,'06-2026'!$CE$7:$CE$463,$A82) -> 21089042 | I82: =COUNTIFS('06-2026'!$C$7:$C$463,$B82,'06-2026'!$A$7:$A$463,"Termination",'06-2026'!$I$7:$I$463,$C82,'06-2026'!$CE$7:$CE$463,$A82) -> 3 | J82: =SUM(D82,F82,H82) -> 1.3044828e+08 | K82: =SUM(E82,G82,I82) -> 11
A83: =A82 -> Nhân Kiệt | B83: =B82 -> PD | C83: VN1002 | D83: =SUMIFS('06-2026'!$CB$7:$CB$463,'06-2026'!$C$7:$C$463,$B83,'06-2026'!$A$7:$A$463,"Out",'06-2026'!$I$7:$I$463,$C83,'06-2026'!$CE$7:$CE$463,$A83) -> 10806321 | E83: =COUNTIFS('06-2026'!$C$7:$C$463,$B83,'06-2026'!$A$7:$A$463,"Out",'06-2026'!$I$7:$I$463,$C83,'06-2026'!$CE$7:$CE$463,$A83) -> 1 | F83: =SUMIFS('06-2026'!$CB$7:$CB$463,'06-2026'!$C$7:$C$463,$B83,'06-2026'!$A$7:$A$463,"Out-New",'06-2026'!$I$7:$I$463,$C83,'06-2026'!$CE$7:$CE$463,$A83) -> 0 | G83: =COUNTIFS('06-2026'!$C$7:$C$463,$B83,'06-2026'!$A$7:$A$463,"Out-New",'06-2026'!$I$7:$I$463,$C83,'06-2026'!$CE$7:$CE$463,$A83) -> 0 | H83: =SUMIFS('06-2026'!$CB$7:$CB$463,'06-2026'!$C$7:$C$463,$B83,'06-2026'!$A$7:$A$463,"Termination",'06-2026'!$I$7:$I$463,$C83,'06-2026'!$CE$7:$CE$463,$A83) -> 0 | I83: =COUNTIFS('06-2026'!$C$7:$C$463,$B83,'06-2026'!$A$7:$A$463,"Termination",'06-2026'!$I$7:$I$463,$C83,'06-2026'!$CE$7:$CE$463,$A83) -> 0 | J83: =SUM(D83,F83,H83) -> 10806321 | K83: =SUM(E83,G83,I83) -> 1
A84: =A83 -> Nhân Kiệt | B84: =B83 -> PD | C84: VN1003 | D84: =SUMIFS('06-2026'!$CB$7:$CB$463,'06-2026'!$C$7:$C$463,$B84,'06-2026'!$A$7:$A$463,"Out",'06-2026'!$I$7:$I$463,$C84,'06-2026'!$CE$7:$CE$463,$A84) -> 96354580 | E84: =COUNTIFS('06-2026'!$C$7:$C$463,$B84,'06-2026'!$A$7:$A$463,"Out",'06-2026'!$I$7:$I$463,$C84,'06-2026'!$CE$7:$CE$463,$A84) -> 8 | F84: =SUMIFS('06-2026'!$CB$7:$CB$463,'06-2026'!$C$7:$C$463,$B84,'06-2026'!$A$7:$A$463,"Out-New",'06-2026'!$I$7:$I$463,$C84,'06-2026'!$CE$7:$CE$463,$A84) -> 0 | G84: =COUNTIFS('06-2026'!$C$7:$C$463,$B84,'06-2026'!$A$7:$A$463,"Out-New",'06-2026'!$I$7:$I$463,$C84,'06-2026'!$CE$7:$CE$463,$A84) -> 0 | H84: =SUMIFS('06-2026'!$CB$7:$CB$463,'06-2026'!$C$7:$C$463,$B84,'06-2026'!$A$7:$A$463,"Termination",'06-2026'!$I$7:$I$463,$C84,'06-2026'!$CE$7:$CE$463,$A84) -> 369280 | I84: =COUNTIFS('06-2026'!$C$7:$C$463,$B84,'06-2026'!$A$7:$A$463,"Termination",'06-2026'!$I$7:$I$463,$C84,'06-2026'!$CE$7:$CE$463,$A84) -> 2 | J84: =SUM(D84,F84,H84) -> 96723860 | K84: =SUM(E84,G84,I84) -> 10
A85: =A84 -> Nhân Kiệt | B85: =B84 -> PD | C85: VN1004 | D85: =SUMIFS('06-2026'!$CB$7:$CB$463,'06-2026'!$C$7:$C$463,$B85,'06-2026'!$A$7:$A$463,"Out",'06-2026'!$I$7:$I$463,$C85,'06-2026'!$CE$7:$CE$463,$A85) -> 9595484 | E85: =COUNTIFS('06-2026'!$C$7:$C$463,$B85,'06-2026'!$A$7:$A$463,"Out",'06-2026'!$I$7:$I$463,$C85,'06-2026'!$CE$7:$CE$463,$A85) -> 1 | F85: =SUMIFS('06-2026'!$CB$7:$CB$463,'06-2026'!$C$7:$C$463,$B85,'06-2026'!$A$7:$A$463,"Out-New",'06-2026'!$I$7:$I$463,$C85,'06-2026'!$CE$7:$CE$463,$A85) -> 0 | G85: =COUNTIFS('06-2026'!$C$7:$C$463,$B85,'06-2026'!$A$7:$A$463,"Out-New",'06-2026'!$I$7:$I$463,$C85,'06-2026'!$CE$7:$CE$463,$A85) -> 0 | H85: =SUMIFS('06-2026'!$CB$7:$CB$463,'06-2026'!$C$7:$C$463,$B85,'06-2026'!$A$7:$A$463,"Termination",'06-2026'!$I$7:$I$463,$C85,'06-2026'!$CE$7:$CE$463,$A85) -> 0 | I85: =COUNTIFS('06-2026'!$C$7:$C$463,$B85,'06-2026'!$A$7:$A$463,"Termination",'06-2026'!$I$7:$I$463,$C85,'06-2026'!$CE$7:$CE$463,$A85) -> 0 | J85: =SUM(D85,F85,H85) -> 9595484 | K85: =SUM(E85,G85,I85) -> 1
A86: =A85 -> Nhân Kiệt | B86: =B85 -> PD | C86: VN1005 | D86: =SUMIFS('06-2026'!$CB$7:$CB$463,'06-2026'!$C$7:$C$463,$B86,'06-2026'!$A$7:$A$463,"Out",'06-2026'!$I$7:$I$463,$C86,'06-2026'!$CE$7:$CE$463,$A86) -> 27465803 | E86: =COUNTIFS('06-2026'!$C$7:$C$463,$B86,'06-2026'!$A$7:$A$463,"Out",'06-2026'!$I$7:$I$463,$C86,'06-2026'!$CE$7:$CE$463,$A86) -> 2 | F86: =SUMIFS('06-2026'!$CB$7:$CB$463,'06-2026'!$C$7:$C$463,$B86,'06-2026'!$A$7:$A$463,"Out-New",'06-2026'!$I$7:$I$463,$C86,'06-2026'!$CE$7:$CE$463,$A86) -> 0 | G86: =COUNTIFS('06-2026'!$C$7:$C$463,$B86,'06-2026'!$A$7:$A$463,"Out-New",'06-2026'!$I$7:$I$463,$C86,'06-2026'!$CE$7:$CE$463,$A86) -> 0 | H86: =SUMIFS('06-2026'!$CB$7:$CB$463,'06-2026'!$C$7:$C$463,$B86,'06-2026'!$A$7:$A$463,"Termination",'06-2026'!$I$7:$I$463,$C86,'06-2026'!$CE$7:$CE$463,$A86) -> 5605115 | I86: =COUNTIFS('06-2026'!$C$7:$C$463,$B86,'06-2026'!$A$7:$A$463,"Termination",'06-2026'!$I$7:$I$463,$C86,'06-2026'!$CE$7:$CE$463,$A86) -> 1 | J86: =SUM(D86,F86,H86) -> 33070918 | K86: =SUM(E86,G86,I86) -> 3
A87: =A85 -> Nhân Kiệt | B87: =B85 -> PD | C87: VN1006 | D87: =SUMIFS('06-2026'!$CB$7:$CB$463,'06-2026'!$C$7:$C$463,$B87,'06-2026'!$A$7:$A$463,"Out",'06-2026'!$I$7:$I$463,$C87,'06-2026'!$CE$7:$CE$463,$A87) -> 205563475 | E87: =COUNTIFS('06-2026'!$C$7:$C$463,$B87,'06-2026'!$A$7:$A$463,"Out",'06-2026'!$I$7:$I$463,$C87,'06-2026'!$CE$7:$CE$463,$A87) -> 14 | F87: =SUMIFS('06-2026'!$CB$7:$CB$463,'06-2026'!$C$7:$C$463,$B87,'06-2026'!$A$7:$A$463,"Out-New",'06-2026'!$I$7:$I$463,$C87,'06-2026'!$CE$7:$CE$463,$A87) -> 0 | G87: =COUNTIFS('06-2026'!$C$7:$C$463,$B87,'06-2026'!$A$7:$A$463,"Out-New",'06-2026'!$I$7:$I$463,$C87,'06-2026'!$CE$7:$CE$463,$A87) -> 0 | H87: =SUMIFS('06-2026'!$CB$7:$CB$463,'06-2026'!$C$7:$C$463,$B87,'06-2026'!$A$7:$A$463,"Termination",'06-2026'!$I$7:$I$463,$C87,'06-2026'!$CE$7:$CE$463,$A87) -> 0 | I87: =COUNTIFS('06-2026'!$C$7:$C$463,$B87,'06-2026'!$A$7:$A$463,"Termination",'06-2026'!$I$7:$I$463,$C87,'06-2026'!$CE$7:$CE$463,$A87) -> 2 | J87: =SUM(D87,F87,H87) -> 205563475 | K87: =SUM(E87,G87,I87) -> 16
A88: =A86 -> Nhân Kiệt | B88: =B86 -> PD | C88: VN1007 | D88: =SUMIFS('06-2026'!$CB$7:$CB$463,'06-2026'!$C$7:$C$463,$B88,'06-2026'!$A$7:$A$463,"Out",'06-2026'!$I$7:$I$463,$C88,'06-2026'!$CE$7:$CE$463,$A88) -> 14110539 | E88: =COUNTIFS('06-2026'!$C$7:$C$463,$B88,'06-2026'!$A$7:$A$463,"Out",'06-2026'!$I$7:$I$463,$C88,'06-2026'!$CE$7:$CE$463,$A88) -> 1 | F88: =SUMIFS('06-2026'!$CB$7:$CB$463,'06-2026'!$C$7:$C$463,$B88,'06-2026'!$A$7:$A$463,"Out-New",'06-2026'!$I$7:$I$463,$C88,'06-2026'!$CE$7:$CE$463,$A88) -> 0 | G88: =COUNTIFS('06-2026'!$C$7:$C$463,$B88,'06-2026'!$A$7:$A$463,"Out-New",'06-2026'!$I$7:$I$463,$C88,'06-2026'!$CE$7:$CE$463,$A88) -> 0 | H88: =SUMIFS('06-2026'!$CB$7:$CB$463,'06-2026'!$C$7:$C$463,$B88,'06-2026'!$A$7:$A$463,"Termination",'06-2026'!$I$7:$I$463,$C88,'06-2026'!$CE$7:$CE$463,$A88) -> 0 | I88: =COUNTIFS('06-2026'!$C$7:$C$463,$B88,'06-2026'!$A$7:$A$463,"Termination",'06-2026'!$I$7:$I$463,$C88,'06-2026'!$CE$7:$CE$463,$A88) -> 0 | J88: =SUM(D88,F88,H88) -> 14110539 | K88: =SUM(E88,G88,I88) -> 1
A89: =A86 -> Nhân Kiệt | B89: =B86 -> PD | C89: VN1022 | D89: =SUMIFS('06-2026'!$CB$7:$CB$463,'06-2026'!$C$7:$C$463,$B89,'06-2026'!$A$7:$A$463,"Out",'06-2026'!$I$7:$I$463,$C89,'06-2026'!$CE$7:$CE$463,$A89) -> 0 | E89: =COUNTIFS('06-2026'!$C$7:$C$463,$B89,'06-2026'!$A$7:$A$463,"Out",'06-2026'!$I$7:$I$463,$C89,'06-2026'!$CE$7:$CE$463,$A89) -> 0 | F89: =SUMIFS('06-2026'!$CB$7:$CB$463,'06-2026'!$C$7:$C$463,$B89,'06-2026'!$A$7:$A$463,"Out-New",'06-2026'!$I$7:$I$463,$C89,'06-2026'!$CE$7:$CE$463,$A89) -> 0 | G89: =COUNTIFS('06-2026'!$C$7:$C$463,$B89,'06-2026'!$A$7:$A$463,"Out-New",'06-2026'!$I$7:$I$463,$C89,'06-2026'!$CE$7:$CE$463,$A89) -> 0 | H89: =SUMIFS('06-2026'!$CB$7:$CB$463,'06-2026'!$C$7:$C$463,$B89,'06-2026'!$A$7:$A$463,"Termination",'06-2026'!$I$7:$I$463,$C89,'06-2026'!$CE$7:$CE$463,$A89) -> 0 | I89: =COUNTIFS('06-2026'!$C$7:$C$463,$B89,'06-2026'!$A$7:$A$463,"Termination",'06-2026'!$I$7:$I$463,$C89,'06-2026'!$CE$7:$CE$463,$A89) -> 0 | J89: =SUM(D89,F89,H89) -> 0 | K89: =SUM(E89,G89,I89) -> 0
A90: =A87 -> Nhân Kiệt | B90: R&D | C90: VN3001 | D90: =SUMIFS('06-2026'!$CB$7:$CB$463,'06-2026'!$C$7:$C$463,$B90,'06-2026'!$A$7:$A$463,"Out",'06-2026'!$I$7:$I$463,$C90,'06-2026'!$CE$7:$CE$463,$A90) -> 35109430 | E90: =COUNTIFS('06-2026'!$C$7:$C$463,$B90,'06-2026'!$A$7:$A$463,"Out",'06-2026'!$I$7:$I$463,$C90,'06-2026'!$CE$7:$CE$463,$A90) -> 3 | F90: =SUMIFS('06-2026'!$CB$7:$CB$463,'06-2026'!$C$7:$C$463,$B90,'06-2026'!$A$7:$A$463,"Out-New",'06-2026'!$I$7:$I$463,$C90,'06-2026'!$CE$7:$CE$463,$A90) -> 0 | G90: =COUNTIFS('06-2026'!$C$7:$C$463,$B90,'06-2026'!$A$7:$A$463,"Out-New",'06-2026'!$I$7:$I$463,$C90,'06-2026'!$CE$7:$CE$463,$A90) -> 0 | H90: =SUMIFS('06-2026'!$CB$7:$CB$463,'06-2026'!$C$7:$C$463,$B90,'06-2026'!$A$7:$A$463,"Termination",'06-2026'!$I$7:$I$463,$C90,'06-2026'!$CE$7:$CE$463,$A90) -> 0 | I90: =COUNTIFS('06-2026'!$C$7:$C$463,$B90,'06-2026'!$A$7:$A$463,"Termination",'06-2026'!$I$7:$I$463,$C90,'06-2026'!$CE$7:$CE$463,$A90) -> 0 | J90: =SUM(D90,F90,H90) -> 35109430 | K90: =SUM(E90,G90,I90) -> 3
A91: =A89 -> Nhân Kiệt | B91: PD Total | D91: =SUM(D82:D90) -> 5.0836487e+08 | E91: =SUM(E82:E90) -> 38 | F91: =SUM(F82:F90) -> 0 | G91: =SUM(G82:G90) -> 0 | H91: =SUM(H82:H90) -> 27063437 | I91: =SUM(I82:I90) -> 8 | J91: =SUM(J82:J90) -> 5.354283e+08 | K91: =SUM(K82:K90) -> 46
A92: =A91 -> Nhân Kiệt | B92: QA | C92: VN3007 | D92: =SUMIFS('06-2026'!$CB$7:$CB$463,'06-2026'!$C$7:$C$463,$B92,'06-2026'!$A$7:$A$463,"Out",'06-2026'!$I$7:$I$463,$C92,'06-2026'!$CE$7:$CE$463,$A92) -> 0 | E92: =COUNTIFS('06-2026'!$C$7:$C$463,$B92,'06-2026'!$A$7:$A$463,"Out",'06-2026'!$I$7:$I$463,$C92,'06-2026'!$CE$7:$CE$463,$A92) -> 0 | F92: =SUMIFS('06-2026'!$CB$7:$CB$463,'06-2026'!$C$7:$C$463,$B92,'06-2026'!$A$7:$A$463,"Out-New",'06-2026'!$I$7:$I$463,$C92,'06-2026'!$CE$7:$CE$463,$A92) -> 0 | G92: =COUNTIFS('06-2026'!$C$7:$C$463,$B92,'06-2026'!$A$7:$A$463,"Out-New",'06-2026'!$I$7:$I$463,$C92,'06-2026'!$CE$7:$CE$463,$A92) -> 0 | H92: =SUMIFS('06-2026'!$CB$7:$CB$463,'06-2026'!$C$7:$C$463,$B92,'06-2026'!$A$7:$A$463,"Termination",'06-2026'!$I$7:$I$463,$C92,'06-2026'!$CE$7:$CE$463,$A92) -> 0 | I92: =COUNTIFS('06-2026'!$C$7:$C$463,$B92,'06-2026'!$A$7:$A$463,"Termination",'06-2026'!$I$7:$I$463,$C92,'06-2026'!$CE$7:$CE$463,$A92) -> 0 | J92: =SUM(D92,F92,H92) -> 0 | K92: =SUM(E92,G92,I92) -> 0
A93: =A92 -> Nhân Kiệt | B93: QA | C93: VN1022 | D93: =SUMIFS('06-2026'!$CB$7:$CB$463,'06-2026'!$C$7:$C$463,$B93,'06-2026'!$A$7:$A$463,"Out",'06-2026'!$I$7:$I$463,$C93,'06-2026'!$CE$7:$CE$463,$A93) -> 0 | E93: =COUNTIFS('06-2026'!$C$7:$C$463,$B93,'06-2026'!$A$7:$A$463,"Out",'06-2026'!$I$7:$I$463,$C93,'06-2026'!$CE$7:$CE$463,$A93) -> 0 | F93: =SUMIFS('06-2026'!$CB$7:$CB$463,'06-2026'!$C$7:$C$463,$B93,'06-2026'!$A$7:$A$463,"Out-New",'06-2026'!$I$7:$I$463,$C93,'06-2026'!$CE$7:$CE$463,$A93) -> 0 | G93: =COUNTIFS('06-2026'!$C$7:$C$463,$B93,'06-2026'!$A$7:$A$463,"Out-New",'06-2026'!$I$7:$I$463,$C93,'06-2026'!$CE$7:$CE$463,$A93) -> 0 | H93: =SUMIFS('06-2026'!$CB$7:$CB$463,'06-2026'!$C$7:$C$463,$B93,'06-2026'!$A$7:$A$463,"Termination",'06-2026'!$I$7:$I$463,$C93,'06-2026'!$CE$7:$CE$463,$A93) -> 0 | I93: =COUNTIFS('06-2026'!$C$7:$C$463,$B93,'06-2026'!$A$7:$A$463,"Termination",'06-2026'!$I$7:$I$463,$C93,'06-2026'!$CE$7:$CE$463,$A93) -> 0 | J93: =SUM(D93,F93,H93) -> 0 | K93: =SUM(E93,G93,I93) -> 0
A94: =A92 -> Nhân Kiệt | B94: QA | C94: VN1071 | D94: =SUMIFS('06-2026'!$CB$7:$CB$463,'06-2026'!$C$7:$C$463,$B94,'06-2026'!$A$7:$A$463,"Out",'06-2026'!$I$7:$I$463,$C94,'06-2026'!$CE$7:$CE$463,$A94) -> 25771615 | E94: =COUNTIFS('06-2026'!$C$7:$C$463,$B94,'06-2026'!$A$7:$A$463,"Out",'06-2026'!$I$7:$I$463,$C94,'06-2026'!$CE$7:$CE$463,$A94) -> 2 | F94: =SUMIFS('06-2026'!$CB$7:$CB$463,'06-2026'!$C$7:$C$463,$B94,'06-2026'!$A$7:$A$463,"Out-New",'06-2026'!$I$7:$I$463,$C94,'06-2026'!$CE$7:$CE$463,$A94) -> 0 | G94: =COUNTIFS('06-2026'!$C$7:$C$463,$B94,'06-2026'!$A$7:$A$463,"Out-New",'06-2026'!$I$7:$I$463,$C94,'06-2026'!$CE$7:$CE$463,$A94) -> 0 | H94: =SUMIFS('06-2026'!$CB$7:$CB$463,'06-2026'!$C$7:$C$463,$B94,'06-2026'!$A$7:$A$463,"Termination",'06-2026'!$I$7:$I$463,$C94,'06-2026'!$CE$7:$CE$463,$A94) -> 0 | I94: =COUNTIFS('06-2026'!$C$7:$C$463,$B94,'06-2026'!$A$7:$A$463,"Termination",'06-2026'!$I$7:$I$463,$C94,'06-2026'!$CE$7:$CE$463,$A94) -> 0 | J94: =SUM(D94,F94,H94) -> 25771615 | K94: =SUM(E94,G94,I94) -> 2
A95: =A93 -> Nhân Kiệt | B95: QA Total | D95: =SUM(D92:D94) -> 25771615 | E95: =SUM(E92:E94) -> 2 | F95: =SUM(F92:F94) -> 0 | G95: =SUM(G92:G94) -> 0 | H95: =SUM(H92:H94) -> 0 | I95: =SUM(I92:I94) -> 0 | J95: =SUM(J92:J94) -> 25771615 | K95: =SUM(K92:K94) -> 2
A96: Nhân Kiệt Total | D96: =SUM(D69,D74,D76,D79,D81,D91,D95) -> 5.6517464e+08 | E96: =SUM(E69,E74,E76,E79,E81,E91,E95) -> 42 | F96: =SUM(F69,F74,F76,F79,F81,F91,F95) -> 0 | G96: =SUM(G69,G74,G76,G79,G81,G91,G95) -> 0 | H96: =SUM(H69,H74,H76,H79,H81,H91,H95) -> 27063437 | I96: =SUM(I69,I74,I76,I79,I81,I91,I95) -> 8 | J96: =SUM(J69,J74,J76,J79,J81,J91,J95) -> 5.9223808e+08 | K96: =SUM(K69,K74,K76,K79,K81,K91,K95) -> 50
A97: Power Connect | B97: LG | C97: VN1005 | D97: =SUMIFS('06-2026'!$CB$7:$CB$463,'06-2026'!$C$7:$C$463,$B97,'06-2026'!$A$7:$A$463,"Out",'06-2026'!$I$7:$I$463,$C97,'06-2026'!$CE$7:$CE$463,$A97) -> 0 | E97: =COUNTIFS('06-2026'!$C$7:$C$463,$B97,'06-2026'!$A$7:$A$463,"Out",'06-2026'!$I$7:$I$463,$C97,'06-2026'!$CE$7:$CE$463,$A97) -> 0 | F97: =SUMIFS('06-2026'!$CB$7:$CB$463,'06-2026'!$C$7:$C$463,$B97,'06-2026'!$A$7:$A$463,"Out-New",'06-2026'!$I$7:$I$463,$C97,'06-2026'!$CE$7:$CE$463,$A97) -> 0 | G97: =COUNTIFS('06-2026'!$C$7:$C$463,$B97,'06-2026'!$A$7:$A$463,"Out-New",'06-2026'!$I$7:$I$463,$C97,'06-2026'!$CE$7:$CE$463,$A97) -> 0 | H97: =SUMIFS('06-2026'!$CB$7:$CB$463,'06-2026'!$C$7:$C$463,$B97,'06-2026'!$A$7:$A$463,"Termination",'06-2026'!$I$7:$I$463,$C97,'06-2026'!$CE$7:$CE$463,$A97) -> 0 | I97: =COUNTIFS('06-2026'!$C$7:$C$463,$B97,'06-2026'!$A$7:$A$463,"Termination",'06-2026'!$I$7:$I$463,$C97,'06-2026'!$CE$7:$CE$463,$A97) -> 0 | J97: =SUM(D97,F97,H97) -> 0 | K97: =SUM(E97,G97,I97) -> 0
A98: =A97 -> Power Connect | B98: =B97 -> LG | C98: VN1033 | D98: =SUMIFS('06-2026'!$CB$7:$CB$463,'06-2026'!$C$7:$C$463,$B98,'06-2026'!$A$7:$A$463,"Out",'06-2026'!$I$7:$I$463,$C98,'06-2026'!$CE$7:$CE$463,$A98) -> 0 | E98: =COUNTIFS('06-2026'!$C$7:$C$463,$B98,'06-2026'!$A$7:$A$463,"Out",'06-2026'!$I$7:$I$463,$C98,'06-2026'!$CE$7:$CE$463,$A98) -> 0 | F98: =SUMIFS('06-2026'!$CB$7:$CB$463,'06-2026'!$C$7:$C$463,$B98,'06-2026'!$A$7:$A$463,"Out-New",'06-2026'!$I$7:$I$463,$C98,'06-2026'!$CE$7:$CE$463,$A98) -> 0 | G98: =COUNTIFS('06-2026'!$C$7:$C$463,$B98,'06-2026'!$A$7:$A$463,"Out-New",'06-2026'!$I$7:$I$463,$C98,'06-2026'!$CE$7:$CE$463,$A98) -> 0 | H98: =SUMIFS('06-2026'!$CB$7:$CB$463,'06-2026'!$C$7:$C$463,$B98,'06-2026'!$A$7:$A$463,"Termination",'06-2026'!$I$7:$I$463,$C98,'06-2026'!$CE$7:$CE$463,$A98) -> 0 | I98: =COUNTIFS('06-2026'!$C$7:$C$463,$B98,'06-2026'!$A$7:$A$463,"Termination",'06-2026'!$I$7:$I$463,$C98,'06-2026'!$CE$7:$CE$463,$A98) -> 0 | J98: =SUM(D98,F98,H98) -> 0 | K98: =SUM(E98,G98,I98) -> 0
A99: =A98 -> Power Connect | B99: =B98 -> LG | C99: VN1042 | D99: =SUMIFS('06-2026'!$CB$7:$CB$463,'06-2026'!$C$7:$C$463,$B99,'06-2026'!$A$7:$A$463,"Out",'06-2026'!$I$7:$I$463,$C99,'06-2026'!$CE$7:$CE$463,$A99) -> 66967689 | E99: =COUNTIFS('06-2026'!$C$7:$C$463,$B99,'06-2026'!$A$7:$A$463,"Out",'06-2026'!$I$7:$I$463,$C99,'06-2026'!$CE$7:$CE$463,$A99) -> 5 | F99: =SUMIFS('06-2026'!$CB$7:$CB$463,'06-2026'!$C$7:$C$463,$B99,'06-2026'!$A$7:$A$463,"Out-New",'06-2026'!$I$7:$I$463,$C99,'06-2026'!$CE$7:$CE$463,$A99) -> 0 | G99: =COUNTIFS('06-2026'!$C$7:$C$463,$B99,'06-2026'!$A$7:$A$463,"Out-New",'06-2026'!$I$7:$I$463,$C99,'06-2026'!$CE$7:$CE$463,$A99) -> 0 | H99: =SUMIFS('06-2026'!$CB$7:$CB$463,'06-2026'!$C$7:$C$463,$B99,'06-2026'!$A$7:$A$463,"Termination",'06-2026'!$I$7:$I$463,$C99,'06-2026'!$CE$7:$CE$463,$A99) -> 3997011 | I99: =COUNTIFS('06-2026'!$C$7:$C$463,$B99,'06-2026'!$A$7:$A$463,"Termination",'06-2026'!$I$7:$I$463,$C99,'06-2026'!$CE$7:$CE$463,$A99) -> 2 | J99: =SUM(D99,F99,H99) -> 70964700 | K99: =SUM(E99,G99,I99) -> 7
A100: =A99 -> Power Connect | B100: LG Total | D100: =SUM(D97:D99) -> 66967689 | E100: =SUM(E97:E99) -> 5 | F100: =SUM(F97:F99) -> 0 | G100: =SUM(G97:G99) -> 0 | H100: =SUM(H97:H99) -> 3997011 | I100: =SUM(I97:I99) -> 2 | J100: =SUM(J97:J99) -> 70964700 | K100: =SUM(K97:K99) -> 7
...

Sheet 06-2026
D1: 1 | E1: 2 | F1: 3 | G1: 4 | H1: 5 | I1: 6 | J1: 7 | K1: 8 | L1: 9 | M1: 10 | N1: 11 | O1: 12 | P1: 13 | Q1: 14 | R1: 15 | S1: 16 | T1: 17 | U1: 18 | V1: 19 | W1: 20 | X1: 21 | Y1: 22 | Z1: 23 | AA1: 24 | AB1: 25 | AC1: 26 | AD1: 27 | AE1: 28 | AF1: 29 | AG1: 30 | AH1: 31 | AI1: 32 | AJ1: 33 | AK1: 34 | AL1: 35 | AM1: 36 | AN1: 37 | AO1: 38 | AP1: 39 | AQ1: 40 | AR1: 41 | AS1: 42 | AT1: 43 | AU1: 44 | AV1: 45 | AW1: 46 | AX1: 47 | AY1: 48 | AZ1: 49 | BA1: 50 | BB1: 51 | BC1: 52 | BD1: 53 | BE1: 54 | BF1: 55 | BG1: 56 | BH1: 57 | BI1: 58 | BJ1: 59 | BK1: 60 | BL1: 61 | BM1: 62 | BN1: 63 | BO1: 64 | BP1: 65 | BQ1: 66 | BR1: 67 | BS1: 68 | BT1: 69 | BU1: 70 | BV1: 71 | BW1: 72 | BX1: 73 | BY1: 74 | BZ1: 75 | CA1: 76 | CB1: 77 | CC1: 78 | CD1: 79 | CE1: 80 | DF1: Phí/ngày | DG1: 1200 | DN1: LCB/208*10%*số ngày làm ca 2*8 | DO1: LCB/208*30%*số ngày làm ca 3*8 | DQ1: LCB/208*30%*số ngày làm ca 3*8
B2: DATALOGIC VIETNAM LLC. | Y2: Số ngày làm đêm 12h | AL2: Phụ cấp 30% - Số ngày làm đêm 12h (từ 22:00 - 6:00) | AQ2: 50k/tuần, nếu làm đủ | BL2: Nghỉ việc báo không đúng số ngày quy định/tự ý bỏ việc, chưa trả thẻ, chìa khóa, giày bảo hộ | BT2: 0.215 | BU2: 0.105 | BY2: Datalogic: trả 100%, NCC: trả: 0% | DF2: Số ngày | DG2: Ngày trả công + làm ngày OFF | DN2: 0.1 | DO2: 0.3 | DQ2: 0.3
I3: x | P3: 1 | Q3: 2 | R3: 3 | S3: 4 | T3: 5 | U3: 6 | V3: 7 | Z3: Số ngày làm việc ngày OFF | AU3: 15,000 | AV3: 15,000 | AW3: 27,000 | BG3: Ca 1, ca 2: 15.000, ca 3: 27.000 | BJ3: =4680000*1.07 -> 5007600 | BN3: Số ngày làm việc x 1200 | BO3: Số ngày nghỉ có đi làm x 1200 | BQ3: Số giờ OT x 286000/208 | BS3: Bù lương 12h training nhân viên mới | CA3: Datalogic: trả 100%, NCC: trả: 0% | CO3: =5550000/208*12 -> 320192.31 | CQ3: Cột P | CR3: Cột Q | CS3: Cột R | CT3: Cột S | CU3: Cột T | CV3: Cột U | CW3: Cột V | CX3: Cột W | CY3: Cột X | DR3: cột ngày đã tính theo giờ tính phụ cấp/8 | EE3: 1
P6: 1.5 | Q6: 1.75 | R6: 2 | S6: 2.1 | T6: 2.2 | U6: 2.9 | V6: 3 | W6: 4.1 | X6: 1 | Z6: Tính phí ESD | AB6: =LCB/208x8 | AC6: 1.5 | AD6: 1.75 | AE6: 2 | AF6: 2.1 | AG6: 2.2 | AH6: 2.9 | AI6: 3 | AJ6: 4.1 | AK6: 1 | AL6: 0.3 | AM6: 300000 | AN6: 150000 | AW6: 10% x LCB ngày | AY6: 50% x LCB ngày | BA6: 50% x 4h (từ 22:00 - 2:00 am) | BC6: x 100% | BD6: Só ngày làm Thứ bảy + ngày nghỉ (Chủ nhật) * 30k/ngày | BH6: Bữa ăn chính + OT các ngày OT | BJ6: Theo lương tối thiểu vùng + 7% (5.007.600đ/tháng) | BM6: 10000 | BN6: 1200 | BP6: 286000 | BW6: Datalogic trả 100% | CQ6: Cột AC | CR6: Cột AD | CS6: Cột AE | CT6: Cột AF | CU6: Cột AG | CV6: Cột AH | CW6: Cột AI | CX6: Cột AJ | CY6: Cột AK | CZ6: Cột BP, BQ | DC6: Cột AT | DD6: Cột AU | DE6: Cột Z | DF6: Cột BN, BO | DK6: Cột BG | DL6: Cột BH | DM6: Cột AV | DN6: Cột AW | DO6: Cột AX | DP6: Cột AY | DQ6: Cột AZ | DR6: Cột BA | DS6: Cột O | DT6: Cột P | DU6: Cột Q | DV6: Cột R | DW6: Cột S | DX6: Cột T | DY6: Cột U | DZ6: Cột V | EA6: Cột W | EB6: Cột X | EC6: Cột BD | ED6: Cột BB | EE6: Cột BC | EF6: Cột BE
A7: Note | B7: Count | C7: DepartmentCode | D7: EmployeeID | E7: Global code | F7: FullName | G7: Giới tính | H7: Trình độ | I7: CostCenter | J7: Working hour | K7: Lương cơ bản | L7: Số ngày công chuẩn | M7: Số giờ công chuẩn | N7: Số ngày làm việc được trả lương | O7: Số giờ làm việc được trả lương | P7: Overtime 150% (hour) | Q7: Overtime 175% (hour) | R7: Overtime 200% (hour) | S7: Overtime 210% (hour) | T7: Overtime 220% (hour) | U7: Overtime 290% (hour) | V7: Overtime 300% (hour) | W7: Overtime 410% (hour) | X7: Overtime 100% (hour) | Y7: Night shift (day) | Z7: Day Off | AA7: Số giờ làm thêm T.O | AB7: Lương tháng 06-2026 | AC7: Overtime 150% (vnd) | AD7: Overtime 175% (vnd) | AE7: Overtime 200% (vnd) | AF7: Overtime 210% (vnd) | AG7: Overtime 220% (vnd) | AH7: Overtime 290% (vnd) | AI7: Overtime 300% (vnd) | AJ7: Overtime 410% (vnd) | AK7: Overtime 100% (vnd) | AL7: Night allowance (vnd) | AM7: Phụ cấp đi lại | AN7: Phụ cấp nhà ở | AO7: Thưởng hiệu suất | AP7: NVXS&TB tháng | AQ7: Thưởng TRP | AR7: Thưởng quý 2-2026 | AS7: Lương tháng 13 | AT7: Thưởng ca ngày (12h) | AU7: Thưởng ca đêm (12h) | AV7: Ca 2 | AW7: P/c ca 2 | AX7: Ca 3 | AY7: P/c ca 3 | AZ7: Ca Lỡ | BA7: P/c ca Lỡ | BB7: Giờ thưởng OT | BC7: Tiền thưởng OT | BD7: Sat/Sun transportation | BE7: Phụ cấp phụ nữ (1.5 giờ/ tháng) | BF7: Phụ cấp bằng cấp | BG7: P/c bữa ăn ca chính 06-2026 | BH7: P/c bữa ăn OT 06-2026 | BI7: Số giờ nghỉ không việc | BJ7: Lương nghỉ không việc | BK7: Lương làm thêm TO | BL7: Phụ cấp khác | BM7: Phí dịch vụ thời gian TO | BN7: ESD | BO7: ESD OT | BP7: Phí dịch vụ | BQ7: Phí dịch vụ OT | BR7: Bù-trừ ESD | BS7: Bù-trừ (06-2026) | BT7: BHXH, BHYT, BHTN&BNN (NSDLĐ) | BU7: BHXH, BHYT, BHTN&BNN (NLĐ) | BV7: Ma chay cưới hỏi (giờ) | BW7: Ma chay cưới hỏi | BX7: Phép năm nhân viên đã sử dụng (giờ) | BY7: Phép năm nhân viên đã sử dụng | BZ7: Phép năm còn lại (giờ) | CA7: Phép năm còn lại | CB7: Tổng chi phí phải trả cho NCC | CC7: Nhân viên thực lãnh | CD7: Notes | CE7: Agency | CF7: Joining date | CG7: Termination date | CH7: Termination | CI7: Phí công đoàn 2% | CJ7: Bù trừ trả cho NCC | CK7: Notes_Bù trừ trả cho NCC | CL7: Tổng chi phí dịch vụ Nhà cung cấp | CM7: Tổng chi phí phải trả cho NCC | CN7: Nhân viên thực lãnh | CO7: Lương tháng | CQ7: OT 150% | CR7: OT 175% | CS7: OT 200% | CT7: OT 210% | CU7: OT 220% | CV7: Overtime 290% (hour) | CW7: Overtime 300% (hour) | CX7: Overtime 410% (hour) | CY7: Overtime 100% (hour) | CZ7: Tổng Phí dịch vụ | DA7: Check- Phí dịch vụ | DB7: sds | DC7: Thưởng ca ngày | DD7: Thưởng ca đêm | DE7: Check Day Off | DF7: Tổng tiền ESD | DG7: Check tiền ESD | DH7: Night Allowance | DI7: Note | DJ7: Số giờ phép còn lại 2022 | DK7: Phụ cấp bữa ăn chính | DL7: Phụ cấp bữa ăn OT | DM7: Số ngày làm ca 2 | DN7: P/c ca 2 | DO7: Số ngày làm ca 3 | DP7: P/c ca 3 | DQ7: Số ngày làm ca Lỡ (L3) | DR7: P/c ca Lỡ (L3) | DS7: Số giờ công phải trả | DT7: OT 150% | DU7: OT 175% | DV7: OT 200% | DW7: OT 210% | DX7: OT 220% | DY7: OT 290% | DZ7: OT 300% | EA7: OT 410% | EB7: OT 100% | EC7: Check PC đi làm ngày nghỉ/Sat-Sun | ED7: Số giờ thưởng đi làm ngày nghỉ | EE7: Số tiền thưởng đi làm ngày nghỉ | EF7: Phụ nữ 1.5h/tháng | EG7: Lương nghỉ không việc | EH7: Check PC đi lại | EI7: Check PC nhà ở | EJ7: Số ngày hưởng PC/Công chuẩn thực tế | EK7: Check PC nữ
A8: Out | B8: =ROW()-7 -> 1 | C8: LG | D8: 22004496 | E8: 93403958 | F8: TRẦN ANH TIẾN | G8: M | H8: THPT | I8: VN1042 | J8: 40 | K8: 6000000 | M8: 176 | O8: 176 | P8: 3.5 | Q8: 0 | R8: 0 | S8: 0 | T8: 0 | U8: 0 | V8: 0 | W8: 0 | X8: 0 | Y8: 0 | AB8: 6000000 | AC8: 178977.27 | AD8: 0 | AE8: 0 | AF8: 0 | AG8: 0 | AH8: 0 | AI8: 0 | AJ8: 0 | AK8: 0 | AM8: 300000 | AN8: 150000 | AO8: 0 | AP8: 0 | AQ8: 1227272.7 | AR8: 500000 | BD8: 0 | BF8: 100000 | BG8: 150000 | BH8: 20000 | BL8: 0 | BN8: 0 | BO8: 0 | BP8: 420000 | BQ8: 8352.2727 | BS8: 0 | BT8: 1290000 | BU8: 630000 | BW8: 0 | BX8: 8 | BY8: 230769.23 | CB8: 10344602 | CC8: 7996250 | CE8: ANNK-HR | CF8: 44624 | CH8: O | CI8: 0 | CJ8: 0 | CL8: =SUM(BN8:BQ8)+CJ8 -> 428352.27 | CM8: =SUM(AB8:AU8,AW8,AY8,BA8,BC8,BD8:BH8,BJ8:BL8,BM8:BR8,BS8,BT8)+100%*CA8-CB8+CJ8+CI8 -> 0.2727 | CN8: =SUM(AB8:AU8,AW8,AY8,BA8,BC8,BD8:BH8,BJ8,BL8)+BS8-BU8+CA8-CC8 -> 0 | CO8: =K8/M8*O8-AB8 -> 0 | CQ8: =$K8/$M8*P8*1.5-AC8 -> 2.7272705e-05 | CR8: =$K8/$M8*Q8*1.75-AD8 -> 0 | CS8: =$K8/$M8*R8*2-AE8 -> 0 | CT8: =$K8/$M8*S8*2.1-AF8 -> 0 | CU8: =$K8/$M8*T8*2.2-AG8 -> 0 | CV8: =$K8/$M8*U8*2.9-AH8 -> 0 | CW8: =$K8/$M8*V8*3-AI8 -> 0 | CX8: =$K8/$M8*W8*4.1-AJ8 -> 0 | CY8: =$K8/$M8*X8*1-AK8 -> 0 | CZ8: =(BP8+BQ8) -> 428352.27 | DA8: =(420000/176)*(O8+P8+Q8+R8+S8+T8+U8+V8+W8+X8+BI8)-CZ8 -> 2.7272792e-05 | DC8: =K8/M8*IFERROR(VLOOKUP($D8,Shift!$B:$AZ,45,0),0)-AT8 -> 0 | DD8: =K8/M8*IFERROR(VLOOKUP($D8,Shift!$B:$AV,47,0),0)*10*50%-ROUND(K8/M8*IFERROR(VLOOKUP($D8,Shift!$B:$AV,47,0),0)*8*30%,0)-AU8 -> 0 | DE8: =VLOOKUP($D8,'Off day working'!A:AM,38,0)-Z8 -> #N/A | DH8: =K8/208*8*30%*VLOOKUP($D8,Shift!$B:$AZ,47,0)-AL8 -> 0 | DK8: =VLOOKUP($D8,Meal!$A:$AK,35,0)-BG8 -> 0 | DL8: =VLOOKUP($D8,Meal!$A:$AK,36,0)-BH8 -> 0 | DM8: =VLOOKUP($D8,Shift!B:AW,39,0)-AV8 -> 0 | DN8: =K8/208*VLOOKUP(D8,Shift!$B:$AO,39,0)*8*10%-AW8 -> 0 | DO8: =VLOOKUP($D8,Shift!$B:$AO,40,0)-AX8 -> 0 | DP8: =K8/208*VLOOKUP(D8,Shift!$B:$AO,40,0)*8*50%-AY8 -> 0 | DQ8: =VLOOKUP($D8,Shift!$B:$AZ,41,0)-AZ8 -> 0 | DR8: =K8/208*VLOOKUP($D8,Shift!$B:$AQ,41,0)*8*50%-BA8 -> 0 | DS8: =VLOOKUP($D8,Att!B:CU,98,0)-O8 -> 0 | DT8: =IFERROR(VLOOKUP($D8,OT!$A:$BR,OT!BC$1,0),0)-P8 -> 0 | DU8: =IFERROR(VLOOKUP($D8,OT!$A:$BR,OT!BD$1,0),0)-Q8 -> 0 | DV8: =IFERROR(VLOOKUP($D8,OT!$A:$BR,OT!BE$1,0),0)-R8 -> 0 | DW8: =IFERROR(VLOOKUP($D8,OT!$A:$BR,OT!BF$1,0),0)-S8 -> 0 | DX8: =IFERROR(VLOOKUP($D8,OT!$A:$BR,OT!BG$1,0),0)-T8 -> 0 | DY8: =IFERROR(VLOOKUP($D8,OT!$A:$BR,OT!BH$1,0),0)-U8 -> 0 | DZ8: =IFERROR(VLOOKUP($D8,OT!$A:$BR,OT!BI$1,0),0)-V8 -> 0 | EA8: =IFERROR(VLOOKUP($D8,OT!$A:$BR,OT!BJ$1,0),0)-W8 -> 0 | EB8: =IFERROR(VLOOKUP($D8,OT!$A:$BR,OT!BK$1,0),0)-X8 -> 0 | EC8: =VLOOKUP(D8,'Off day working'!A:AL,38,0)*30000-BD8 -> #N/A | EF8: =IF(G8="M",0-BE8,IF(G8="F",K8/208*1.5-BE8)) -> 0 | EG8: =4960000*1.07/208*VLOOKUP(D8,Att!B:BZ,77,0)-BJ8 -> 0 | EI8: =IF(AND(CH8="X",EJ8>=0.5),150000/VLOOKUP(D8,Att!B:AT,45,0)*VLOOKUP(D8,Att!B:AP,41,0),IF(AND(CH8="X",EJ8<0.5),0,150000))-AN8 -> 0 | EJ8: =VLOOKUP(D8,Att!B:AP,41,0)/VLOOKUP(D8,Att!B:AT,45,0) -> 0.95454545
A9: Out | B9: =ROW()-7 -> 2 | C9: PD | D9: 24004676 | E9: 93404137 | F9: NGUYỄN NGỌC KHÁNH LINH | G9: F | H9: THPT | I9: VN1001 | J9: 48-12 | K9: 5900000 | M9: 208 | O9: 208 | P9: 43.5 | Q9: 0 | R9: 0 | S9: 0 | T9: 0 | U9: 0 | V9: 0 | W9: 0 | X9: 0 | Y9: 18 | AB9: 5899999.9 | AC9: 1850841.3 | AD9: 0 | AE9: 0 | AF9: 0 | AG9: 0 | AH9: 0 | AI9: 0 | AJ9: 0 | AK9: 0 | AL9: 1021153.8 | AM9: 300000 | AN9: 150000 | AO9: 505000 | AP9: 120000 | AQ9: 1021153.8 | AR9: 500000 | AT9: 0 | AU9: 1106250 | AV9: 0 | AW9: 0 | AX9: 3 | AY9: 340384.62 | BB9: 20 | BC9: 567307.69 | BD9: 0 | BE9: 42548 | BF9: 100000 | BH9: 776000 | BL9: 0 | BN9: 0 | BO9: 0 | BP9: 420000 | BQ9: 87836.538 | BS9: 0 | BT9: 1268500 | BU9: 619500 | BW9: 0 | BX9: 18 | BY9: 510576.92 | CB9: 92556999 | CC9: 13681162 | CE9: MEKONG SUBLABOR | CF9: 45344 | CH9: O | CI9: 118000 | CJ9: 76362000 | CK9: PHÍ CHUYỂN ĐỔI LAO ĐỘNG 76,362,000 VND | CL9: =SUM(BN9:BQ9)+CJ9 -> 76869837 | CM9: =SUM(AB9:AU9,AW9,AY9,BA9,BC9,BD9:BH9,BJ9:BL9,BM9:BR9,BS9,BT9)+100%*CA9-CB9+CJ9+CI9 -> -23.231 | CN9: =SUM(AB9:AU9,AW9,AY9,BA9,BC9,BD9:BH9,BJ9,BL9)+BS9-BU9+CA9-CC9 -> -22.7695 | CO9: =K9/M9*O9-AB9 -> 0.1135 | CQ9: =$K9/$M9*P9*1.5-AC9 -> -4.6154018e-05 | CR9: =$K9/$M9*Q9*1.75-AD9 -> 0 | CS9: =$K9/$M9*R9*2-AE9 -> 0 | CT9: =$K9/$M9*S9*2.1-AF9 -> 0 | CU9: =$K9/$M9*T9*2.2-AG9 -> 0 | CV9: =$K9/$M9*U9*2.9-AH9 -> 0 | CW9: =$K9/$M9*V9*3-AI9 -> 0 | CX9: =$K9/$M9*W9*4.1-AJ9 -> 0 | CY9: =$K9/$M9*X9*1-AK9 -> 0 | CZ9: =(BP9+BQ9) -> 507836.54 | DA9: =(420000/208)*(O9+P9+Q9+R9+S9+T9+U9+V9+W9+X9+BI9)-CZ9 -> -3.8461527e-05 | DC9: =K9/M9*IFERROR(VLOOKUP($D9,Shift!$B:$AZ,45,0),0)-AT9 -> 0 | DD9: =K9/M9*IFERROR(VLOOKUP($D9,Shift!$B:$AV,47,0),0)*10*50%-ROUND(K9/M9*IFERROR(VLOOKUP($D9,Shift!$B:$AV,47,0),0)*8*30%,0)-AU9 -> -0.15384615 | DE9: =VLOOKUP($D9,'Off day working'!A:AM,38,0)-Z9 -> 0 | DH9: =K9/208*8*30%*VLOOKUP($D9,Shift!$B:$AZ,47,0)-AL9 -> -4.6153902e-05 | DK9: =VLOOKUP($D9,Meal!$A:$AK,35,0)-BG9 -> 0 | DL9: =VLOOKUP($D9,Meal!$A:$AK,36,0)-BH9 -> 0 | DM9: =VLOOKUP($D9,Shift!B:AW,39,0)-AV9 -> 0 | DN9: =K9/208*VLOOKUP(D9,Shift!$B:$AO,39,0)*8*10%-AW9 -> 0 | DO9: =VLOOKUP($D9,Shift!$B:$AO,40,0)-AX9 -> 0 | DP9: =K9/208*VLOOKUP(D9,Shift!$B:$AO,40,0)*8*50%-AY9 -> -1.5384634e-05 | DQ9: =VLOOKUP($D9,Shift!$B:$AZ,41,0)-AZ9 -> 0 | DR9: =K9/208*VLOOKUP($D9,Shift!$B:$AQ,41,0)*8*50%-BA9 -> 0 | DS9: =VLOOKUP($D9,Att!B:CU,98,0)-O9 -> 0 | DT9: =IFERROR(VLOOKUP($D9,OT!$A:$BR,OT!BC$1,0),0)-P9 -> 0 | DU9: =IFERROR(VLOOKUP($D9,OT!$A:$BR,OT!BD$1,0),0)-Q9 -> 0 | DV9: =IFERROR(VLOOKUP($D9,OT!$A:$BR,OT!BE$1,0),0)-R9 -> 0 | DW9: =IFERROR(VLOOKUP($D9,OT!$A:$BR,OT!BF$1,0),0)-S9 -> 0 | DX9: =IFERROR(VLOOKUP($D9,OT!$A:$BR,OT!BG$1,0),0)-T9 -> 0 | DY9: =IFERROR(VLOOKUP($D9,OT!$A:$BR,OT!BH$1,0),0)-U9 -> 0 | DZ9: =IFERROR(VLOOKUP($D9,OT!$A:$BR,OT!BI$1,0),0)-V9 -> 0 | EA9: =IFERROR(VLOOKUP($D9,OT!$A:$BR,OT!BJ$1,0),0)-W9 -> 0 | EB9: =IFERROR(VLOOKUP($D9,OT!$A:$BR,OT!BK$1,0),0)-X9 -> 0 | EC9: =VLOOKUP(D9,'Off day working'!A:AL,38,0)*30000-BD9 -> 0 | EF9: =IF(G9="M",0-BE9,IF(G9="F",K9/208*1.5-BE9)) -> 0.076923077 | EG9: =4960000*1.07/208*VLOOKUP(D9,Att!B:BZ,77,0)-BJ9 -> 0 | EI9: =IF(AND(CH9="X",EJ9>=0.5),150000/VLOOKUP(D9,Att!B:AT,45,0)*VLOOKUP(D9,Att!B:AP,41,0),IF(AND(CH9="X",EJ9<0.5),0,150000))-AN9 -> 0 | EJ9: =VLOOKUP(D9,Att!B:AP,41,0)/VLOOKUP(D9,Att!B:AT,45,0) -> 1.0458696
A10: Out | B10: =ROW()-7 -> 3 | C10: PD | D10: 24004687 | E10: 93404148 | F10: TIÊU MỸ DUNG | G10: F | H10: Đại học | I10: VN1001 | J10: 48-12 | K10: 5900000 | M10: 208 | O10: 200 | P10: 48 | Q10: 0 | R10: 16 | S10: 0 | T10: 0 | U10: 8 | V10: 0 | W10: 0 | X10: 0 | Y10: 11 | Z10: 2 | AB10: 5673076.7 | AC10: 2042307.7 | AD10: 0 | AE10: 907692.31 | AF10: 0 | AG10: 0 | AH10: 658076.92 | AI10: 0 | AJ10: 0 | AK10: 0 | AL10: 612692.31 | AM10: 300000 | AN10: 150000 | AO10: 730000 | AP10: 0 | AQ10: 765865.38 | AR10: 500000 | AT10: 0 | AU10: 663750 | AV10: 0 | AW10: 0 | AX10: 2 | AY10: 226923.08 | BB10: 24 | BC10: 680769.23 | BD10: 60000 | BE10: 42548 | BF10: 200000 | BH10: 704000 | BL10: 0 | BN10: 0 | BO10: 0 | BP10: 403846.15 | BQ10: 145384.62 | BS10: 0 | BT10: 1268500 | BU10: 619500 | BW10: 0 | BY10: 0 | CB10: 16853458 | CC10: 14298228 | CE10: MEKONG SUBLABOR | CF10: 45344 | CH10: O | CI10: 118000 | CJ10: 0 | CL10: =SUM(BN10:BQ10)+CJ10 -> 549230.77 | CM10: =SUM(AB10:AU10,AW10,AY10,BA10,BC10,BD10:BH10,BJ10:BL10,BM10:BR10,BS10,BT10)+100%*CA10-CB10+CJ10+CI10 -> -25.6123 | CN10: =SUM(AB10:AU10,AW10,AY10,BA10,BC10,BD10:BH10,BJ10,BL10)+BS10-BU10+CA10-CC10 -> -26.3815 | CO10: =K10/M10*O10-AB10 -> 0.22687692 | CQ10: =$K10/$M10*P10*1.5-AC10 -> 7.6922588e-06 | CR10: =$K10/$M10*Q10*1.75-AD10 -> 0 | CS10: =$K10/$M10*R10*2-AE10 -> -7.6922588e-06 | CT10: =$K10/$M10*S10*2.1-AF10 -> 0 | CU10: =$K10/$M10*T10*2.2-AG10 -> 0 | CV10: =$K10/$M10*U10*2.9-AH10 -> -2.3076893e-05 | CW10: =$K10/$M10*V10*3-AI10 -> 0 | CX10: =$K10/$M10*W10*4.1-AJ10 -> 0 | CY10: =$K10/$M10*X10*1-AK10 -> 0 | CZ10: =(BP10+BQ10) -> 549230.77 | DA10: =(420000/208)*(O10+P10+Q10+R10+S10+T10+U10+V10+W10+X10+BI10)-CZ10 -> 3.0769268e-05 | DC10: =K10/M10*IFERROR(VLOOKUP($D10,Shift!$B:$AZ,45,0),0)-AT10 -> 0 | DD10: =K10/M10*IFERROR(VLOOKUP($D10,Shift!$B:$AV,47,0),0)*10*50%-ROUND(K10/M10*IFERROR(VLOOKUP($D10,Shift!$B:$AV,47,0),0)*8*30%,0)-AU10 -> 0.30769231 | DE10: =VLOOKUP($D10,'Off day working'!A:AM,38,0)-Z10 -> 0 | DH10: =K10/208*8*30%*VLOOKUP($D10,Shift!$B:$AZ,47,0)-AL10 -> -7.6922588e-06 | DK10: =VLOOKUP($D10,Meal!$A:$AK,35,0)-BG10 -> 0 | DL10: =VLOOKUP($D10,Meal!$A:$AK,36,0)-BH10 -> 0 | DM10: =VLOOKUP($D10,Shift!B:AW,39,0)-AV10 -> 0 | DN10: =K10/208*VLOOKUP(D10,Shift!$B:$AO,39,0)*8*10%-AW10 -> 0 | DO10: =VLOOKUP($D10,Shift!$B:$AO,40,0)-AX10 -> 0 | DP10: =K10/208*VLOOKUP(D10,Shift!$B:$AO,40,0)*8*50%-AY10 -> 2.3076951e-05 | DQ10: =VLOOKUP($D10,Shift!$B:$AZ,41,0)-AZ10 -> 0 | DR10: =K10/208*VLOOKUP($D10,Shift!$B:$AQ,41,0)*8*50%-BA10 -> 0 | DS10: =VLOOKUP($D10,Att!B:CU,98,0)-O10 -> 0 | DT10: =IFERROR(VLOOKUP($D10,OT!$A:$BR,OT!BC$1,0),0)-P10 -> 0 | DU10: =IFERROR(VLOOKUP($D10,OT!$A:$BR,OT!BD$1,0),0)-Q10 -> 0 | DV10: =IFERROR(VLOOKUP($D10,OT!$A:$BR,OT!BE$1,0),0)-R10 -> 0 | DW10: =IFERROR(VLOOKUP($D10,OT!$A:$BR,OT!BF$1,0),0)-S10 -> 0 | DX10: =IFERROR(VLOOKUP($D10,OT!$A:$BR,OT!BG$1,0),0)-T10 -> 0 | DY10: =IFERROR(VLOOKUP($D10,OT!$A:$BR,OT!BH$1,0),0)-U10 -> 0 | DZ10: =IFERROR(VLOOKUP($D10,OT!$A:$BR,OT!BI$1,0),0)-V10 -> 0 | EA10: =IFERROR(VLOOKUP($D10,OT!$A:$BR,OT!BJ$1,0),0)-W10 -> 0 | EB10: =IFERROR(VLOOKUP($D10,OT!$A:$BR,OT!BK$1,0),0)-X10 -> 0 | EC10: =VLOOKUP(D10,'Off day working'!A:AL,38,0)*30000-BD10 -> 0 | EF10: =IF(G10="M",0-BE10,IF(G10="F",K10/208*1.5-BE10)) -> 0.076923077 | EG10: =4960000*1.07/208*VLOOKUP(D10,Att!B:BZ,77,0)-BJ10 -> 0 | EI10: =IF(AND(CH10="X",EJ10>=0.5),150000/VLOOKUP(D10,Att!B:AT,45,0)*VLOOKUP(D10,Att!B:AP,41,0),IF(AND(CH10="X",EJ10<0.5),0,150000))-AN10 -> 0 | EJ10: =VLOOKUP(D10,Att!B:AP,41,0)/VLOOKUP(D10,Att!B:AT,45,0) -> 1.1009154
A11: Out | B11: =ROW()-7 -> 4 | C11: R&D | D11: 24004708 | E11: 93404169 | F11: NGUYỄN THỊ HÒA | G11: F | H11: THPT | I11: VN3001 | J11: 48-12 | K11: 5900000 | M11: 208 | O11: 200 | P11: 36 | Q11: 0 | R11: 0 | S11: 0 | T11: 0 | U11: 0 | V11: 0 | W11: 0 | X11: 0 | Y11: 0 | AB11: 5673076.7 | AC11: 1531730.8 | AD11: 0 | AE11: 0 | AF11: 0 | AG11: 0 | AH11: 0 | AI11: 0 | AJ11: 0 | AK11: 0 | AL11: 0 | AM11: 300000 | AN11: 150000 | AO11: 555000 | AP11: 0 | AQ11: 1021153.8 | AR11: 500000 | AT11: 0 | AU11: 0 | AV11: 0 | AW11: 0 | AX11: 0 | AY11: 0 | BB11: 18 | BC11: 510576.92 | BD11: 0 | BE11: 42548 | BF11: 100000 | BG11: 95000 | BH11: 300000 | BL11: 0 | BN11: 0 | BO11: 0 | BP11: 403846.15 | BQ11: 72692.308 | BS11: 0 | BT11: 1268500 | BU11: 619500 | BW11: 0 | BX11: 10 | BY11: 283653.85 | CB11: 12524143 | CC11: 10159604 | CE11: ANNK-HR | CF11: 45350 | CH11: O | CI11: 0 | CJ11: 0 | CL11: =SUM(BN11:BQ11)+CJ11 -> 476538.46 | CM11: =SUM(AB11:AU11,AW11,AY11,BA11,BC11,BD11:BH11,BJ11:BL11,BM11:BR11,BS11,BT11)+100%*CA11-CB11+CJ11+CI11 -> -18.3069 | CN11: =SUM(AB11:AU11,AW11,AY11,BA11,BC11,BD11:BH11,BJ11,BL11)+BS11-BU11+CA11-CC11 -> -17.7684 | CO11: =K11/M11*O11-AB11 -> 0.22687692 | CQ11: =$K11/$M11*P11*1.5-AC11 -> 3.0769501e-05 | CR11: =$K11/$M11*Q11*1.75-AD11 -> 0 | CS11: =$K11/$M11*R11*2-AE11 -> 0 | CT11: =$K11/$M11*S11*2.1-AF11 -> 0 | CU11: =$K11/$M11*T11*2.2-AG11 -> 0 | CV11: =$K11/$M11*U11*2.9-AH11 -> 0 | CW11: =$K11/$M11*V11*3-AI11 -> 0 | CX11: =$K11/$M11*W11*4.1-AJ11 -> 0 | CY11: =$K11/$M11*X11*1-AK11 -> 0 | CZ11: =(BP11+BQ11) -> 476538.46 | DA11: =(420000/208)*(O11+P11+Q11+R11+S11+T11+U11+V11+W11+X11+BI11)-CZ11 -> 3.8461585e-05 | DC11: =K11/M11*IFERROR(VLOOKUP($D11,Shift!$B:$AZ,45,0),0)-AT11 -> 0 | DD11: =K11/M11*IFERROR(VLOOKUP($D11,Shift!$B:$AV,47,0),0)*10*50%-ROUND(K11/M11*IFERROR(VLOOKUP($D11,Shift!$B:$AV,47,0),0)*8*30%,0)-AU11 -> 0 | DE11: =VLOOKUP($D11,'Off day working'!A:AM,38,0)-Z11 -> 0 | DH11: =K11/208*8*30%*VLOOKUP($D11,Shift!$B:$AZ,47,0)-AL11 -> 0 | DK11: =VLOOKUP($D11,Meal!$A:$AK,35,0)-BG11 -> 0 | DL11: =VLOOKUP($D11,Meal!$A:$AK,36,0)-BH11 -> 0 | DM11: =VLOOKUP($D11,Shift!B:AW,39,0)-AV11 -> 0 | DN11: =K11/208*VLOOKUP(D11,Shift!$B:$AO,39,0)*8*10%-AW11 -> 0 | DO11: =VLOOKUP($D11,Shift!$B:$AO,40,0)-AX11 -> 0 | DP11: =K11/208*VLOOKUP(D11,Shift!$B:$AO,40,0)*8*50%-AY11 -> 0 | DQ11: =VLOOKUP($D11,Shift!$B:$AZ,41,0)-AZ11 -> 0 | DR11: =K11/208*VLOOKUP($D11,Shift!$B:$AQ,41,0)*8*50%-BA11 -> 0 | DS11: =VLOOKUP($D11,Att!B:CU,98,0)-O11 -> 0 | DT11: =IFERROR(VLOOKUP($D11,OT!$A:$BR,OT!BC$1,0),0)-P11 -> 0 | DU11: =IFERROR(VLOOKUP($D11,OT!$A:$BR,OT!BD$1,0),0)-Q11 -> 0 | DV11: =IFERROR(VLOOKUP($D11,OT!$A:$BR,OT!BE$1,0),0)-R11 -> 0 | DW11: =IFERROR(VLOOKUP($D11,OT!$A:$BR,OT!BF$1,0),0)-S11 -> 0 | DX11: =IFERROR(VLOOKUP($D11,OT!$A:$BR,OT!BG$1,0),0)-T11 -> 0 | DY11: =IFERROR(VLOOKUP($D11,OT!$A:$BR,OT!BH$1,0),0)-U11 -> 0 | DZ11: =IFERROR(VLOOKUP($D11,OT!$A:$BR,OT!BI$1,0),0)-V11 -> 0 | EA11: =IFERROR(VLOOKUP($D11,OT!$A:$BR,OT!BJ$1,0),0)-W11 -> 0 | EB11: =IFERROR(VLOOKUP($D11,OT!$A:$BR,OT!BK$1,0),0)-X11 -> 0 | EC11: =VLOOKUP(D11,'Off day working'!A:AL,38,0)*30000-BD11 -> 0 | EF11: =IF(G11="M",0-BE11,IF(G11="F",K11/208*1.5-BE11)) -> 0.076923077 | EG11: =4960000*1.07/208*VLOOKUP(D11,Att!B:BZ,77,0)-BJ11 -> 0 | EI11: =IF(AND(CH11="X",EJ11>=0.5),150000/VLOOKUP(D11,Att!B:AT,45,0)*VLOOKUP(D11,Att!B:AP,41,0),IF(AND(CH11="X",EJ11<0.5),0,150000))-AN11 -> 0 | EJ11: =VLOOKUP(D11,Att!B:AP,41,0)/VLOOKUP(D11,Att!B:AT,45,0) -> 1.0526316
A12: Out | B12: =ROW()-7 -> 5 | C12: R&D | D12: 24004714 | E12: 93404175 | F12: NGUYỄN LÊ HỒNG HẠNH | G12: F | H12: THPT | I12: VN3001 | J12: 48-12 | K12: 5900000 | M12: 208 | O12: 208 | P12: 34 | Q12: 0 | R12: 0 | S12: 0 | T12: 0 | U12: 0 | V12: 0 | W12: 0 | X12: 0 | Y12: 0 | AB12: 5899999.9 | AC12: 1446634.6 | AD12: 0 | AE12: 0 | AF12: 0 | AG12: 0 | AH12: 0 | AI12: 0 | AJ12: 0 | AK12: 0 | AL12: 0 | AM12: 300000 | AN12: 150000 | AO12: 525000 | AP12: 0 | AQ12: 1021153.8 | AR12: 500000 | AT12: 0 | AU12: 0 | AV12: 0 | AW12: 0 | AX12: 0 | AY12: 0 | BB12: 17 | BC12: 482211.54 | BD12: 0 | BE12: 42548 | BF12: 100000 | BG12: 95000 | BH12: 300000 | BL12: 0 | BN12: 0 | BO12: 0 | BP12: 420000 | BQ12: 68653.846 | BS12: 0 | BT12: 1268500 | BU12: 619500 | BW12: 0 | BX12: 18 | BY12: 510576.92 | CB12: 12619719 | CC12: 10243065 | CE12: ANNK-HR | CF12: 45350 | CH12: O | CI12: 0 | CJ12: 0 | CL12: =SUM(BN12:BQ12)+CJ12 -> 488653.85 | CM12: =SUM(AB12:AU12,AW12,AY12,BA12,BC12,BD12:BH12,BJ12:BL12,BM12:BR12,BS12,BT12)+100%*CA12-CB12+CJ12+CI12 -> -17.2657 | CN12: =SUM(AB12:AU12,AW12,AY12,BA12,BC12,BD12:BH12,BJ12,BL12)+BS12-BU12+CA12-CC12 -> -17.1119 | CO12: =K12/M12*O12-AB12 -> 0.1135 | CQ12: =$K12/$M12*P12*1.5-AC12 -> -1.5384518e-05 | CR12: =$K12/$M12*Q12*1.75-AD12 -> 0 | CS12: =$K12/$M12*R12*2-AE12 -> 0 | CT12: =$K12/$M12*S12*2.1-AF12 -> 0 | CU12: =$K12/$M12*T12*2.2-AG12 -> 0 | CV12: =$K12/$M12*U12*2.9-AH12 -> 0 | CW12: =$K12/$M12*V12*3-AI12 -> 0 | CX12: =$K12/$M12*W12*4.1-AJ12 -> 0 | CY12: =$K12/$M12*X12*1-AK12 -> 0 | CZ12: =(BP12+BQ12) -> 488653.85 | DA12: =(420000/208)*(O12+P12+Q12+R12+S12+T12+U12+V12+W12+X12+BI12)-CZ12 -> -4.6153844e-05 | DC12: =K12/M12*IFERROR(VLOOKUP($D12,Shift!$B:$AZ,45,0),0)-AT12 -> 0 | DD12: =K12/M12*IFERROR(VLOOKUP($D12,Shift!$B:$AV,47,0),0)*10*50%-ROUND(K12/M12*IFERROR(VLOOKUP($D12,Shift!$B:$AV,47,0),0)*8*30%,0)-AU12 -> 0 | DE12: =VLOOKUP($D12,'Off day working'!A:AM,38,0)-Z12 -> 0 | DH12: =K12/208*8*30%*VLOOKUP($D12,Shift!$B:$AZ,47,0)-AL12 -> 0 | DK12: =VLOOKUP($D12,Meal!$A:$AK,35,0)-BG12 -> 0 | DL12: =VLOOKUP($D12,Meal!$A:$AK,36,0)-BH12 -> 0 | DM12: =VLOOKUP($D12,Shift!B:AW,39,0)-AV12 -> 0 | DN12: =K12/208*VLOOKUP(D12,Shift!$B:$AO,39,0)*8*10%-AW12 -> 0 | DO12: =VLOOKUP($D12,Shift!$B:$AO,40,0)-AX12 -> 0 | DP12: =K12/208*VLOOKUP(D12,Shift!$B:$AO,40,0)*8*50%-AY12 -> 0 | DQ12: =VLOOKUP($D12,Shift!$B:$AZ,41,0)-AZ12 -> 0 | DR12: =K12/208*VLOOKUP($D12,Shift!$B:$AQ,41,0)*8*50%-BA12 -> 0 | DS12: =VLOOKUP($D12,Att!B:CU,98,0)-O12 -> 0 | DT12: =IFERROR(VLOOKUP($D12,OT!$A:$BR,OT!BC$1,0),0)-P12 -> 0 | DU12: =IFERROR(VLOOKUP($D12,OT!$A:$BR,OT!BD$1,0),0)-Q12 -> 0 | DV12: =IFERROR(VLOOKUP($D12,OT!$A:$BR,OT!BE$1,0),0)-R12 -> 0 | DW12: =IFERROR(VLOOKUP($D12,OT!$A:$BR,OT!BF$1,0),0)-S12 -> 0 | DX12: =IFERROR(VLOOKUP($D12,OT!$A:$BR,OT!BG$1,0),0)-T12 -> 0 | DY12: =IFERROR(VLOOKUP($D12,OT!$A:$BR,OT!BH$1,0),0)-U12 -> 0 | DZ12: =IFERROR(VLOOKUP($D12,OT!$A:$BR,OT!BI$1,0),0)-V12 -> 0 | EA12: =IFERROR(VLOOKUP($D12,OT!$A:$BR,OT!BJ$1,0),0)-W12 -> 0 | EB12: =IFERROR(VLOOKUP($D12,OT!$A:$BR,OT!BK$1,0),0)-X12 -> 0 | EC12: =VLOOKUP(D12,'Off day working'!A:AL,38,0)*30000-BD12 -> 0 | EF12: =IF(G12="M",0-BE12,IF(G12="F",K12/208*1.5-BE12)) -> 0.076923077 | EG12: =4960000*1.07/208*VLOOKUP(D12,Att!B:BZ,77,0)-BJ12 -> 0 | EI12: =IF(AND(CH12="X",EJ12>=0.5),150000/VLOOKUP(D12,Att!B:AT,45,0)*VLOOKUP(D12,Att!B:AP,41,0),IF(AND(CH12="X",EJ12<0.5),0,150000))-AN12 -> 0 | EJ12: =VLOOKUP(D12,Att!B:AP,41,0)/VLOOKUP(D12,Att!B:AT,45,0) -> 1.0526316
A13: Out | B13: =ROW()-7 -> 6 | C13: PD | D13: 24004741 | E13: 93404202 | F13: NGUYỄN THỊ MỸ LINH | G13: F | H13: THPT | I13: VN1001 | J13: 48-12 | K13: 5900000 | M13: 208 | O13: 208 | P13: 38 | Q13: 0 | R13: 12 | S13: 0 | T13: 0 | U13: 0 | V13: 0 | W13: 0 | X13: 0 | Y13: 6 | Z13: 1 | AB13: 5899999.9 | AC13: 1616826.9 | AD13: 0 | AE13: 680769.23 | AF13: 0 | AG13: 0 | AH13: 0 | AI13: 0 | AJ13: 0 | AK13: 0 | AL13: 340384.62 | AM13: 300000 | AN13: 150000 | AO13: 412500 | AP13: 0 | AQ13: 1021153.8 | AR13: 500000 | AT13: 0 | AU13: 368750 | AV13: 0 | AW13: 0 | AX13: 1 | AY13: 113461.54 | BB13: 19 | BC13: 538942.31 | BD13: 30000 | BE13: 42548 | BF13: 100000 | BG13: 62000 | BH13: 450000 | BL13: 0 | BN13: 0 | BO13: 0 | BP13: 420000 | BQ13: 100961.54 | BS13: 0 | BT13: 1268500 | BU13: 619500 | BW13: 0 | BX13: 28 | BY13: 794230.77 | CB13: 14534818 | CC13: 12007856 | CE13: MEKONG SUBLABOR | CF13: 45369 | CH13: O | CI13: 118000 | CJ13: 0 | CL13: =SUM(BN13:BQ13)+CJ13 -> 520961.54 | CM13: =SUM(AB13:AU13,AW13,AY13,BA13,BC13,BD13:BH13,BJ13:BL13,BM13:BR13,BS13,BT13)+100%*CA13-CB13+CJ13+CI13 -> -20.111 | CN13: =SUM(AB13:AU13,AW13,AY13,BA13,BC13,BD13:BH13,BJ13,BL13)+BS13-BU13+CA13-CC13 -> -19.6495 | CO13: =K13/M13*O13-AB13 -> 0.1135 | CQ13: =$K13/$M13*P13*1.5-AC13 -> -2.3076776e-05 | CR13: =$K13/$M13*Q13*1.75-AD13 -> 0 | CS13: =$K13/$M13*R13*2-AE13 -> -3.0769268e-05 | CT13: =$K13/$M13*S13*2.1-AF13 -> 0 | CU13: =$K13/$M13*T13*2.2-AG13 -> 0 | CV13: =$K13/$M13*U13*2.9-AH13 -> 0 | CW13: =$K13/$M13*V13*3-AI13 -> 0 | CX13: =$K13/$M13*W13*4.1-AJ13 -> 0 | CY13: =$K13/$M13*X13*1-AK13 -> 0 | CZ13: =(BP13+BQ13) -> 520961.54 | DA13: =(420000/208)*(O13+P13+Q13+R13+S13+T13+U13+V13+W13+X13+BI13)-CZ13 -> -3.8461527e-05 | DC13: =K13/M13*IFERROR(VLOOKUP($D13,Shift!$B:$AZ,45,0),0)-AT13 -> 0 | DD13: =K13/M13*IFERROR(VLOOKUP($D13,Shift!$B:$AV,47,0),0)*10*50%-ROUND(K13/M13*IFERROR(VLOOKUP($D13,Shift!$B:$AV,47,0),0)*8*30%,0)-AU13 -> -0.38461538 | DE13: =VLOOKUP($D13,'Off day working'!A:AM,38,0)-Z13 -> 0 | DH13: =K13/208*8*30%*VLOOKUP($D13,Shift!$B:$AZ,47,0)-AL13 -> -1.5384634e-05 | DK13: =VLOOKUP($D13,Meal!$A:$AK,35,0)-BG13 -> 0 | DL13: =VLOOKUP($D13,Meal!$A:$AK,36,0)-BH13 -> 0 | DM13: =VLOOKUP($D13,Shift!B:AW,39,0)-AV13 -> 0 | DN13: =K13/208*VLOOKUP(D13,Shift!$B:$AO,39,0)*8*10%-AW13 -> 0 | DO13: =VLOOKUP($D13,Shift!$B:$AO,40,0)-AX13 -> 0 | DP13: =K13/208*VLOOKUP(D13,Shift!$B:$AO,40,0)*8*50%-AY13 -> -3.8461527e-05 | DQ13: =VLOOKUP($D13,Shift!$B:$AZ,41,0)-AZ13 -> 0 | DR13: =K13/208*VLOOKUP($D13,Shift!$B:$AQ,41,0)*8*50%-BA13 -> 0 | DS13: =VLOOKUP($D13,Att!B:CU,98,0)-O13 -> 0 | DT13: =IFERROR(VLOOKUP($D13,OT!$A:$BR,OT!BC$1,0),0)-P13 -> 0 | DU13: =IFERROR(VLOOKUP($D13,OT!$A:$BR,OT!BD$1,0),0)-Q13 -> 0 | DV13: =IFERROR(VLOOKUP($D13,OT!$A:$BR,OT!BE$1,0),0)-R13 -> 0 | DW13: =IFERROR(VLOOKUP($D13,OT!$A:$BR,OT!BF$1,0),0)-S13 -> 0 | DX13: =IFERROR(VLOOKUP($D13,OT!$A:$BR,OT!BG$1,0),0)-T13 -> 0 | DY13: =IFERROR(VLOOKUP($D13,OT!$A:$BR,OT!BH$1,0),0)-U13 -> 0 | DZ13: =IFERROR(VLOOKUP($D13,OT!$A:$BR,OT!BI$1,0),0)-V13 -> 0 | EA13: =IFERROR(VLOOKUP($D13,OT!$A:$BR,OT!BJ$1,0),0)-W13 -> 0 | EB13: =IFERROR(VLOOKUP($D13,OT!$A:$BR,OT!BK$1,0),0)-X13 -> 0 | EC13: =VLOOKUP(D13,'Off day working'!A:AL,38,0)*30000-BD13 -> 0 | EF13: =IF(G13="M",0-BE13,IF(G13="F",K13/208*1.5-BE13)) -> 0.076923077 | EG13: =4960000*1.07/208*VLOOKUP(D13,Att!B:BZ,77,0)-BJ13 -> 0 | EI13: =IF(AND(CH13="X",EJ13>=0.5),150000/VLOOKUP(D13,Att!B:AT,45,0)*VLOOKUP(D13,Att!B:AP,41,0),IF(AND(CH13="X",EJ13<0.5),0,150000))-AN13 -> 0 | EJ13: =VLOOKUP(D13,Att!B:AP,41,0)/VLOOKUP(D13,Att!B:AT,45,0) -> 0.99082387
A14: Out | B14: =ROW()-7 -> 7 | C14: PD | D14: 24004755 | E14: 93404216 | F14: ĐỖ THỊ BẢO YẾN | G14: F | I14: VN1001 | J14: 48-12 | K14: 5900000 | M14: 208 | O14: 160 | P14: 16 | Q14: 0 | R14: 20 | S14: 0 | T14: 0 | U14: 0 | V14: 0 | W14: 0 | X14: 0 | Y14: 0 | Z14: 2 | AB14: 4538461.4 | AC14: 680769.23 | AD14: 0 | AE14: 1134615.4 | AF14: 0 | AG14: 0 | AH14: 0 | AI14: 0 | AJ14: 0 | AK14: 0 | AL14: 0 | AM14: 300000 | AN14: 150000 | AO14: 155000 | AP14: 0 | AQ14: 765865.38 | AR14: 500000 | AT14: 0 | AU14: 0 | AV14: 0 | AW14: 0 | AX14: 0 | AY14: 0 | BB14: 8 | BC14: 226923.08 | BD14: 60000 | BE14: 42548 | BG14: 190000 | BH14: 175000 | BL14: 0 | BN14: 0 | BO14: 0 | BP14: 323076.92 | BQ14: 72692.308 | BS14: 0 | BT14: 1268500 | BU14: 619500 | BW14: 0 | BY14: 0 | CB14: 10701460 | CC14: 8299691 | CE14: MEKONG SUBLABOR | CF14: 45370 | CH14: O | CI14: 118000 | CJ14: 0 | CL14: =SUM(BN14:BQ14)+CJ14 -> 395769.23 | CM14: =SUM(AB14:AU14,AW14,AY14,BA14,BC14,BD14:BH14,BJ14:BL14,BM14:BR14,BS14,BT14)+100%*CA14-CB14+CJ14+CI14 -> -8.2642 | CN14: =SUM(AB14:AU14,AW14,AY14,BA14,BC14,BD14:BH14,BJ14,BL14)+BS14-BU14+CA14-CC14 -> -8.495 | CO14: =K14/M14*O14-AB14 -> 0.11346154 | CQ14: =$K14/$M14*P14*1.5-AC14 -> -3.0769268e-05 | CR14: =$K14/$M14*Q14*1.75-AD14 -> 0 | CS14: =$K14/$M14*R14*2-AE14 -> 1.538475e-05 | CT14: =$K14/$M14*S14*2.1-AF14 -> 0 | CU14: =$K14/$M14*T14*2.2-AG14 -> 0 | CV14: =$K14/$M14*U14*2.9-AH14 -> 0 | CW14: =$K14/$M14*V14*3-AI14 -> 0 | CX14: =$K14/$M14*W14*4.1-AJ14 -> 0 | CY14: =$K14/$M14*X14*1-AK14 -> 0 | CZ14: =(BP14+BQ14) -> 395769.23 | DA14: =(420000/208)*(O14+P14+Q14+R14+S14+T14+U14+V14+W14+X14+BI14)-CZ14 -> -3.0769268e-05 | DC14: =K14/M14*IFERROR(VLOOKUP($D14,Shift!$B:$AZ,45,0),0)-AT14 -> 0 | DD14: =K14/M14*IFERROR(VLOOKUP($D14,Shift!$B:$AV,47,0),0)*10*50%-ROUND(K14/M14*IFERROR(VLOOKUP($D14,Shift!$B:$AV,47,0),0)*8*30%,0)-AU14 -> 0 | DE14: =VLOOKUP($D14,'Off day working'!A:AM,38,0)-Z14 -> 0 | DH14: =K14/208*8*30%*VLOOKUP($D14,Shift!$B:$AZ,47,0)-AL14 -> 0 | DK14: =VLOOKUP($D14,Meal!$A:$AK,35,0)-BG14 -> 0 | DL14: =VLOOKUP($D14,Meal!$A:$AK,36,0)-BH14 -> 0 | DM14: =VLOOKUP($D14,Shift!B:AW,39,0)-AV14 -> 0 | DN14: =K14/208*VLOOKUP(D14,Shift!$B:$AO,39,0)*8*10%-AW14 -> 0 | DO14: =VLOOKUP($D14,Shift!$B:$AO,40,0)-AX14 -> 0 | DP14: =K14/208*VLOOKUP(D14,Shift!$B:$AO,40,0)*8*50%-AY14 -> 0 | DQ14: =VLOOKUP($D14,Shift!$B:$AZ,41,0)-AZ14 -> 0 | DR14: =K14/208*VLOOKUP($D14,Shift!$B:$AQ,41,0)*8*50%-BA14 -> 0 | DS14: =VLOOKUP($D14,Att!B:CU,98,0)-O14 -> 0 | DT14: =IFERROR(VLOOKUP($D14,OT!$A:$BR,OT!BC$1,0),0)-P14 -> 0 | DU14: =IFERROR(VLOOKUP($D14,OT!$A:$BR,OT!BD$1,0),0)-Q14 -> 0 | DV14: =IFERROR(VLOOKUP($D14,OT!$A:$BR,OT!BE$1,0),0)-R14 -> 0 | DW14: =IFERROR(VLOOKUP($D14,OT!$A:$BR,OT!BF$1,0),0)-S14 -> 0 | DX14: =IFERROR(VLOOKUP($D14,OT!$A:$BR,OT!BG$1,0),0)-T14 -> 0 | DY14: =IFERROR(VLOOKUP($D14,OT!$A:$BR,OT!BH$1,0),0)-U14 -> 0 | DZ14: =IFERROR(VLOOKUP($D14,OT!$A:$BR,OT!BI$1,0),0)-V14 -> 0 | EA14: =IFERROR(VLOOKUP($D14,OT!$A:$BR,OT!BJ$1,0),0)-W14 -> 0 | EB14: =IFERROR(VLOOKUP($D14,OT!$A:$BR,OT!BK$1,0),0)-X14 -> 0 | EC14: =VLOOKUP(D14,'Off day working'!A:AL,38,0)*30000-BD14 -> 0 | EF14: =IF(G14="M",0-BE14,IF(G14="F",K14/208*1.5-BE14)) -> 0.076923077 | EG14: =4960000*1.07/208*VLOOKUP(D14,Att!B:BZ,77,0)-BJ14 -> 0 | EI14: =IF(AND(CH14="X",EJ14>=0.5),150000/VLOOKUP(D14,Att!B:AT,45,0)*VLOOKUP(D14,Att!B:AP,41,0),IF(AND(CH14="X",EJ14<0.5),0,150000))-AN14 -> 0 | EJ14: =VLOOKUP(D14,Att!B:AP,41,0)/VLOOKUP(D14,Att!B:AT,45,0) -> 0.89473684
A15: Out | B15: =ROW()-7 -> 8 | C15: PD | D15: 24004788 | E15: 93404249 | F15: VŨ THỊ MỸ LƯƠNG | G15: F | H15: Đại học | I15: VN1001 | J15: 48-12 | K15: 5900000 | M15: 208 | O15: 200 | P15: 36 | Q15: 0 | R15: 12 | S15: 0 | T15: 0 | U15: 0 | V15: 0 | W15: 0 | X15: 0 | Y15: 5 | Z15: 1 | AB15: 5673076.7 | AC15: 1531730.8 | AD15: 0 | AE15: 680769.23 | AF15: 0 | AG15: 0 | AH15: 0 | AI15: 0 | AJ15: 0 | AK15: 0 | AL15: 272307.69 | AM15: 300000 | AN15: 150000 | AO15: 510000 | AP15: 120000 | AQ15: 765865.38 | AR15: 500000 | AT15: 0 | AU15: 295000 | AV15: 0 | AW15: 0 | AX15: 1 | AY15: 113461.54 | BB15: 18 | BC15: 510576.92 | BD15: 30000 | BE15: 42548 | BF15: 200000 | BG15: 95000 | BH15: 450000 | BL15: 0 | BN15: 0 | BO15: 0 | BP15: 403846.15 | BQ15: 96923.077 | BS15: 0 | BT15: 1268500 | BU15: 619500 | BW15: 0 | BY15: 0 | CB15: 14127624 | CC15: 11620855 | CE15: Nhân Kiệt | CF15: 45386 | CH15: O | CI15: 118000 | CJ15: 0 | CL15: =SUM(BN15:BQ15)+CJ15 -> 500769.23 | CM15: =SUM(AB15:AU15,AW15,AY15,BA15,BC15,BD15:BH15,BJ15:BL15,BM15:BR15,BS15,BT15)+100%*CA15-CB15+CJ15+CI15 -> -18.5377 | CN15: =SUM(AB15:AU15,AW15,AY15,BA15,BC15,BD15:BH15,BJ15,BL15)+BS15-BU15+CA15-CC15 -> -18.7684 | CO15: =K15/M15*O15-AB15 -> 0.22687692 | CQ15: =$K15/$M15*P15*1.5-AC15 -> 3.0769501e-05 | CR15: =$K15/$M15*Q15*1.75-AD15 -> 0 | CS15: =$K15/$M15*R15*2-AE15 -> -3.0769268e-05 | CT15: =$K15/$M15*S15*2.1-AF15 -> 0 | CU15: =$K15/$M15*T15*2.2-AG15 -> 0 | CV15: =$K15/$M15*U15*2.9-AH15 -> 0 | CW15: =$K15/$M15*V15*3-AI15 -> 0 | CX15: =$K15/$M15*W15*4.1-AJ15 -> 0 | CY15: =$K15/$M15*X15*1-AK15 -> 0 | CZ15: =(BP15+BQ15) -> 500769.23 | DA15: =(420000/208)*(O15+P15+Q15+R15+S15+T15+U15+V15+W15+X15+BI15)-CZ15 -> 6.9230853e-05 | DC15: =K15/M15*IFERROR(VLOOKUP($D15,Shift!$B:$AZ,45,0),0)-AT15 -> 0 | DD15: =K15/M15*IFERROR(VLOOKUP($D15,Shift!$B:$AV,47,0),0)*10*50%-ROUND(K15/M15*IFERROR(VLOOKUP($D15,Shift!$B:$AV,47,0),0)*8*30%,0)-AU15 -> -0.30769231 | DE15: =VLOOKUP($D15,'Off day working'!A:AM,38,0)-Z15 -> 0 | DH15: =K15/208*8*30%*VLOOKUP($D15,Shift!$B:$AZ,47,0)-AL15 -> 7.692317e-06 | DK15: =VLOOKUP($D15,Meal!$A:$AK,35,0)-BG15 -> 0 | DL15: =VLOOKUP($D15,Meal!$A:$AK,36,0)-BH15 -> 0 | DM15: =VLOOKUP($D15,Shift!B:AW,39,0)-AV15 -> 0 | DN15: =K15/208*VLOOKUP(D15,Shift!$B:$AO,39,0)*8*10%-AW15 -> 0 | DO15: =VLOOKUP($D15,Shift!$B:$AO,40,0)-AX15 -> 0 | DP15: =K15/208*VLOOKUP(D15,Shift!$B:$AO,40,0)*8*50%-AY15 -> -3.8461527e-05 | DQ15: =VLOOKUP($D15,Shift!$B:$AZ,41,0)-AZ15 -> 0 | DR15: =K15/208*VLOOKUP($D15,Shift!$B:$AQ,41,0)*8*50%-BA15 -> 0 | DS15: =VLOOKUP($D15,Att!B:CU,98,0)-O15 -> 0 | DT15: =IFERROR(VLOOKUP($D15,OT!$A:$BR,OT!BC$1,0),0)-P15 -> 0 | DU15: =IFERROR(VLOOKUP($D15,OT!$A:$BR,OT!BD$1,0),0)-Q15 -> 0 | DV15: =IFERROR(VLOOKUP($D15,OT!$A:$BR,OT!BE$1,0),0)-R15 -> 0 | DW15: =IFERROR(VLOOKUP($D15,OT!$A:$BR,OT!BF$1,0),0)-S15 -> 0 | DX15: =IFERROR(VLOOKUP($D15,OT!$A:$BR,OT!BG$1,0),0)-T15 -> 0 | DY15: =IFERROR(VLOOKUP($D15,OT!$A:$BR,OT!BH$1,0),0)-U15 -> 0 | DZ15: =IFERROR(VLOOKUP($D15,OT!$A:$BR,OT!BI$1,0),0)-V15 -> 0 | EA15: =IFERROR(VLOOKUP($D15,OT!$A:$BR,OT!BJ$1,0),0)-W15 -> 0 | EB15: =IFERROR(VLOOKUP($D15,OT!$A:$BR,OT!BK$1,0),0)-X15 -> 0 | EC15: =VLOOKUP(D15,'Off day working'!A:AL,38,0)*30000-BD15 -> 0 | EF15: =IF(G15="M",0-BE15,IF(G15="F",K15/208*1.5-BE15)) -> 0.076923077 | EG15: =4960000*1.07/208*VLOOKUP(D15,Att!B:BZ,77,0)-BJ15 -> 0 | EI15: =IF(AND(CH15="X",EJ15>=0.5),150000/VLOOKUP(D15,Att!B:AT,45,0)*VLOOKUP(D15,Att!B:AP,41,0),IF(AND(CH15="X",EJ15<0.5),0,150000))-AN15 -> 0 | EJ15: =VLOOKUP(D15,Att!B:AP,41,0)/VLOOKUP(D15,Att!B:AT,45,0) -> 1.1052632
A16: Out | B16: =ROW()-7 -> 9 | C16: PD | D16: 24004790 | E16: 93404251 | F16: NGUYỄN NGỌC SƠN | G16: M | H16: Trung cấp | I16: VN1003 | J16: 48-12 | K16: 5900000 | M16: 208 | O16: 182 | P16: 36 | Q16: 0 | R16: 0 | S16: 0 | T16: 0 | U16: 0 | V16: 0 | W16: 0 | X16: 0 | Y16: 9 | AB16: 5162499.8 | AC16: 1531730.8 | AD16: 0 | AE16: 0 | AF16: 0 | AG16: 0 | AH16: 0 | AI16: 0 | AJ16: 0 | AK16: 0 | AL16: 544615.38 | AM16: 300000 | AN16: 150000 | AO16: 180000 | AP16: 0 | AQ16: 510576.92 | AR16: 0 | AT16: 0 | AU16: 590000 | AV16: 0 | AW16: 0 | AX16: 1 | AY16: 113461.54 | BB16: 18 | BC16: 510576.92 | BD16: 0 | BF16: 150000 | BG16: 99000 | BH16: 474000 | BL16: 0 | BN16: 0 | BO16: 0 | BP16: 367500 | BQ16: 72692.308 | BS16: 0 | BT16: 1268500 | BU16: 619500 | BW16: 0 | BY16: 0 | CB16: 12143173 | CC16: 9696980 | CE16: Nhân Kiệt | CF16: 45386 | CH16: O | CI16: 118000 | CJ16: 0 | CL16: =SUM(BN16:BQ16)+CJ16 -> 440192.31 | CM16: =SUM(AB16:AU16,AW16,AY16,BA16,BC16,BD16:BH16,BJ16:BL16,BM16:BR16,BS16,BT16)+100%*CA16-CB16+CJ16+CI16 -> -19.3838 | CN16: =SUM(AB16:AU16,AW16,AY16,BA16,BC16,BD16:BH16,BJ16,BL16)+BS16-BU16+CA16-CC16 -> -18.6915 | CO16: =K16/M16*O16-AB16 -> 0.2269 | CQ16: =$K16/$M16*P16*1.5-AC16 -> 3.0769501e-05 | CR16: =$K16/$M16*Q16*1.75-AD16 -> 0 | CS16: =$K16/$M16*R16*2-AE16 -> 0 | CT16: =$K16/$M16*S16*2.1-AF16 -> 0 | CU16: =$K16/$M16*T16*2.2-AG16 -> 0 | CV16: =$K16/$M16*U16*2.9-AH16 -> 0 | CW16: =$K16/$M16*V16*3-AI16 -> 0 | CX16: =$K16/$M16*W16*4.1-AJ16 -> 0 | CY16: =$K16/$M16*X16*1-AK16 -> 0 | CZ16: =(BP16+BQ16) -> 440192.31 | DA16: =(420000/208)*(O16+P16+Q16+R16+S16+T16+U16+V16+W16+X16+BI16)-CZ16 -> -7.692317e-06 | DC16: =K16/M16*IFERROR(VLOOKUP($D16,Shift!$B:$AZ,45,0),0)-AT16 -> 0 | DD16: =K16/M16*IFERROR(VLOOKUP($D16,Shift!$B:$AV,47,0),0)*10*50%-ROUND(K16/M16*IFERROR(VLOOKUP($D16,Shift!$B:$AV,47,0),0)*8*30%,0)-AU16 -> 0.38461538 | DE16: =VLOOKUP($D16,'Off day working'!A:AM,38,0)-Z16 -> 0 | DH16: =K16/208*8*30%*VLOOKUP($D16,Shift!$B:$AZ,47,0)-AL16 -> 1.5384634e-05 | DK16: =VLOOKUP($D16,Meal!$A:$AK,35,0)-BG16 -> 0 | DL16: =VLOOKUP($D16,Meal!$A:$AK,36,0)-BH16 -> 0 | DM16: =VLOOKUP($D16,Shift!B:AW,39,0)-AV16 -> 0 | DN16: =K16/208*VLOOKUP(D16,Shift!$B:$AO,39,0)*8*10%-AW16 -> 0 | DO16: =VLOOKUP($D16,Shift!$B:$AO,40,0)-AX16 -> 0 | DP16: =K16/208*VLOOKUP(D16,Shift!$B:$AO,40,0)*8*50%-AY16 -> -3.8461527e-05 | DQ16: =VLOOKUP($D16,Shift!$B:$AZ,41,0)-AZ16 -> 0 | DR16: =K16/208*VLOOKUP($D16,Shift!$B:$AQ,41,0)*8*50%-BA16 -> 0 | DS16: =VLOOKUP($D16,Att!B:CU,98,0)-O16 -> 0 | DT16: =IFERROR(VLOOKUP($D16,OT!$A:$BR,OT!BC$1,0),0)-P16 -> 0 | DU16: =IFERROR(VLOOKUP($D16,OT!$A:$BR,OT!BD$1,0),0)-Q16 -> 0 | DV16: =IFERROR(VLOOKUP($D16,OT!$A:$BR,OT!BE$1,0),0)-R16 -> 0 | DW16: =IFERROR(VLOOKUP($D16,OT!$A:$BR,OT!BF$1,0),0)-S16 -> 0 | DX16: =IFERROR(VLOOKUP($D16,OT!$A:$BR,OT!BG$1,0),0)-T16 -> 0 | DY16: =IFERROR(VLOOKUP($D16,OT!$A:$BR,OT!BH$1,0),0)-U16 -> 0 | DZ16: =IFERROR(VLOOKUP($D16,OT!$A:$BR,OT!BI$1,0),0)-V16 -> 0 | EA16: =IFERROR(VLOOKUP($D16,OT!$A:$BR,OT!BJ$1,0),0)-W16 -> 0 | EB16: =IFERROR(VLOOKUP($D16,OT!$A:$BR,OT!BK$1,0),0)-X16 -> 0 | EC16: =VLOOKUP(D16,'Off day working'!A:AL,38,0)*30000-BD16 -> 0 | EF16: =IF(G16="M",0-BE16,IF(G16="F",K16/208*1.5-BE16)) -> 0 | EG16: =4960000*1.07/208*VLOOKUP(D16,Att!B:BZ,77,0)-BJ16 -> 0 | EI16: =IF(AND(CH16="X",EJ16>=0.5),150000/VLOOKUP(D16,Att!B:AT,45,0)*VLOOKUP(D16,Att!B:AP,41,0),IF(AND(CH16="X",EJ16<0.5),0,150000))-AN16 -> 0 | EJ16: =VLOOKUP(D16,Att!B:AP,41,0)/VLOOKUP(D16,Att!B:AT,45,0) -> 1
A17: Out | B17: =ROW()-7 -> 10 | C17: PD | D17: 24004842 | E17: 93404303 | F17: NGUYỄN THIỆN CẨM | G17: M | H17: THPT | I17: VN1003 | J17: 48-12 | K17: 5900000 | M17: 208 | O17: 152 | P17: 30 | Q17: 0 | R17: 0 | S17: 0 | T17: 0 | U17: 0 | V17: 0 | W17: 0 | X17: 0 | Y17: 7 | AB17: 4311538.2 | AC17: 1276442.3 | AD17: 0 | AE17: 0 | AF17: 0 | AG17: 0 | AH17: 0 | AI17: 0 | AJ17: 0 | AK17: 0 | AL17: 408461.54 | AM17: 300000 | AN17: 150000 | AO17: 510000 | AP17: 0 | AQ17: 255288.46 | AR17: 0 | AT17: 0 | AU17: 442500 | AV17: 0 | AW17: 0 | AX17: 1 | AY17: 113461.54 | BB17: 15 | BC17: 425480.77 | BD17: 0 | BF17: 100000 | BG17: 40000 | BH17: 414000 | BL17: 0 | BN17: 0 | BO17: 0 | BP17: 306923.08 | BQ17: 60576.923 | BS17: 0 | BT17: 1268500 | BU17: 619500 | BW17: 0 | BX17: 10 | BY17: 283653.85 | CB17: 10501189 | CC17: 8127689 | CE17: MEKONG SUBLABOR | CF17: 45422 | CH17: O | CI17: 118000 | CJ17: 0 | CL17: =SUM(BN17:BQ17)+CJ17 -> 367500 | CM17: =SUM(AB17:AU17,AW17,AY17,BA17,BC17,BD17:BH17,BJ17:BL17,BM17:BR17,BS17,BT17)+100%*CA17-CB17+CJ17+CI17 -> -16.1492 | CN17: =SUM(AB17:AU17,AW17,AY17,BA17,BC17,BD17:BH17,BJ17,BL17)+BS17-BU17+CA17-CC17 -> -16.1492 | CO17: =K17/M17*O17-AB17 -> 0.22693846 | CQ17: =$K17/$M17*P17*1.5-AC17 -> -7.6922588e-06 | CR17: =$K17/$M17*Q17*1.75-AD17 -> 0 | CS17: =$K17/$M17*R17*2-AE17 -> 0 | CT17: =$K17/$M17*S17*2.1-AF17 -> 0 | CU17: =$K17/$M17*T17*2.2-AG17 -> 0 | CV17: =$K17/$M17*U17*2.9-AH17 -> 0 | CW17: =$K17/$M17*V17*3-AI17 -> 0 | CX17: =$K17/$M17*W17*4.1-AJ17 -> 0 | CY17: =$K17/$M17*X17*1-AK17 -> 0 | CZ17: =(BP17+BQ17) -> 367500 | DA17: =(420000/208)*(O17+P17+Q17+R17+S17+T17+U17+V17+W17+X17+BI17)-CZ17 -> 0 | DC17: =K17/M17*IFERROR(VLOOKUP($D17,Shift!$B:$AZ,45,0),0)-AT17 -> 0 | DD17: =K17/M17*IFERROR(VLOOKUP($D17,Shift!$B:$AV,47,0),0)*10*50%-ROUND(K17/M17*IFERROR(VLOOKUP($D17,Shift!$B:$AV,47,0),0)*8*30%,0)-AU17 -> -0.46153846 | DE17: =VLOOKUP($D17,'Off day working'!A:AM,38,0)-Z17 -> 0 | DH17: =K17/208*8*30%*VLOOKUP($D17,Shift!$B:$AZ,47,0)-AL17 -> -3.8461527e-05 | DK17: =VLOOKUP($D17,Meal!$A:$AK,35,0)-BG17 -> 0 | DL17: =VLOOKUP($D17,Meal!$A:$AK,36,0)-BH17 -> 0 | DM17: =VLOOKUP($D17,Shift!B:AW,39,0)-AV17 -> 0 | DN17: =K17/208*VLOOKUP(D17,Shift!$B:$AO,39,0)*8*10%-AW17 -> 0 | DO17: =VLOOKUP($D17,Shift!$B:$AO,40,0)-AX17 -> 0 | DP17: =K17/208*VLOOKUP(D17,Shift!$B:$AO,40,0)*8*50%-AY17 -> -3.8461527e-05 | DQ17: =VLOOKUP($D17,Shift!$B:$AZ,41,0)-AZ17 -> 0 | DR17: =K17/208*VLOOKUP($D17,Shift!$B:$AQ,41,0)*8*50%-BA17 -> 0 | DS17: =VLOOKUP($D17,Att!B:CU,98,0)-O17 -> 0 | DT17: =IFERROR(VLOOKUP($D17,OT!$A:$BR,OT!BC$1,0),0)-P17 -> 0 | DU17: =IFERROR(VLOOKUP($D17,OT!$A:$BR,OT!BD$1,0),0)-Q17 -> 0 | DV17: =IFERROR(VLOOKUP($D17,OT!$A:$BR,OT!BE$1,0),0)-R17 -> 0 | DW17: =IFERROR(VLOOKUP($D17,OT!$A:$BR,OT!BF$1,0),0)-S17 -> 0 | DX17: =IFERROR(VLOOKUP($D17,OT!$A:$BR,OT!BG$1,0),0)-T17 -> 0 | DY17: =IFERROR(VLOOKUP($D17,OT!$A:$BR,OT!BH$1,0),0)-U17 -> 0 | DZ17: =IFERROR(VLOOKUP($D17,OT!$A:$BR,OT!BI$1,0),0)-V17 -> 0 | EA17: =IFERROR(VLOOKUP($D17,OT!$A:$BR,OT!BJ$1,0),0)-W17 -> 0 | EB17: =IFERROR(VLOOKUP($D17,OT!$A:$BR,OT!BK$1,0),0)-X17 -> 0 | EC17: =VLOOKUP(D17,'Off day working'!A:AL,38,0)*30000-BD17 -> 0 | EF17: =IF(G17="M",0-BE17,IF(G17="F",K17/208*1.5-BE17)) -> 0 | EG17: =4960000*1.07/208*VLOOKUP(D17,Att!B:BZ,77,0)-BJ17 -> 0 | EI17: =IF(AND(CH17="X",EJ17>=0.5),150000/VLOOKUP(D17,Att!B:AT,45,0)*VLOOKUP(D17,Att!B:AP,41,0),IF(AND(CH17="X",EJ17<0.5),0,150000))-AN17 -> 0 | EJ17: =VLOOKUP(D17,Att!B:AP,41,0)/VLOOKUP(D17,Att!B:AT,45,0) -> 0.78947368
